Workbook

Sheet Cover
B2: Bank of Aleppo Commercial (BAC) — Corporate Credit Model
B3: Borrower: Qalaa Olive & Laurel Industries LLC | Term Loan USD 2.4m + Revolver USD 0.9m
B4: Prepared by: Yamen Agha, Credit Analyst (portfolio case study) | Units: USD '000 unless stated
B6: DISCLAIMER | C6: All names, companies, the bank and every figure in this workbook are FICTIONAL and for illustration only. Bank of Aleppo Commercial is not a real bank; Qalaa Olive & Laurel Industries LLC is not a real company. Macro references describe the general post-2025 Syrian context. This is not a real credit decision or investment advice.
B8: Sheet | C8: What it does
B9: Dashboard | C9: Key outputs: facilities, DSCR by scenario, leverage, LTV, rating, checks, charts
B10: Assumptions | C10: All inputs: facility terms, projection drivers, scenario shocks (blue cells)
B11: IS / BS / CF | C11: Three years of historical statements (FY2023–FY2025) with FY2022 opening balance sheet; CF derived from BS movements
B12: Ratios | C12: Profitability, liquidity, leverage, coverage and efficiency ratios
B13: Debt_Schedule | C13: Term loan, revolver and existing loan schedules: balances, interest, principal
B14: Projections | C14: Five-year base case plus Downside, FX shock and Combined severe stress cases with DSCR and covenant tests
B15: Sensitivity | C15: FY2028 DSCR grid: sales decline x SYP depreciation, fully formula-driven
B16: Collateral | C16: Market values, haircuts, lending values, LTV and coverage
B17: Scorecard | C17: Internal risk rating scorecard (weighted factors -> BAC grade)
B18: Checks | C18: Integrity checks: balance sheet balances, cash ties, grid reconciles, loans repaid
B21: Colour code
B22: 1,000 | C22: Hard-coded input / assumption
B23: 1,000 | C23: Formula
B24: 1,000 | C24: Link to another sheet

Sheet Dashboard
A1: Dashboard – Key Credit Metrics
A2: Qalaa Olive & Laurel Industries LLC (fictional) | Bank of Aleppo Commercial (fictional) | USD '000
A4: Facilities
A5: Facility A – Term loan | B5: =Assumptions!$C$12 -> 2400
A6: Facility B – Revolver limit | B6: =Assumptions!$C$17 -> 900
A7: Total exposure | B7: =Assumptions!$C$12+Assumptions!$C$17 -> 3300
A8: Pro-forma Debt / EBITDA at drawdown | B8: =Scorecard!C8 -> 1.7254389
A9: LTV on market value | B9: =Collateral!C15 -> 0.39864641
A10: LTV on lending value | B10: =Collateral!C16 -> 0.72083683
A11: Collateral coverage | B11: =Collateral!C17 -> 1.3872765
A12: Internal rating | B12: =Scorecard!C27 -> 4
A13: Scorecard total | B13: =Scorecard!E22 -> 6.5
A14: All integrity checks pass | B14: =Checks!C16 -> ALL PASS
A16: DSCR by scenario
A17: Scenario | B17: FY2027 | C17: FY2028 | D17: FY2029 | E17: FY2030 | F17: FY2031 | G17: Minimum
A18: Base | B18: =Projections!D30 -> 3.0390471 | C18: =Projections!E30 -> 1.7735813 | D18: =Projections!F30 -> 2.6645642 | E18: =Projections!G30 -> 2.9830747 | F18: =Projections!H30 -> 3.3181605 | G18: =Projections!I30 -> 1.7735813
A19: Downside | B19: =Projections!D55 -> 2.4469773 | C19: =Projections!E55 -> 1.271525 | D19: =Projections!F55 -> 1.9212111 | E19: =Projections!G55 -> 2.1604047 | F19: =Projections!H55 -> 2.4159244 | G19: =Projections!I55 -> 1.271525
A20: FX shock | B20: =Projections!D80 -> 2.481905 | C20: =Projections!E80 -> 1.2864675 | D20: =Projections!F80 -> 1.963608 | E20: =Projections!G80 -> 2.1929108 | F20: =Projections!H80 -> 2.432405 | G20: =Projections!I80 -> 1.2864675
A21: Combined | B21: =Projections!D105 -> 1.6263219 | C21: =Projections!E105 -> 0.78037882 | D21: =Projections!F105 -> 1.2114563 | E21: =Projections!G105 -> 1.3470426 | F21: =Projections!H105 -> 1.4861509 | G21: =Projections!I105 -> 0.78037882
A22: Covenant minimum | B22: =Assumptions!$C$51 -> 1.25 | C22: =Assumptions!$C$51 -> 1.25 | D22: =Assumptions!$C$51 -> 1.25 | E22: =Assumptions!$C$51 -> 1.25 | F22: =Assumptions!$C$51 -> 1.25
A24: Base case revenue & EBITDA
A25: USD '000 | B25: FY2027 | C25: FY2028 | D25: FY2029 | E25: FY2030 | F25: FY2031
A26: Revenue | B26: =Projections!D15 -> 10898.92 | C26: =Projections!E15 -> 12206.79 | D26: =Projections!F15 -> 12931.569 | E26: =Projections!G15 -> 13578.147 | F26: =Projections!H15 -> 14121.273
A27: EBITDA | B27: =Projections!D19 -> 2440.2522 | C27: =Projections!E19 -> 2958.9524 | D27: =Projections!F19 -> 3110.8237 | E27: =Projections!G19 -> 3228.9515 | F27: =Projections!H19 -> 3304.2342
A28: Total debt (year end) | B28: =Debt_Schedule!D26 -> 3230 | C28: =Debt_Schedule!E26 -> 2430 | D28: =Debt_Schedule!F26 -> 1830 | E28: =Debt_Schedule!G26 -> 1230 | F28: =Debt_Schedule!H26 -> 630

Sheet Assumptions
A1: Assumptions & Inputs
A2: Blue cells are inputs. Change them and every sheet recalculates. USD '000.
A4: 1. General
A5: Corporate income tax rate (assumed) | B5: Illustrative effective rate | C5: 0.2
A6: Export share of revenue (projection) | B6: Gulf, Iraq, Jordan, EU | C6: 0.58
A7: Share of operating costs paid in SYP | B7: Wages, local services | C7: 0.65
A8: Net working capital, % of revenue | B8: FY2025 actual ~28% | C8: 0.27
A9: Maintenance capex, % of revenue | C9: 0.02
A11: 2. Proposed BAC facilities
A12: Facility A – Term loan amount | B12: Equipment + solar PV | C12: 2400
A13: Total project cost | B13: 75% debt / 25% sponsor equity | C13: 3200
A14: Facility A – all-in rate (3M Term SOFR 3.75% + 6.00%) | B14: Floor 9.25% | C14: 0.0975
A15: Facility A – principal grace (years) | B15: Interest-only in FY2027 | C15: 1
A16: Facility A – amortisation period (years) | B16: 16 equal quarterly instalments | C16: 4
A17: Facility B – Revolver limit | B17: Harvest stock + export receivables | C17: 900
A18: Facility B – all-in rate (3M Term SOFR 3.75% + 5.25%) | B18: Floor 8.75% | C18: 0.09
A19: Facility B – average utilisation | C19: 0.7
A20: Facility B – commitment fee on undrawn | C20: 0.005
A21: Arrangement fee (both facilities) | B21: Paid at signing | C21: 0.01
A22: DSRA – quarters of debt service held in cash | B22: Pledged to BAC | C22: 1
A24: 3. Existing debt (permitted)
A25: Existing term loan – balance at drawdown (end FY2026E) | B25: Other local lender | C25: 400
A26: Existing term loan – annual repayment | B26: Matures FY2028 | C26: 200
A27: Existing term loan – rate | C27: 0.1
A29: 4. Projection drivers (base case)
A30: Driver | B30: Note | C30: FY2026E | D30: FY2027 | E30: FY2028 | F30: FY2029 | G30: FY2030 | H30: FY2031
A31: Core revenue FY2026E (existing lines) | B31: 8M-2026 run-rate | C31: 9700
A32: Core revenue growth | B32: Volume + price | D32: 0.06 | E32: 0.06 | F32: 0.05 | G32: 0.05 | H32: 0.04
A33: New-line revenue uplift on core | B33: Ramp-up of bottling line | C33: 0 | D33: 0.06 | E33: 0.12 | F33: 0.13 | G33: 0.13 | H33: 0.13
A34: Raw materials, packaging & labour, % revenue | B34: Premium Gulf packaging | C34: 0.605 | D34: 0.61 | E34: 0.61 | F34: 0.61 | G34: 0.61 | H34: 0.61
A35: Energy cost, % revenue | B35: Solar PV from mid-FY2027 | C35: 0.088 | D35: 0.068 | E35: 0.053 | F35: 0.053 | G35: 0.053 | H35: 0.053
A36: Operating expenses FY2026E | C36: 990
A37: Operating expense growth | D37: 0.08 | E37: 0.08 | F37: 0.08 | G37: 0.08 | H37: 0.08
A38: D&A – existing asset base | C38: 380 | D38: 380 | E38: 380 | F38: 380 | G38: 380 | H38: 380
A39: Useful life of new equipment (years) | D39: 10 | E39: 10 | F39: 10 | G39: 10 | H39: 10
A41: 5. Stress scenarios (applied FY2027–FY2031)
A42: Shock parameter | B42: Note | C42: Base | D42: Downside | E42: FX shock | F42: Combined
A43: Sales volume change vs base | C43: 0 | D43: -0.1 | E43: 0 | F43: -0.15
A44: SYP depreciation vs USD | B44: +50% = USD/SYP rate rises 50% | C44: 0 | D44: 0 | E44: 0.5 | F44: 0.4
A45: Price pass-through of FX move (domestic) | B45: Share recovered via SYP price rises | C45: 0.5 | D45: 0.5 | E45: 0.5 | F45: 0.5
A46: Raw-material cost shock (pp of revenue) | C46: 0 | D46: 0.015 | E46: 0 | F46: 0.02
A47: Energy cost shock (pp of revenue) | B47: Grid tariff / diesel | C47: 0 | D47: 0.01 | E47: 0 | F47: 0.015
A48: Interest rate shock (pp) | C48: 0 | D48: 0.02 | E48: 0 | F48: 0.015
A50: 6. Covenant thresholds
A51: Minimum DSCR | C51: 1.25
A52: Maximum Total Debt / EBITDA | C52: 3
A53: Minimum current ratio | C53: 1.2
A54: Maximum Debt / Equity | C54: 1.5

Sheet IS
A1: Historical Income Statement
A2: Audited, FY ending 31 December. USD '000. Fictional.
A4: USD '000 | B4: Note | D4: FY2023 | E4: FY2024 | F4: FY2025
A5: Revenue | D5: 6180 | E5: 7420 | F5: 8860
A6: of which export share | D6: 0.48 | E6: 0.52 | F6: 0.55
A7: Raw materials & packaging | D7: -3460 | E7: -4085 | F7: -4785
A8: Direct labour | D8: -420 | E8: -480 | F8: -540
A9: Energy (diesel generators & grid) | D9: -690 | E9: -770 | F9: -805
A10: Gross profit | D10: =SUM(D5,D7:D9) -> 1610 | E10: =SUM(E5,E7:E9) -> 2085 | F10: =SUM(F5,F7:F9) -> 2730
A11: Selling, general & admin (incl. export logistics) | D11: -610 | E11: -745 | F11: -890
A12: EBITDA | D12: =D10+D11 -> 1000 | E12: =E10+E11 -> 1340 | F12: =F10+F11 -> 1840
A13: Depreciation & amortisation | D13: -300 | E13: -330 | F13: -360
A14: EBIT | D14: =D12+D13 -> 700 | E14: =E12+E13 -> 1010 | F14: =F12+F13 -> 1480
A15: Interest expense | D15: -170 | E15: -150 | F15: -125
A16: Net FX translation loss | D16: -60 | E16: -40 | F16: -20
A17: Profit before tax | D17: =D14+D15+D16 -> 470 | E17: =E14+E15+E16 -> 820 | F17: =F14+F15+F16 -> 1335
A18: Income tax | B18: PBT x tax rate | D18: =-D17*Assumptions!$C$5 -> -94 | E18: =-E17*Assumptions!$C$5 -> -164 | F18: =-F17*Assumptions!$C$5 -> -267
A19: Net income | D19: =D17+D18 -> 376 | E19: =E17+E18 -> 656 | F19: =F17+F18 -> 1068
A20: Dividends paid | D20: -80 | E20: -120 | F20: -220
A22: Margins
A23: Gross margin | D23: =D10/D5 -> 0.2605178 | E23: =E10/E5 -> 0.2809973 | F23: =F10/F5 -> 0.30812641
A24: EBITDA margin | D24: =D12/D5 -> 0.1618123 | E24: =E12/E5 -> 0.18059299 | F24: =F12/F5 -> 0.20767494
A25: Net margin | D25: =D19/D5 -> 0.060841424 | E25: =E19/E5 -> 0.088409704 | F25: =F19/F5 -> 0.12054176
A26: Revenue growth | E26: =E5/D5-1 -> 0.20064725 | F26: =F5/E5-1 -> 0.19407008

Sheet BS
A1: Historical Balance Sheet
A2: 31 December. FY2022 shown as opening position. Cash is linked from the cash flow statement. USD '000.
A4: USD '000 | B4: Note | C4: FY2022 | D4: FY2023 | E4: FY2024 | F4: FY2025
A5: Assets
A6: Cash & bank balances | B6: FY2023+ = CF closing cash | C6: 300 | D6: =CF!D26 -> 341 | E6: =CF!E26 -> 287 | F6: =CF!F26 -> 555
A7: Trade receivables | C7: 950 | D7: 1050 | E7: 1240 | F7: 1420
A8: Inventories (olive oil, olives, soap) | C8: 1500 | D8: 1640 | E8: 1880 | F8: 2120
A9: Prepayments & other current assets | C9: 150 | D9: 170 | E9: 190 | F9: 220
A10: Total current assets | C10: =SUM(C6:C9) -> 2900 | D10: =SUM(D6:D9) -> 3201 | E10: =SUM(E6:E9) -> 3597 | F10: =SUM(F6:F9) -> 4315
A11: Property, plant & equipment, net | B11: Prior + capex – D&A | C11: 2900 | D11: =C11-CF!D15+IS!D13 -> 2850 | E11: =D11-CF!E15+IS!E13 -> 2940 | F11: =E11-CF!F15+IS!F13 -> 2960
A12: TOTAL ASSETS | C12: =C10+C11 -> 5800 | D12: =D10+D11 -> 6051 | E12: =E10+E11 -> 6537 | F12: =F10+F11 -> 7275
A14: Liabilities & equity
A15: Trade payables | C15: 700 | D15: 770 | E15: 890 | F15: 990
A16: Accruals & tax payable | C16: 200 | D16: 235 | E16: 265 | F16: 305
A17: Short-term bank debt (to be refinanced by BAC revolver) | C17: 600 | D17: 650 | E17: 650 | F17: 600
A18: Total current liabilities | C18: =SUM(C15:C17) -> 1500 | D18: =SUM(D15:D17) -> 1655 | E18: =SUM(E15:E17) -> 1805 | F18: =SUM(F15:F17) -> 1895
A19: Long-term bank debt (incl. current portion) | C19: 1200 | D19: 1000 | E19: 800 | F19: 600
A20: Total liabilities | C20: =C18+C19 -> 2700 | D20: =D18+D19 -> 2655 | E20: =E18+E19 -> 2605 | F20: =F18+F19 -> 2495
A21: Share capital | C21: 2000 | D21: 2000 | E21: 2000 | F21: 2000
A22: Retained earnings | B22: Prior + NI – dividends | C22: 1100 | D22: =C22+IS!D19+IS!D20 -> 1396 | E22: =D22+IS!E19+IS!E20 -> 1932 | F22: =E22+IS!F19+IS!F20 -> 2780
A23: Total equity | C23: =C21+C22 -> 3100 | D23: =D21+D22 -> 3396 | E23: =E21+E22 -> 3932 | F23: =F21+F22 -> 4780
A24: TOTAL LIABILITIES & EQUITY | C24: =C20+C23 -> 5800 | D24: =D20+D23 -> 6051 | E24: =E20+E23 -> 6537 | F24: =F20+F23 -> 7275
A26: Balance check (assets – L&E) | C26: =ROUND(C12-C24,6) -> 0 | D26: =ROUND(D12-D24,6) -> 0 | E26: =ROUND(E12-E24,6) -> 0 | F26: =ROUND(F12-F24,6) -> 0
A27: Total bank debt | C27: =C17+C19 -> 1800 | D27: =D17+D19 -> 1650 | E27: =E17+E19 -> 1450 | F27: =F17+F19 -> 1200
A28: Net working capital (ex cash, ex debt) | C28: =C7+C8+C9-C15-C16 -> 1700 | D28: =D7+D8+D9-D15-D16 -> 1855 | E28: =E7+E8+E9-E15-E16 -> 2155 | F28: =F7+F8+F9-F15-F16 -> 2465

Sheet CF
A1: Historical Cash Flow Statement (indirect)
A2: Derived from income statement and balance sheet movements. USD '000.
A4: USD '000 | B4: Note | D4: FY2023 | E4: FY2024 | F4: FY2025
A5: Operating activities
A6: Net income | D6: =IS!D19 -> 376 | E6: =IS!E19 -> 656 | F6: =IS!F19 -> 1068
A7: Add back: D&A | D7: =-IS!D13 -> 300 | E7: =-IS!E13 -> 330 | F7: =-IS!F13 -> 360
A8: (Increase) / decrease in receivables | D8: =BS!C7-BS!D7 -> -100 | E8: =BS!D7-BS!E7 -> -190 | F8: =BS!E7-BS!F7 -> -180
A9: (Increase) / decrease in inventories | D9: =BS!C8-BS!D8 -> -140 | E9: =BS!D8-BS!E8 -> -240 | F9: =BS!E8-BS!F8 -> -240
A10: (Increase) / decrease in other current assets | D10: =BS!C9-BS!D9 -> -20 | E10: =BS!D9-BS!E9 -> -20 | F10: =BS!E9-BS!F9 -> -30
A11: Increase / (decrease) in payables | D11: =BS!D15-BS!C15 -> 70 | E11: =BS!E15-BS!D15 -> 120 | F11: =BS!F15-BS!E15 -> 100
A12: Increase / (decrease) in accruals | D12: =BS!D16-BS!C16 -> 35 | E12: =BS!E16-BS!D16 -> 30 | F12: =BS!F16-BS!E16 -> 40
A13: Cash flow from operations | D13: =SUM(D6:D12) -> 521 | E13: =SUM(E6:E12) -> 686 | F13: =SUM(F6:F12) -> 1118
A14: Investing activities
A15: Capital expenditure | D15: -250 | E15: -420 | F15: -380
A16: Cash flow from investing | D16: =D15 -> -250 | E16: =E15 -> -420 | F16: =F15 -> -380
A17: Financing activities
A18: Net change in short-term bank debt | D18: =BS!D17-BS!C17 -> 50 | E18: =BS!E17-BS!D17 -> 0 | F18: =BS!F17-BS!E17 -> -50
A19: Net change in long-term debt | D19: =BS!D19-BS!C19 -> -200 | E19: =BS!E19-BS!D19 -> -200 | F19: =BS!F19-BS!E19 -> -200
A20: Dividends paid | D20: =IS!D20 -> -80 | E20: =IS!E20 -> -120 | F20: =IS!F20 -> -220
A21: Share capital issued | D21: =BS!D21-BS!C21 -> 0 | E21: =BS!E21-BS!D21 -> 0 | F21: =BS!F21-BS!E21 -> 0
A22: Cash flow from financing | D22: =SUM(D18:D21) -> -230 | E22: =SUM(E18:E21) -> -320 | F22: =SUM(F18:F21) -> -470
A24: Net change in cash | D24: =D13+D16+D22 -> 41 | E24: =E13+E16+E22 -> -54 | F24: =F13+F16+F22 -> 268
A25: Opening cash | D25: =BS!C6 -> 300 | E25: =BS!D6 -> 341 | F25: =BS!E6 -> 287
A26: Closing cash | D26: =D25+D24 -> 341 | E26: =E25+E24 -> 287 | F26: =F25+F24 -> 555
A28: Free cash flow (CFO + capex) | D28: =D13+D15 -> 271 | E28: =E13+E15 -> 266 | F28: =F13+F15 -> 738
A29: Cash tie-out (CF closing – BS cash) | D29: =ROUND(D26-BS!D6,6) -> 0 | E29: =ROUND(E26-BS!E6,6) -> 0 | F29: =ROUND(F26-BS!F6,6) -> 0

Sheet Ratios
A1: Ratio Analysis
A2: Calculated from IS / BS / CF. Average balances not used (year-end basis) for simplicity.
A4: Ratio | B4: Formula | D4: FY2023 | E4: FY2024 | F4: FY2025
A5: Profitability
A6: Gross margin | B6: Gross profit / Revenue | D6: =IS!D10/IS!D5 -> 0.2605178 | E6: =IS!E10/IS!E5 -> 0.2809973 | F6: =IS!F10/IS!F5 -> 0.30812641
A7: EBITDA margin | B7: EBITDA / Revenue | D7: =IS!D12/IS!D5 -> 0.1618123 | E7: =IS!E12/IS!E5 -> 0.18059299 | F7: =IS!F12/IS!F5 -> 0.20767494
A8: Net margin | B8: Net income / Revenue | D8: =IS!D19/IS!D5 -> 0.060841424 | E8: =IS!E19/IS!E5 -> 0.088409704 | F8: =IS!F19/IS!F5 -> 0.12054176
A9: Return on assets | B9: Net income / Total assets | D9: =IS!D19/BS!D12 -> 0.06213849 | E9: =IS!E19/BS!E12 -> 0.10035184 | F9: =IS!F19/BS!F12 -> 0.14680412
A10: Return on equity | B10: Net income / Total equity | D10: =IS!D19/BS!D23 -> 0.11071849 | E10: =IS!E19/BS!E23 -> 0.16683622 | F10: =IS!F19/BS!F23 -> 0.22343096
A11: Liquidity
A12: Current ratio | B12: Current assets / Current liabilities | D12: =BS!D10/BS!D18 -> 1.934139 | E12: =BS!E10/BS!E18 -> 1.9927978 | F12: =BS!F10/BS!F18 -> 2.2770449
A13: Quick ratio | B13: (Current assets – Inventory) / CL | D13: =(BS!D10-BS!D8)/BS!D18 -> 0.94320242 | E13: =(BS!E10-BS!E8)/BS!E18 -> 0.95124654 | F13: =(BS!F10-BS!F8)/BS!F18 -> 1.1583113
A14: Cash ratio | B14: Cash / Current liabilities | D14: =BS!D6/BS!D18 -> 0.2060423 | E14: =BS!E6/BS!E18 -> 0.15900277 | F14: =BS!F6/BS!F18 -> 0.29287599
A15: Leverage
A16: Debt / Equity | B16: Total bank debt / Equity | D16: =BS!D27/BS!D23 -> 0.48586572 | E16: =BS!E27/BS!E23 -> 0.36876907 | F16: =BS!F27/BS!F23 -> 0.25104603
A17: Total Debt / EBITDA | B17: Total bank debt / EBITDA | D17: =BS!D27/IS!D12 -> 1.65 | E17: =BS!E27/IS!E12 -> 1.0820896 | F17: =BS!F27/IS!F12 -> 0.65217391
A18: Net Debt / EBITDA | B18: (Debt – Cash) / EBITDA | D18: =(BS!D27-BS!D6)/IS!D12 -> 1.309 | E18: =(BS!E27-BS!E6)/IS!E12 -> 0.86791045 | F18: =(BS!F27-BS!F6)/IS!F12 -> 0.35054348
A19: Liabilities / Total assets | B19: Total liabilities / Total assets | D19: =BS!D20/BS!D12 -> 0.43877045 | E19: =BS!E20/BS!E12 -> 0.39850084 | F19: =BS!F20/BS!F12 -> 0.34295533
A20: Coverage
A21: Interest cover (EBITDA) | B21: EBITDA / Interest | D21: =IS!D12/-IS!D15 -> 5.8823529 | E21: =IS!E12/-IS!E15 -> 8.9333333 | F21: =IS!F12/-IS!F15 -> 14.72
A22: Interest cover (EBIT) | B22: EBIT / Interest | D22: =IS!D14/-IS!D15 -> 4.1176471 | E22: =IS!E14/-IS!E15 -> 6.7333333 | F22: =IS!F14/-IS!F15 -> 11.84
A23: Historical DSCR | B23: (EBITDA – tax – maint. capex) / (interest + LT principal) | D23: =(IS!D12+IS!D18-Assumptions!$C$9*IS!D5)/(-IS!D15+200) -> 2.1145946 | E23: =(IS!E12+IS!E18-Assumptions!$C$9*IS!E5)/(-IS!E15+200) -> 2.936 | F23: =(IS!F12+IS!F18-Assumptions!$C$9*IS!F5)/(-IS!F15+200) -> 4.2947692
A24: Efficiency
A25: Days sales outstanding (DSO) | B25: Receivables / Revenue x 365 | D25: =BS!D7/IS!D5*365 -> 62.014563 | E25: =BS!E7/IS!E5*365 -> 60.997305 | F25: =BS!F7/IS!F5*365 -> 58.498871
A26: Days inventory outstanding (DIO) | B26: Inventory / COGS x 365 | D26: =BS!D8/-(IS!D7+IS!D8+IS!D9)*365 -> 130.98468 | E26: =BS!E8/-(IS!E7+IS!E8+IS!E9)*365 -> 128.62231 | F26: =BS!F8/-(IS!F7+IS!F8+IS!F9)*365 -> 126.23165
A27: Days payables outstanding (DPO) | B27: Payables / COGS x 365 | D27: =BS!D15/-(IS!D7+IS!D8+IS!D9)*365 -> 61.498906 | E27: =BS!E15/-(IS!E7+IS!E8+IS!E9)*365 -> 60.890347 | F27: =BS!F15/-(IS!F7+IS!F8+IS!F9)*365 -> 58.947798
A28: Cash conversion cycle | B28: DSO + DIO – DPO | D28: =D25+D26-D27 -> 131.50034 | E28: =E25+E26-E27 -> 128.72926 | F28: =F25+F26-F27 -> 125.78272
A29: Asset turnover | B29: Revenue / Total assets | D29: =IS!D5/BS!D12 -> 1.0213188 | E29: =IS!E5/BS!E12 -> 1.1350773 | F29: =IS!F5/BS!F12 -> 1.2178694
A30: Net working capital / Revenue | B30: NWC / Revenue | D30: =BS!D28/IS!D5 -> 0.30016181 | E30: =BS!E28/IS!E5 -> 0.29043127 | F30: =BS!F28/IS!F5 -> 0.2782167
A31: Cash conversion (CFO / Net income) | B31: CFO / Net income | D31: =CF!D13/IS!D19 -> 1.3856383 | E31: =CF!E13/IS!E19 -> 1.0457317 | F31: =CF!F13/IS!F19 -> 1.0468165

Sheet Debt_Schedule
A1: Debt Schedule
A2: Facility A drawn Nov-2026 (end FY2026E). Interest on opening balance (conservative). USD '000.
A4: USD '000 | B4: Note | C4: FY2026E | D4: FY2027 | E4: FY2028 | F4: FY2029 | G4: FY2030 | H4: FY2031
A5: Year index | C5: 0 | D5: 1 | E5: 2 | F5: 3 | G5: 4 | H5: 5
A6: Facility A – Term loan
A7: Opening balance | C7: 0 | D7: =C10 -> 2400 | E7: =D10 -> 2400 | F7: =E10 -> 1800 | G7: =F10 -> 1200 | H7: =G10 -> 600
A8: Drawdown | C8: =Assumptions!$C$12 -> 2400 | D8: 0 | E8: 0 | F8: 0 | G8: 0 | H8: 0
A9: Scheduled repayment | B9: Grace then straight-line | C9: 0 | D9: =IF(D5<=Assumptions!$C$15,0,MIN(D7,Assumptions!$C$12/Assumptions!$C$16)) -> 0 | E9: =IF(E5<=Assumptions!$C$15,0,MIN(E7,Assumptions!$C$12/Assumptions!$C$16)) -> 600 | F9: =IF(F5<=Assumptions!$C$15,0,MIN(F7,Assumptions!$C$12/Assumptions!$C$16)) -> 600 | G9: =IF(G5<=Assumptions!$C$15,0,MIN(G7,Assumptions!$C$12/Assumptions!$C$16)) -> 600 | H9: =IF(H5<=Assumptions!$C$15,0,MIN(H7,Assumptions!$C$12/Assumptions!$C$16)) -> 600
A10: Closing balance | C10: =C7+C8-C9 -> 2400 | D10: =D7+D8-D9 -> 2400 | E10: =E7+E8-E9 -> 1800 | F10: =F7+F8-F9 -> 1200 | G10: =G7+G8-G9 -> 600 | H10: =H7+H8-H9 -> 0
A11: Interest (opening x rate) | D11: =D7*Assumptions!$C$14 -> 234 | E11: =E7*Assumptions!$C$14 -> 234 | F11: =F7*Assumptions!$C$14 -> 175.5 | G11: =G7*Assumptions!$C$14 -> 117 | H11: =H7*Assumptions!$C$14 -> 58.5
A12: Facility B – Revolving credit facility
A13: Average drawn balance | B13: Limit x utilisation | C13: =Assumptions!$C$17*Assumptions!$C$19 -> 630 | D13: =Assumptions!$C$17*Assumptions!$C$19 -> 630 | E13: =Assumptions!$C$17*Assumptions!$C$19 -> 630 | F13: =Assumptions!$C$17*Assumptions!$C$19 -> 630 | G13: =Assumptions!$C$17*Assumptions!$C$19 -> 630 | H13: =Assumptions!$C$17*Assumptions!$C$19 -> 630
A14: Interest on drawn | D14: =D13*Assumptions!$C$18 -> 56.7 | E14: =E13*Assumptions!$C$18 -> 56.7 | F14: =F13*Assumptions!$C$18 -> 56.7 | G14: =G13*Assumptions!$C$18 -> 56.7 | H14: =H13*Assumptions!$C$18 -> 56.7
A15: Commitment fee on undrawn | D15: =(Assumptions!$C$17-D13)*Assumptions!$C$20 -> 1.35 | E15: =(Assumptions!$C$17-E13)*Assumptions!$C$20 -> 1.35 | F15: =(Assumptions!$C$17-F13)*Assumptions!$C$20 -> 1.35 | G15: =(Assumptions!$C$17-G13)*Assumptions!$C$20 -> 1.35 | H15: =(Assumptions!$C$17-H13)*Assumptions!$C$20 -> 1.35
A16: Existing term loan (other lender)
A17: Opening balance | D17: =C19 -> 400 | E17: =D19 -> 200 | F17: =E19 -> 0 | G17: =F19 -> 0 | H17: =G19 -> 0
A18: Repayment | D18: =MIN(D17,Assumptions!$C$26) -> 200 | E18: =MIN(E17,Assumptions!$C$26) -> 200 | F18: =MIN(F17,Assumptions!$C$26) -> 0 | G18: =MIN(G17,Assumptions!$C$26) -> 0 | H18: =MIN(H17,Assumptions!$C$26) -> 0
A19: Closing balance | C19: =Assumptions!$C$25 -> 400 | D19: =D17-D18 -> 200 | E19: =E17-E18 -> 0 | F19: =F17-F18 -> 0 | G19: =G17-G18 -> 0 | H19: =H17-H18 -> 0
A20: Interest (opening x rate) | D20: =D17*Assumptions!$C$27 -> 40 | E20: =E17*Assumptions!$C$27 -> 20 | F20: =F17*Assumptions!$C$27 -> 0 | G20: =G17*Assumptions!$C$27 -> 0 | H20: =H17*Assumptions!$C$27 -> 0
A21: Totals
A22: Total interest & fees | D22: =D11+D14+D15+D20 -> 332.05 | E22: =E11+E14+E15+E20 -> 312.05 | F22: =F11+F14+F15+F20 -> 233.55 | G22: =G11+G14+G15+G20 -> 175.05 | H22: =H11+H14+H15+H20 -> 116.55
A23: Total scheduled principal | D23: =D9+D18 -> 200 | E23: =E9+E18 -> 800 | F23: =F9+F18 -> 600 | G23: =G9+G18 -> 600 | H23: =H9+H18 -> 600
A24: Total debt service (base rates) | D24: =D22+D23 -> 532.05 | E24: =E22+E23 -> 1112.05 | F24: =F22+F23 -> 833.55 | G24: =G22+G23 -> 775.05 | H24: =H22+H23 -> 716.55
A25: Interest-bearing base for rate shocks | B25: TL open + RCF drawn + existing open | D25: =D7+D13+D17 -> 3430 | E25: =E7+E13+E17 -> 3230 | F25: =F7+F13+F17 -> 2430 | G25: =G7+G13+G17 -> 1830 | H25: =H7+H13+H17 -> 1230
A26: Total debt at year end | B26: TL + RCF drawn + existing | C26: =C10+C13+C19 -> 3430 | D26: =D10+D13+D19 -> 3230 | E26: =E10+E13+E19 -> 2430 | F26: =F10+F13+F19 -> 1830 | G26: =G10+G13+G19 -> 1230 | H26: =H10+H13+H19 -> 630
A27: DSRA requirement (max annual DS / 4 x quarters) | C27: =MAX(D24:H24)/4*Assumptions!$C$22 -> 278.0125

Sheet Projections
A1: Five-Year Projections, DSCR & Stress Tests
A2: Base case plus three stress cases. Shocks from Assumptions section 5. USD '000.
A4: USD '000 | B4: Note | C4: FY2026E | D4: FY2027 | E4: FY2028 | F4: FY2029 | G4: FY2030 | H4: FY2031 | I4: Min / Max
A5: Base revenue & cost build (before shocks)
A6: Core revenue | C6: =Assumptions!C31 -> 9700 | D6: =C6*(1+Assumptions!D32) -> 10282 | E6: =D6*(1+Assumptions!E32) -> 10898.92 | F6: =E6*(1+Assumptions!F32) -> 11443.866 | G6: =F6*(1+Assumptions!G32) -> 12016.059 | H6: =G6*(1+Assumptions!H32) -> 12496.702
A7: Base revenue incl. new-line uplift | C7: =C6*(1+Assumptions!C33) -> 9700 | D7: =D6*(1+Assumptions!D33) -> 10898.92 | E7: =E6*(1+Assumptions!E33) -> 12206.79 | F7: =F6*(1+Assumptions!F33) -> 12931.569 | G7: =G6*(1+Assumptions!G33) -> 13578.147 | H7: =H6*(1+Assumptions!H33) -> 14121.273
A8: Base operating expenses | C8: =Assumptions!C36 -> 990 | D8: =C8*(1+Assumptions!D37) -> 1069.2 | E8: =D8*(1+Assumptions!E37) -> 1154.736 | F8: =E8*(1+Assumptions!F37) -> 1247.1149 | G8: =F8*(1+Assumptions!G37) -> 1346.8841 | H8: =G8*(1+Assumptions!H37) -> 1454.6348
A9: Depreciation (existing + new equipment) | C9: =Assumptions!C38 -> 380 | D9: =Assumptions!D38+Assumptions!$C$13/Assumptions!D39 -> 700 | E9: =Assumptions!E38+Assumptions!$C$13/Assumptions!E39 -> 700 | F9: =Assumptions!F38+Assumptions!$C$13/Assumptions!F39 -> 700 | G9: =Assumptions!G38+Assumptions!$C$13/Assumptions!G39 -> 700 | H9: =Assumptions!H38+Assumptions!$C$13/Assumptions!H39 -> 700
A10: FY2026E EBITDA (management estimate basis) | C10: =C7*(1-Assumptions!C34-Assumptions!C35)-C8 -> 1987.9
A12: Scenario: Base
A13: FX factor on SYP-priced items | B13: (1 + pass-through x dep) / (1 + dep) | D13: =(1+Assumptions!$C$45*Assumptions!$C$44)/(1+Assumptions!$C$44) -> 1 | E13: =(1+Assumptions!$C$45*Assumptions!$C$44)/(1+Assumptions!$C$44) -> 1 | F13: =(1+Assumptions!$C$45*Assumptions!$C$44)/(1+Assumptions!$C$44) -> 1 | G13: =(1+Assumptions!$C$45*Assumptions!$C$44)/(1+Assumptions!$C$44) -> 1 | H13: =(1+Assumptions!$C$45*Assumptions!$C$44)/(1+Assumptions!$C$44) -> 1
A14: Volume-adjusted revenue | B14: Base x (1 + sales shock) | D14: =D7*(1+Assumptions!$C$43) -> 10898.92 | E14: =E7*(1+Assumptions!$C$43) -> 12206.79 | F14: =F7*(1+Assumptions!$C$43) -> 12931.569 | G14: =G7*(1+Assumptions!$C$43) -> 13578.147 | H14: =H7*(1+Assumptions!$C$43) -> 14121.273
A15: Revenue (USD) | B15: Export + domestic x FX factor | D15: =D14*(Assumptions!$C$6+(1-Assumptions!$C$6)*D13) -> 10898.92 | E15: =E14*(Assumptions!$C$6+(1-Assumptions!$C$6)*E13) -> 12206.79 | F15: =F14*(Assumptions!$C$6+(1-Assumptions!$C$6)*F13) -> 12931.569 | G15: =G14*(Assumptions!$C$6+(1-Assumptions!$C$6)*G13) -> 13578.147 | H15: =H14*(Assumptions!$C$6+(1-Assumptions!$C$6)*H13) -> 14121.273
A16: Raw materials, packaging & labour | B16: USD-linked; on volume | D16: =-D14*(Assumptions!D34+Assumptions!$C$46) -> -6648.3412 | E16: =-E14*(Assumptions!E34+Assumptions!$C$46) -> -7446.1421 | F16: =-F14*(Assumptions!F34+Assumptions!$C$46) -> -7888.2568 | G16: =-G14*(Assumptions!G34+Assumptions!$C$46) -> -8282.6697 | H16: =-H14*(Assumptions!H34+Assumptions!$C$46) -> -8613.9765
A17: Energy | D17: =-D14*(Assumptions!D35+Assumptions!$C$47) -> -741.12656 | E17: =-E14*(Assumptions!E35+Assumptions!$C$47) -> -646.95989 | F17: =-F14*(Assumptions!F35+Assumptions!$C$47) -> -685.37313 | G17: =-G14*(Assumptions!G35+Assumptions!$C$47) -> -719.64179 | H17: =-H14*(Assumptions!H35+Assumptions!$C$47) -> -748.42746
A18: Operating expenses | B18: SYP share x FX factor | D18: =-D8*((1-Assumptions!$C$7)+Assumptions!$C$7*D13) -> -1069.2 | E18: =-E8*((1-Assumptions!$C$7)+Assumptions!$C$7*E13) -> -1154.736 | F18: =-F8*((1-Assumptions!$C$7)+Assumptions!$C$7*F13) -> -1247.1149 | G18: =-G8*((1-Assumptions!$C$7)+Assumptions!$C$7*G13) -> -1346.8841 | H18: =-H8*((1-Assumptions!$C$7)+Assumptions!$C$7*H13) -> -1454.6348
A19: EBITDA | D19: =SUM(D15:D18) -> 2440.2522 | E19: =SUM(E15:E18) -> 2958.9524 | F19: =SUM(F15:F18) -> 3110.8237 | G19: =SUM(G15:G18) -> 3228.9515 | H19: =SUM(H15:H18) -> 3304.2342 | I19: =MIN(D19:H19) -> 2440.2522
A20: EBITDA margin | D20: =D19/D15 -> 0.22389854 | E20: =E19/E15 -> 0.24240216 | F20: =F19/F15 -> 0.24056043 | G20: =G19/G15 -> 0.23780502 | H20: =H19/H15 -> 0.23398982
A21: Interest & fees | B21: Base + rate shock x debt | D21: =Debt_Schedule!D22+Assumptions!$C$48*Debt_Schedule!D25 -> 332.05 | E21: =Debt_Schedule!E22+Assumptions!$C$48*Debt_Schedule!E25 -> 312.05 | F21: =Debt_Schedule!F22+Assumptions!$C$48*Debt_Schedule!F25 -> 233.55 | G21: =Debt_Schedule!G22+Assumptions!$C$48*Debt_Schedule!G25 -> 175.05 | H21: =Debt_Schedule!H22+Assumptions!$C$48*Debt_Schedule!H25 -> 116.55
A22: Profit before tax | D22: =D19-D9-D21 -> 1408.2022 | E22: =E19-E9-E21 -> 1946.9024 | F22: =F19-F9-F21 -> 2177.2737 | G22: =G19-G9-G21 -> 2353.9015 | H22: =H19-H9-H21 -> 2487.6842
A23: Cash tax | B23: MAX(0, PBT x rate) | D23: =MAX(0,D22*Assumptions!$C$5) -> 281.64045 | E23: =MAX(0,E22*Assumptions!$C$5) -> 389.38047 | F23: =MAX(0,F22*Assumptions!$C$5) -> 435.45475 | G23: =MAX(0,G22*Assumptions!$C$5) -> 470.78029 | H23: =MAX(0,H22*Assumptions!$C$5) -> 497.53683
A24: Net income | D24: =D22-D23 -> 1126.5618 | E24: =E22-E23 -> 1557.5219 | F24: =F22-F23 -> 1741.819 | G24: =G22-G23 -> 1883.1212 | H24: =H22-H23 -> 1990.1473
A25: Maintenance capex | B25: % of revenue | D25: =Assumptions!$C$9*D15 -> 217.9784 | E25: =Assumptions!$C$9*E15 -> 244.13581 | F25: =Assumptions!$C$9*F15 -> 258.63137 | G25: =Assumptions!$C$9*G15 -> 271.56294 | H25: =Assumptions!$C$9*H15 -> 282.42546
A26: Increase in net working capital | B26: MAX(0, NWC% x revenue growth) | D26: =MAX(0,Assumptions!$C$8*(D15-$C$7)) -> 323.7084 | E26: =MAX(0,Assumptions!$C$8*(E15-D15)) -> 353.12501 | F26: =MAX(0,Assumptions!$C$8*(F15-E15)) -> 195.69011 | G26: =MAX(0,Assumptions!$C$8*(G15-F15)) -> 174.57618 | H26: =MAX(0,Assumptions!$C$8*(H15-G15)) -> 146.64399
A27: Cash flow available for debt service (CFADS) | B27: EBITDA – tax – capex – ΔNWC | D27: =D19-D23-D25-D26 -> 1616.925 | E27: =E19-E23-E25-E26 -> 1972.3111 | F27: =F19-F23-F25-F26 -> 2221.0475 | G27: =G19-G23-G25-G26 -> 2312.0321 | H27: =H19-H23-H25-H26 -> 2377.6279
A28: Scheduled principal | D28: =Debt_Schedule!D23 -> 200 | E28: =Debt_Schedule!E23 -> 800 | F28: =Debt_Schedule!F23 -> 600 | G28: =Debt_Schedule!G23 -> 600 | H28: =Debt_Schedule!H23 -> 600
A29: Total debt service | B29: Interest & fees + principal | D29: =D21+D28 -> 532.05 | E29: =E21+E28 -> 1112.05 | F29: =F21+F28 -> 833.55 | G29: =G21+G28 -> 775.05 | H29: =H21+H28 -> 716.55
A30: DSCR | B30: CFADS / debt service | D30: =D27/D29 -> 3.0390471 | E30: =E27/E29 -> 1.7735813 | F30: =F27/F29 -> 2.6645642 | G30: =G27/G29 -> 2.9830747 | H30: =H27/H29 -> 3.3181605 | I30: =MIN(D30:H30) -> 1.7735813
A31: CFADS headroom before DSCR = 1.0x | B31: 1 – 1/DSCR | D31: =1-1/D30 -> 0.67094949 | E31: =1-1/E30 -> 0.43616906 | F31: =1-1/F30 -> 0.62470411 | G31: =1-1/G30 -> 0.66477541 | H31: =1-1/H30 -> 0.6986282
A32: Total Debt / EBITDA | B32: Year-end debt / EBITDA | D32: =Debt_Schedule!D26/D19 -> 1.3236337 | E32: =Debt_Schedule!E26/E19 -> 0.82123661 | F32: =Debt_Schedule!F26/F19 -> 0.58826863 | G32: =Debt_Schedule!G26/G19 -> 0.38092861 | H32: =Debt_Schedule!H26/H19 -> 0.19066445 | I32: =MAX(D32:H32) -> 1.3236337
A33: Cumulative cash after debt service | D33: =0+D27-D29 -> 1084.875 | E33: =D33+E27-E29 -> 1945.1361 | F33: =E33+F27-F29 -> 3332.6336 | G33: =F33+G27-G29 -> 4869.6156 | H33: =G33+H27-H29 -> 6530.6935
A34: Covenant: DSCR ≥ minimum | D34: =IF(D30>=Assumptions!$C$51,"PASS","BREACH") -> PASS | E34: =IF(E30>=Assumptions!$C$51,"PASS","BREACH") -> PASS | F34: =IF(F30>=Assumptions!$C$51,"PASS","BREACH") -> PASS | G34: =IF(G30>=Assumptions!$C$51,"PASS","BREACH") -> PASS | H34: =IF(H30>=Assumptions!$C$51,"PASS","BREACH") -> PASS
A35: Covenant: Debt/EBITDA ≤ maximum | D35: =IF(D32<=Assumptions!$C$52,"PASS","BREACH") -> PASS | E35: =IF(E32<=Assumptions!$C$52,"PASS","BREACH") -> PASS | F35: =IF(F32<=Assumptions!$C$52,"PASS","BREACH") -> PASS | G35: =IF(G32<=Assumptions!$C$52,"PASS","BREACH") -> PASS | H35: =IF(H32<=Assumptions!$C$52,"PASS","BREACH") -> PASS
A37: Scenario: Downside
A38: FX factor on SYP-priced items | B38: (1 + pass-through x dep) / (1 + dep) | D38: =(1+Assumptions!$D$45*Assumptions!$D$44)/(1+Assumptions!$D$44) -> 1 | E38: =(1+Assumptions!$D$45*Assumptions!$D$44)/(1+Assumptions!$D$44) -> 1 | F38: =(1+Assumptions!$D$45*Assumptions!$D$44)/(1+Assumptions!$D$44) -> 1 | G38: =(1+Assumptions!$D$45*Assumptions!$D$44)/(1+Assumptions!$D$44) -> 1 | H38: =(1+Assumptions!$D$45*Assumptions!$D$44)/(1+Assumptions!$D$44) -> 1
A39: Volume-adjusted revenue | B39: Base x (1 + sales shock) | D39: =D7*(1+Assumptions!$D$43) -> 9809.028 | E39: =E7*(1+Assumptions!$D$43) -> 10986.111 | F39: =F7*(1+Assumptions!$D$43) -> 11638.412 | G39: =G7*(1+Assumptions!$D$43) -> 12220.332 | H39: =H7*(1+Assumptions!$D$43) -> 12709.146
A40: Revenue (USD) | B40: Export + domestic x FX factor | D40: =D39*(Assumptions!$C$6+(1-Assumptions!$C$6)*D38) -> 9809.028 | E40: =E39*(Assumptions!$C$6+(1-Assumptions!$C$6)*E38) -> 10986.111 | F40: =F39*(Assumptions!$C$6+(1-Assumptions!$C$6)*F38) -> 11638.412 | G40: =G39*(Assumptions!$C$6+(1-Assumptions!$C$6)*G38) -> 12220.332 | H40: =H39*(Assumptions!$C$6+(1-Assumptions!$C$6)*H38) -> 12709.146
A41: Raw materials, packaging & labour | B41: USD-linked; on volume | D41: =-D39*(Assumptions!D34+Assumptions!$D$46) -> -6130.6425 | E41: =-E39*(Assumptions!E34+Assumptions!$D$46) -> -6866.3196 | F41: =-F39*(Assumptions!F34+Assumptions!$D$46) -> -7274.0073 | G41: =-G39*(Assumptions!G34+Assumptions!$D$46) -> -7637.7077 | H41: =-H39*(Assumptions!H34+Assumptions!$D$46) -> -7943.216
A42: Energy | D42: =-D39*(Assumptions!D35+Assumptions!$D$47) -> -765.10418 | E42: =-E39*(Assumptions!E35+Assumptions!$D$47) -> -692.12502 | F42: =-F39*(Assumptions!F35+Assumptions!$D$47) -> -733.21994 | G42: =-G39*(Assumptions!G35+Assumptions!$D$47) -> -769.88094 | H42: =-H39*(Assumptions!H35+Assumptions!$D$47) -> -800.67617
A43: Operating expenses | B43: SYP share x FX factor | D43: =-D8*((1-Assumptions!$C$7)+Assumptions!$C$7*D38) -> -1069.2 | E43: =-E8*((1-Assumptions!$C$7)+Assumptions!$C$7*E38) -> -1154.736 | F43: =-F8*((1-Assumptions!$C$7)+Assumptions!$C$7*F38) -> -1247.1149 | G43: =-G8*((1-Assumptions!$C$7)+Assumptions!$C$7*G38) -> -1346.8841 | H43: =-H8*((1-Assumptions!$C$7)+Assumptions!$C$7*H38) -> -1454.6348
A44: EBITDA | D44: =SUM(D40:D43) -> 1844.0813 | E44: =SUM(E40:E43) -> 2272.9307 | F44: =SUM(F40:F43) -> 2384.0696 | G44: =SUM(G40:G43) -> 2465.8596 | H44: =SUM(H40:H43) -> 2510.6186 | I44: =MIN(D44:H44) -> 1844.0813
A45: EBITDA margin | D45: =D44/D40 -> 0.18799837 | E45: =E44/E40 -> 0.20689129 | F45: =F44/F40 -> 0.20484493 | G45: =G44/G40 -> 0.20178335 | H45: =H44/H40 -> 0.19754425
A46: Interest & fees | B46: Base + rate shock x debt | D46: =Debt_Schedule!D22+Assumptions!$D$48*Debt_Schedule!D25 -> 400.65 | E46: =Debt_Schedule!E22+Assumptions!$D$48*Debt_Schedule!E25 -> 376.65 | F46: =Debt_Schedule!F22+Assumptions!$D$48*Debt_Schedule!F25 -> 282.15 | G46: =Debt_Schedule!G22+Assumptions!$D$48*Debt_Schedule!G25 -> 211.65 | H46: =Debt_Schedule!H22+Assumptions!$D$48*Debt_Schedule!H25 -> 141.15
A47: Profit before tax | D47: =D44-D9-D46 -> 743.43132 | E47: =E44-E9-E46 -> 1196.2807 | F47: =F44-F9-F46 -> 1401.9196 | G47: =G44-G9-G46 -> 1554.2096 | H47: =H44-H9-H46 -> 1669.4686
A48: Cash tax | B48: MAX(0, PBT x rate) | D48: =MAX(0,D47*Assumptions!$C$5) -> 148.68626 | E48: =MAX(0,E47*Assumptions!$C$5) -> 239.25615 | F48: =MAX(0,F47*Assumptions!$C$5) -> 280.38392 | G48: =MAX(0,G47*Assumptions!$C$5) -> 310.84192 | H48: =MAX(0,H47*Assumptions!$C$5) -> 333.89373
A49: Net income | D49: =D47-D48 -> 594.74505 | E49: =E47-E48 -> 957.0246 | F49: =F47-F48 -> 1121.5357 | G49: =G47-G48 -> 1243.3677 | H49: =H47-H48 -> 1335.5749
A50: Maintenance capex | B50: % of revenue | D50: =Assumptions!$C$9*D40 -> 196.18056 | E50: =Assumptions!$C$9*E40 -> 219.72223 | F50: =Assumptions!$C$9*F40 -> 232.76823 | G50: =Assumptions!$C$9*G40 -> 244.40665 | H50: =Assumptions!$C$9*H40 -> 254.18291
A51: Increase in net working capital | B51: MAX(0, NWC% x revenue growth) | D51: =MAX(0,Assumptions!$C$8*(D40-$C$7)) -> 29.43756 | E51: =MAX(0,Assumptions!$C$8*(E40-D40)) -> 317.81251 | F51: =MAX(0,Assumptions!$C$8*(F40-E40)) -> 176.1211 | G51: =MAX(0,Assumptions!$C$8*(G40-F40)) -> 157.11856 | H51: =MAX(0,Assumptions!$C$8*(H40-G40)) -> 131.97959
A52: Cash flow available for debt service (CFADS) | B52: EBITDA – tax – capex – ΔNWC | D52: =D44-D48-D50-D51 -> 1469.7769 | E52: =E44-E48-E50-E51 -> 1496.1399 | F52: =F44-F48-F50-F51 -> 1694.7963 | G52: =G44-G48-G50-G51 -> 1753.4925 | H52: =H44-H48-H50-H51 -> 1790.5624
A53: Scheduled principal | D53: =Debt_Schedule!D23 -> 200 | E53: =Debt_Schedule!E23 -> 800 | F53: =Debt_Schedule!F23 -> 600 | G53: =Debt_Schedule!G23 -> 600 | H53: =Debt_Schedule!H23 -> 600
A54: Total debt service | B54: Interest & fees + principal | D54: =D46+D53 -> 600.65 | E54: =E46+E53 -> 1176.65 | F54: =F46+F53 -> 882.15 | G54: =G46+G53 -> 811.65 | H54: =H46+H53 -> 741.15
A55: DSCR | B55: CFADS / debt service | D55: =D52/D54 -> 2.4469773 | E55: =E52/E54 -> 1.271525 | F55: =F52/F54 -> 1.9212111 | G55: =G52/G54 -> 2.1604047 | H55: =H52/H54 -> 2.4159244 | I55: =MIN(D55:H55) -> 1.271525
A56: CFADS headroom before DSCR = 1.0x | B56: 1 – 1/DSCR | D56: =1-1/D55 -> 0.59133254 | E56: =1-1/E55 -> 0.21354278 | F56: =1-1/F55 -> 0.47949498 | G56: =1-1/G55 -> 0.53712376 | H56: =1-1/H55 -> 0.58607977
A57: Total Debt / EBITDA | B57: Year-end debt / EBITDA | D57: =Debt_Schedule!D26/D44 -> 1.7515497 | E57: =Debt_Schedule!E26/E44 -> 1.0691043 | F57: =Debt_Schedule!F26/F44 -> 0.76759505 | G57: =Debt_Schedule!G26/G44 -> 0.49881185 | H57: =Debt_Schedule!H26/H44 -> 0.25093417 | I57: =MAX(D57:H57) -> 1.7515497
A58: Cumulative cash after debt service | D58: =0+D52-D54 -> 869.12693 | E58: =D58+E52-E54 -> 1188.6168 | F58: =E58+F52-F54 -> 2001.2631 | G58: =F58+G52-G54 -> 2943.1056 | H58: =G58+H52-H54 -> 3992.518
A59: Covenant: DSCR ≥ minimum | D59: =IF(D55>=Assumptions!$C$51,"PASS","BREACH") -> PASS | E59: =IF(E55>=Assumptions!$C$51,"PASS","BREACH") -> PASS | F59: =IF(F55>=Assumptions!$C$51,"PASS","BREACH") -> PASS | G59: =IF(G55>=Assumptions!$C$51,"PASS","BREACH") -> PASS | H59: =IF(H55>=Assumptions!$C$51,"PASS","BREACH") -> PASS
A60: Covenant: Debt/EBITDA ≤ maximum | D60: =IF(D57<=Assumptions!$C$52,"PASS","BREACH") -> PASS | E60: =IF(E57<=Assumptions!$C$52,"PASS","BREACH") -> PASS | F60: =IF(F57<=Assumptions!$C$52,"PASS","BREACH") -> PASS | G60: =IF(G57<=Assumptions!$C$52,"PASS","BREACH") -> PASS | H60: =IF(H57<=Assumptions!$C$52,"PASS","BREACH") -> PASS
A62: Scenario: FX shock
A63: FX factor on SYP-priced items | B63: (1 + pass-through x dep) / (1 + dep) | D63: =(1+Assumptions!$E$45*Assumptions!$E$44)/(1+Assumptions!$E$44) -> 0.83333333 | E63: =(1+Assumptions!$E$45*Assumptions!$E$44)/(1+Assumptions!$E$44) -> 0.83333333 | F63: =(1+Assumptions!$E$45*Assumptions!$E$44)/(1+Assumptions!$E$44) -> 0.83333333 | G63: =(1+Assumptions!$E$45*Assumptions!$E$44)/(1+Assumptions!$E$44) -> 0.83333333 | H63: =(1+Assumptions!$E$45*Assumptions!$E$44)/(1+Assumptions!$E$44) -> 0.83333333
A64: Volume-adjusted revenue | B64: Base x (1 + sales shock) | D64: =D7*(1+Assumptions!$E$43) -> 10898.92 | E64: =E7*(1+Assumptions!$E$43) -> 12206.79 | F64: =F7*(1+Assumptions!$E$43) -> 12931.569 | G64: =G7*(1+Assumptions!$E$43) -> 13578.147 | H64: =H7*(1+Assumptions!$E$43) -> 14121.273
A65: Revenue (USD) | B65: Export + domestic x FX factor | D65: =D64*(Assumptions!$C$6+(1-Assumptions!$C$6)*D63) -> 10135.996 | E65: =E64*(Assumptions!$C$6+(1-Assumptions!$C$6)*E63) -> 11352.315 | F65: =F64*(Assumptions!$C$6+(1-Assumptions!$C$6)*F63) -> 12026.359 | G65: =G64*(Assumptions!$C$6+(1-Assumptions!$C$6)*G63) -> 12627.677 | H65: =H64*(Assumptions!$C$6+(1-Assumptions!$C$6)*H63) -> 13132.784
A66: Raw materials, packaging & labour | B66: USD-linked; on volume | D66: =-D64*(Assumptions!D34+Assumptions!$E$46) -> -6648.3412 | E66: =-E64*(Assumptions!E34+Assumptions!$E$46) -> -7446.1421 | F66: =-F64*(Assumptions!F34+Assumptions!$E$46) -> -7888.2568 | G66: =-G64*(Assumptions!G34+Assumptions!$E$46) -> -8282.6697 | H66: =-H64*(Assumptions!H34+Assumptions!$E$46) -> -8613.9765
A67: Energy | D67: =-D64*(Assumptions!D35+Assumptions!$E$47) -> -741.12656 | E67: =-E64*(Assumptions!E35+Assumptions!$E$47) -> -646.95989 | F67: =-F64*(Assumptions!F35+Assumptions!$E$47) -> -685.37313 | G67: =-G64*(Assumptions!G35+Assumptions!$E$47) -> -719.64179 | H67: =-H64*(Assumptions!H35+Assumptions!$E$47) -> -748.42746
A68: Operating expenses | B68: SYP share x FX factor | D68: =-D8*((1-Assumptions!$C$7)+Assumptions!$C$7*D63) -> -953.37 | E68: =-E8*((1-Assumptions!$C$7)+Assumptions!$C$7*E63) -> -1029.6396 | F68: =-F8*((1-Assumptions!$C$7)+Assumptions!$C$7*F63) -> -1112.0108 | G68: =-G8*((1-Assumptions!$C$7)+Assumptions!$C$7*G63) -> -1200.9716 | H68: =-H8*((1-Assumptions!$C$7)+Assumptions!$C$7*H63) -> -1297.0494
A69: EBITDA | D69: =SUM(D65:D68) -> 1793.1578 | E69: =SUM(E65:E68) -> 2229.5734 | F69: =SUM(F65:F68) -> 2340.718 | G69: =SUM(G65:G68) -> 2424.3936 | H69: =SUM(H65:H68) -> 2473.3305 | I69: =MIN(D69:H69) -> 1793.1578
A70: EBITDA margin | D70: =D69/D65 -> 0.17690989 | E70: =E69/E65 -> 0.19639813 | F70: =F69/F65 -> 0.19463231 | G70: =G69/G65 -> 0.19199047 | H70: =H69/H65 -> 0.18833254
A71: Interest & fees | B71: Base + rate shock x debt | D71: =Debt_Schedule!D22+Assumptions!$E$48*Debt_Schedule!D25 -> 332.05 | E71: =Debt_Schedule!E22+Assumptions!$E$48*Debt_Schedule!E25 -> 312.05 | F71: =Debt_Schedule!F22+Assumptions!$E$48*Debt_Schedule!F25 -> 233.55 | G71: =Debt_Schedule!G22+Assumptions!$E$48*Debt_Schedule!G25 -> 175.05 | H71: =Debt_Schedule!H22+Assumptions!$E$48*Debt_Schedule!H25 -> 116.55
A72: Profit before tax | D72: =D69-D9-D71 -> 761.10784 | E72: =E69-E9-E71 -> 1217.5234 | F72: =F69-F9-F71 -> 1407.168 | G72: =G69-G9-G71 -> 1549.3436 | H72: =H69-H9-H71 -> 1656.7805
A73: Cash tax | B73: MAX(0, PBT x rate) | D73: =MAX(0,D72*Assumptions!$C$5) -> 152.22157 | E73: =MAX(0,E72*Assumptions!$C$5) -> 243.50469 | F73: =MAX(0,F72*Assumptions!$C$5) -> 281.43361 | G73: =MAX(0,G72*Assumptions!$C$5) -> 309.86872 | H73: =MAX(0,H72*Assumptions!$C$5) -> 331.3561
A74: Net income | D74: =D72-D73 -> 608.88627 | E74: =E72-E73 -> 974.01875 | F74: =F72-F73 -> 1125.7344 | G74: =G72-G73 -> 1239.4749 | H74: =H72-H73 -> 1325.4244
A75: Maintenance capex | B75: % of revenue | D75: =Assumptions!$C$9*D65 -> 202.71991 | E75: =Assumptions!$C$9*E65 -> 227.0463 | F75: =Assumptions!$C$9*F65 -> 240.52718 | G75: =Assumptions!$C$9*G65 -> 252.55353 | H75: =Assumptions!$C$9*H65 -> 262.65568
A76: Increase in net working capital | B76: MAX(0, NWC% x revenue growth) | D76: =MAX(0,Assumptions!$C$8*(D65-$C$7)) -> 117.71881 | E76: =MAX(0,Assumptions!$C$8*(E65-D65)) -> 328.40626 | F76: =MAX(0,Assumptions!$C$8*(F65-E65)) -> 181.9918 | G76: =MAX(0,Assumptions!$C$8*(G65-F65)) -> 162.35584 | H76: =MAX(0,Assumptions!$C$8*(H65-G65)) -> 136.37891
A77: Cash flow available for debt service (CFADS) | B77: EBITDA – tax – capex – ΔNWC | D77: =D69-D73-D75-D76 -> 1320.4975 | E77: =E69-E73-E75-E76 -> 1430.6162 | F77: =F69-F73-F75-F76 -> 1636.7655 | G77: =G69-G73-G75-G76 -> 1699.6155 | H77: =H69-H73-H75-H76 -> 1742.9398
A78: Scheduled principal | D78: =Debt_Schedule!D23 -> 200 | E78: =Debt_Schedule!E23 -> 800 | F78: =Debt_Schedule!F23 -> 600 | G78: =Debt_Schedule!G23 -> 600 | H78: =Debt_Schedule!H23 -> 600
A79: Total debt service | B79: Interest & fees + principal | D79: =D71+D78 -> 532.05 | E79: =E71+E78 -> 1112.05 | F79: =F71+F78 -> 833.55 | G79: =G71+G78 -> 775.05 | H79: =H71+H78 -> 716.55
A80: DSCR | B80: CFADS / debt service | D80: =D77/D79 -> 2.481905 | E80: =E77/E79 -> 1.2864675 | F80: =F77/F79 -> 1.963608 | G80: =G77/G79 -> 2.1929108 | H80: =H77/H79 -> 2.432405 | I80: =MIN(D80:H80) -> 1.2864675
A81: CFADS headroom before DSCR = 1.0x | B81: 1 – 1/DSCR | D81: =1-1/D80 -> 0.59708369 | E81: =1-1/E80 -> 0.22267761 | F81: =1-1/F80 -> 0.49073339 | G81: =1-1/G80 -> 0.5439851 | H81: =1-1/H80 -> 0.58888426
A82: Total Debt / EBITDA | B82: Year-end debt / EBITDA | D82: =Debt_Schedule!D26/D69 -> 1.8012915 | E82: =Debt_Schedule!E26/E69 -> 1.0898946 | F82: =Debt_Schedule!F26/F69 -> 0.78181138 | G82: =Debt_Schedule!G26/G69 -> 0.50734336 | H82: =Debt_Schedule!H26/H69 -> 0.25471727 | I82: =MAX(D82:H82) -> 1.8012915
A83: Cumulative cash after debt service | D83: =0+D77-D79 -> 788.44755 | E83: =D83+E77-E79 -> 1107.0137 | F83: =E83+F77-F79 -> 1910.2292 | G83: =F83+G77-G79 -> 2834.7947 | H83: =G83+H77-H79 -> 3861.1845
A84: Covenant: DSCR ≥ minimum | D84: =IF(D80>=Assumptions!$C$51,"PASS","BREACH") -> PASS | E84: =IF(E80>=Assumptions!$C$51,"PASS","BREACH") -> PASS | F84: =IF(F80>=Assumptions!$C$51,"PASS","BREACH") -> PASS | G84: =IF(G80>=Assumptions!$C$51,"PASS","BREACH") -> PASS | H84: =IF(H80>=Assumptions!$C$51,"PASS","BREACH") -> PASS
A85: Covenant: Debt/EBITDA ≤ maximum | D85: =IF(D82<=Assumptions!$C$52,"PASS","BREACH") -> PASS | E85: =IF(E82<=Assumptions!$C$52,"PASS","BREACH") -> PASS | F85: =IF(F82<=Assumptions!$C$52,"PASS","BREACH") -> PASS | G85: =IF(G82<=Assumptions!$C$52,"PASS","BREACH") -> PASS | H85: =IF(H82<=Assumptions!$C$52,"PASS","BREACH") -> PASS
A87: Scenario: Combined
A88: FX factor on SYP-priced items | B88: (1 + pass-through x dep) / (1 + dep) | D88: =(1+Assumptions!$F$45*Assumptions!$F$44)/(1+Assumptions!$F$44) -> 0.85714286 | E88: =(1+Assumptions!$F$45*Assumptions!$F$44)/(1+Assumptions!$F$44) -> 0.85714286 | F88: =(1+Assumptions!$F$45*Assumptions!$F$44)/(1+Assumptions!$F$44) -> 0.85714286 | G88: =(1+Assumptions!$F$45*Assumptions!$F$44)/(1+Assumptions!$F$44) -> 0.85714286 | H88: =(1+Assumptions!$F$45*Assumptions!$F$44)/(1+Assumptions!$F$44) -> 0.85714286
A89: Volume-adjusted revenue | B89: Base x (1 + sales shock) | D89: =D7*(1+Assumptions!$F$43) -> 9264.082 | E89: =E7*(1+Assumptions!$F$43) -> 10375.772 | F89: =F7*(1+Assumptions!$F$43) -> 10991.833 | G89: =G7*(1+Assumptions!$F$43) -> 11541.425 | H89: =H7*(1+Assumptions!$F$43) -> 12003.082
A90: Revenue (USD) | B90: Export + domestic x FX factor | D90: =D89*(Assumptions!$C$6+(1-Assumptions!$C$6)*D88) -> 8708.2371 | E90: =E89*(Assumptions!$C$6+(1-Assumptions!$C$6)*E88) -> 9753.2255 | F90: =F89*(Assumptions!$C$6+(1-Assumptions!$C$6)*F88) -> 10332.323 | G90: =G89*(Assumptions!$C$6+(1-Assumptions!$C$6)*G88) -> 10848.939 | H90: =H89*(Assumptions!$C$6+(1-Assumptions!$C$6)*H88) -> 11282.897
A91: Raw materials, packaging & labour | B91: USD-linked; on volume | D91: =-D89*(Assumptions!D34+Assumptions!$F$46) -> -5836.3717 | E91: =-E89*(Assumptions!E34+Assumptions!$F$46) -> -6536.7363 | F91: =-F89*(Assumptions!F34+Assumptions!$F$46) -> -6924.855 | G91: =-G89*(Assumptions!G34+Assumptions!$F$46) -> -7271.0977 | H91: =-H89*(Assumptions!H34+Assumptions!$F$46) -> -7561.9416
A92: Energy | D92: =-D89*(Assumptions!D35+Assumptions!$F$47) -> -768.91881 | E92: =-E89*(Assumptions!E35+Assumptions!$F$47) -> -705.55249 | F92: =-F89*(Assumptions!F35+Assumptions!$F$47) -> -747.44466 | G92: =-G89*(Assumptions!G35+Assumptions!$F$47) -> -784.8169 | H92: =-H89*(Assumptions!H35+Assumptions!$F$47) -> -816.20957
A93: Operating expenses | B93: SYP share x FX factor | D93: =-D8*((1-Assumptions!$C$7)+Assumptions!$C$7*D88) -> -969.91714 | E93: =-E8*((1-Assumptions!$C$7)+Assumptions!$C$7*E88) -> -1047.5105 | F93: =-F8*((1-Assumptions!$C$7)+Assumptions!$C$7*F88) -> -1131.3114 | G93: =-G8*((1-Assumptions!$C$7)+Assumptions!$C$7*G88) -> -1221.8163 | H93: =-H8*((1-Assumptions!$C$7)+Assumptions!$C$7*H88) -> -1319.5616
A94: EBITDA | D94: =SUM(D90:D93) -> 1133.0295 | E94: =SUM(E90:E93) -> 1463.4263 | F94: =SUM(F90:F93) -> 1528.7123 | G94: =SUM(G90:G93) -> 1571.2086 | H94: =SUM(H90:H93) -> 1585.1843 | I94: =MIN(D94:H94) -> 1133.0295
A95: EBITDA margin | D95: =D94/D90 -> 0.13011009 | E95: =E94/E90 -> 0.15004536 | F95: =F94/F90 -> 0.14795436 | G95: =G94/G90 -> 0.14482601 | H95: =H94/H90 -> 0.14049444
A96: Interest & fees | B96: Base + rate shock x debt | D96: =Debt_Schedule!D22+Assumptions!$F$48*Debt_Schedule!D25 -> 383.5 | E96: =Debt_Schedule!E22+Assumptions!$F$48*Debt_Schedule!E25 -> 360.5 | F96: =Debt_Schedule!F22+Assumptions!$F$48*Debt_Schedule!F25 -> 270 | G96: =Debt_Schedule!G22+Assumptions!$F$48*Debt_Schedule!G25 -> 202.5 | H96: =Debt_Schedule!H22+Assumptions!$F$48*Debt_Schedule!H25 -> 135
A97: Profit before tax | D97: =D94-D9-D96 -> 49.529471 | E97: =E94-E9-E96 -> 402.92627 | F97: =F94-F9-F96 -> 558.7123 | G97: =G94-G9-G96 -> 668.70858 | H97: =H94-H9-H96 -> 750.18427
A98: Cash tax | B98: MAX(0, PBT x rate) | D98: =MAX(0,D97*Assumptions!$C$5) -> 9.9058942 | E98: =MAX(0,E97*Assumptions!$C$5) -> 80.585254 | F98: =MAX(0,F97*Assumptions!$C$5) -> 111.74246 | G98: =MAX(0,G97*Assumptions!$C$5) -> 133.74172 | H98: =MAX(0,H97*Assumptions!$C$5) -> 150.03685
A99: Net income | D99: =D97-D98 -> 39.623577 | E99: =E97-E98 -> 322.34102 | F99: =F97-F98 -> 446.96984 | G99: =G97-G98 -> 534.96686 | H99: =H97-H98 -> 600.14741
A100: Maintenance capex | B100: % of revenue | D100: =Assumptions!$C$9*D90 -> 174.16474 | E100: =Assumptions!$C$9*E90 -> 195.06451 | F100: =Assumptions!$C$9*F90 -> 206.64647 | G100: =Assumptions!$C$9*G90 -> 216.97879 | H100: =Assumptions!$C$9*H90 -> 225.65794
A101: Increase in net working capital | B101: MAX(0, NWC% x revenue growth) | D101: =MAX(0,Assumptions!$C$8*(D90-$C$7)) -> 0 | E101: =MAX(0,Assumptions!$C$8*(E90-D90)) -> 282.14688 | F101: =MAX(0,Assumptions!$C$8*(F90-E90)) -> 156.3564 | G101: =MAX(0,Assumptions!$C$8*(G90-F90)) -> 139.48636 | H101: =MAX(0,Assumptions!$C$8*(H90-G90)) -> 117.16855
A102: Cash flow available for debt service (CFADS) | B102: EBITDA – tax – capex – ΔNWC | D102: =D94-D98-D100-D101 -> 948.95884 | E102: =E94-E98-E100-E101 -> 905.62962 | F102: =F94-F98-F100-F101 -> 1053.967 | G102: =G94-G98-G100-G101 -> 1081.0017 | H102: =H94-H98-H100-H101 -> 1092.3209
A103: Scheduled principal | D103: =Debt_Schedule!D23 -> 200 | E103: =Debt_Schedule!E23 -> 800 | F103: =Debt_Schedule!F23 -> 600 | G103: =Debt_Schedule!G23 -> 600 | H103: =Debt_Schedule!H23 -> 600
A104: Total debt service | B104: Interest & fees + principal | D104: =D96+D103 -> 583.5 | E104: =E96+E103 -> 1160.5 | F104: =F96+F103 -> 870 | G104: =G96+G103 -> 802.5 | H104: =H96+H103 -> 735
A105: DSCR | B105: CFADS / debt service | D105: =D102/D104 -> 1.6263219 | E105: =E102/E104 -> 0.78037882 | F105: =F102/F104 -> 1.2114563 | G105: =G102/G104 -> 1.3470426 | H105: =H102/H104 -> 1.4861509 | I105: =MIN(D105:H105) -> 0.78037882
...

Sheet Sensitivity
A1: Sensitivity: FY2028 DSCR (first full amortisation year)
A2: Each cell recomputes CFADS / debt service for the sales change (rows) and SYP depreciation (columns). Other shocks off; base rates.
A4: FX pass-through used | B4: =Assumptions!$C$45 -> 0.5
A6: Sales change ↓ / SYP depreciation → | C6: 0 | D6: 0.2 | E6: 0.4 | F6: 0.6 | G6: 0.8
A7: 0 | C7: =((((Projections!$E$7*(1+$A7))*(Assumptions!$C$6+(1-Assumptions!$C$6)*((1+$B$4*C$6)/(1+C$6))))-(Projections!$E$7*(1+$A7))*(Assumptions!$E$34+Assumptions!$E$35)-Projections!$E$8*((1-Assumptions!$C$7)+Assumptions!$C$7*((1+$B$4*C$6)/(1+C$6))))-MAX(0,((((Projections!$E$7*(1+$A7))*(Assumptions!$C$6+(1-Assumptions!$C$6)*((1+$B$4*C$6)/(1+C$6))))-(Projections!$E$7*(1+$A7))*(Assumptions!$E$34+Assumptions!$E$35)-Projections!$E$8*((1-Assumptions!$C$7)+Assumptions!$C$7*((1+$B$4*C$6)/(1+C$6))))-Projections!$E$9-Debt_Schedule!$E$22)*Assumptions!$C$5)-Assumptions!$C$9*((Projections!$E$7*(1+$A7))*(Assumptions!$C$6+(1-Assumptions!$C$6)*((1+$B$4*C$6)/(1+C$6))))-MAX(0,Assumptions!$C$8*(((Projections!$E$7*(1+$A7))*(Assumptions!$C$6+(1-Assumptions!$C$6)*((1+$B$4*C$6)/(1+C$6))))-(Projections!$D$7*(1+$A7)*(Assumptions!$C$6+(1-Assumptions!$C$6)*((1+$B$4*C$6)/(1+C$6)))))))/Debt_Schedule!$E$24 -> 1.7735813 | D7: =((((Projections!$E$7*(1+$A7))*(Assumptions!$C$6+(1-Assumptions!$C$6)*((1+$B$4*D$6)/(1+D$6))))-(Projections!$E$7*(1+$A7))*(Assumptions!$E$34+Assumptions!$E$35)-Projections!$E$8*((1-Assumptions!$C$7)+Assumptions!$C$7*((1+$B$4*D$6)/(1+D$6))))-MAX(0,((((Projections!$E$7*(1+$A7))*(Assumptions!$C$6+(1-Assumptions!$C$6)*((1+$B$4*D$6)/(1+D$6))))-(Projections!$E$7*(1+$A7))*(Assumptions!$E$34+Assumptions!$E$35)-Projections!$E$8*((1-Assumptions!$C$7)+Assumptions!$C$7*((1+$B$4*D$6)/(1+D$6))))-Projections!$E$9-Debt_Schedule!$E$22)*Assumptions!$C$5)-Assumptions!$C$9*((Projections!$E$7*(1+$A7))*(Assumptions!$C$6+(1-Assumptions!$C$6)*((1+$B$4*D$6)/(1+D$6))))-MAX(0,Assumptions!$C$8*(((Projections!$E$7*(1+$A7))*(Assumptions!$C$6+(1-Assumptions!$C$6)*((1+$B$4*D$6)/(1+D$6))))-(Projections!$D$7*(1+$A7)*(Assumptions!$C$6+(1-Assumptions!$C$6)*((1+$B$4*D$6)/(1+D$6)))))))/Debt_Schedule!$E$24 -> 1.5300244 | E7: =((((Projections!$E$7*(1+$A7))*(Assumptions!$C$6+(1-Assumptions!$C$6)*((1+$B$4*E$6)/(1+E$6))))-(Projections!$E$7*(1+$A7))*(Assumptions!$E$34+Assumptions!$E$35)-Projections!$E$8*((1-Assumptions!$C$7)+Assumptions!$C$7*((1+$B$4*E$6)/(1+E$6))))-MAX(0,((((Projections!$E$7*(1+$A7))*(Assumptions!$C$6+(1-Assumptions!$C$6)*((1+$B$4*E$6)/(1+E$6))))-(Projections!$E$7*(1+$A7))*(Assumptions!$E$34+Assumptions!$E$35)-Projections!$E$8*((1-Assumptions!$C$7)+Assumptions!$C$7*((1+$B$4*E$6)/(1+E$6))))-Projections!$E$9-Debt_Schedule!$E$22)*Assumptions!$C$5)-Assumptions!$C$9*((Projections!$E$7*(1+$A7))*(Assumptions!$C$6+(1-Assumptions!$C$6)*((1+$B$4*E$6)/(1+E$6))))-MAX(0,Assumptions!$C$8*(((Projections!$E$7*(1+$A7))*(Assumptions!$C$6+(1-Assumptions!$C$6)*((1+$B$4*E$6)/(1+E$6))))-(Projections!$D$7*(1+$A7)*(Assumptions!$C$6+(1-Assumptions!$C$6)*((1+$B$4*E$6)/(1+E$6)))))))/Debt_Schedule!$E$24 -> 1.3560552 | F7: =((((Projections!$E$7*(1+$A7))*(Assumptions!$C$6+(1-Assumptions!$C$6)*((1+$B$4*F$6)/(1+F$6))))-(Projections!$E$7*(1+$A7))*(Assumptions!$E$34+Assumptions!$E$35)-Projections!$E$8*((1-Assumptions!$C$7)+Assumptions!$C$7*((1+$B$4*F$6)/(1+F$6))))-MAX(0,((((Projections!$E$7*(1+$A7))*(Assumptions!$C$6+(1-Assumptions!$C$6)*((1+$B$4*F$6)/(1+F$6))))-(Projections!$E$7*(1+$A7))*(Assumptions!$E$34+Assumptions!$E$35)-Projections!$E$8*((1-Assumptions!$C$7)+Assumptions!$C$7*((1+$B$4*F$6)/(1+F$6))))-Projections!$E$9-Debt_Schedule!$E$22)*Assumptions!$C$5)-Assumptions!$C$9*((Projections!$E$7*(1+$A7))*(Assumptions!$C$6+(1-Assumptions!$C$6)*((1+$B$4*F$6)/(1+F$6))))-MAX(0,Assumptions!$C$8*(((Projections!$E$7*(1+$A7))*(Assumptions!$C$6+(1-Assumptions!$C$6)*((1+$B$4*F$6)/(1+F$6))))-(Projections!$D$7*(1+$A7)*(Assumptions!$C$6+(1-Assumptions!$C$6)*((1+$B$4*F$6)/(1+F$6)))))))/Debt_Schedule!$E$24 -> 1.2255783 | G7: =((((Projections!$E$7*(1+$A7))*(Assumptions!$C$6+(1-Assumptions!$C$6)*((1+$B$4*G$6)/(1+G$6))))-(Projections!$E$7*(1+$A7))*(Assumptions!$E$34+Assumptions!$E$35)-Projections!$E$8*((1-Assumptions!$C$7)+Assumptions!$C$7*((1+$B$4*G$6)/(1+G$6))))-MAX(0,((((Projections!$E$7*(1+$A7))*(Assumptions!$C$6+(1-Assumptions!$C$6)*((1+$B$4*G$6)/(1+G$6))))-(Projections!$E$7*(1+$A7))*(Assumptions!$E$34+Assumptions!$E$35)-Projections!$E$8*((1-Assumptions!$C$7)+Assumptions!$C$7*((1+$B$4*G$6)/(1+G$6))))-Projections!$E$9-Debt_Schedule!$E$22)*Assumptions!$C$5)-Assumptions!$C$9*((Projections!$E$7*(1+$A7))*(Assumptions!$C$6+(1-Assumptions!$C$6)*((1+$B$4*G$6)/(1+G$6))))-MAX(0,Assumptions!$C$8*(((Projections!$E$7*(1+$A7))*(Assumptions!$C$6+(1-Assumptions!$C$6)*((1+$B$4*G$6)/(1+G$6))))-(Projections!$D$7*(1+$A7)*(Assumptions!$C$6+(1-Assumptions!$C$6)*((1+$B$4*G$6)/(1+G$6)))))))/Debt_Schedule!$E$24 -> 1.1240962
A8: -0.05 | C8: =((((Projections!$E$7*(1+$A8))*(Assumptions!$C$6+(1-Assumptions!$C$6)*((1+$B$4*C$6)/(1+C$6))))-(Projections!$E$7*(1+$A8))*(Assumptions!$E$34+Assumptions!$E$35)-Projections!$E$8*((1-Assumptions!$C$7)+Assumptions!$C$7*((1+$B$4*C$6)/(1+C$6))))-MAX(0,((((Projections!$E$7*(1+$A8))*(Assumptions!$C$6+(1-Assumptions!$C$6)*((1+$B$4*C$6)/(1+C$6))))-(Projections!$E$7*(1+$A8))*(Assumptions!$E$34+Assumptions!$E$35)-Projections!$E$8*((1-Assumptions!$C$7)+Assumptions!$C$7*((1+$B$4*C$6)/(1+C$6))))-Projections!$E$9-Debt_Schedule!$E$22)*Assumptions!$C$5)-Assumptions!$C$9*((Projections!$E$7*(1+$A8))*(Assumptions!$C$6+(1-Assumptions!$C$6)*((1+$B$4*C$6)/(1+C$6))))-MAX(0,Assumptions!$C$8*(((Projections!$E$7*(1+$A8))*(Assumptions!$C$6+(1-Assumptions!$C$6)*((1+$B$4*C$6)/(1+C$6))))-(Projections!$D$7*(1+$A8)*(Assumptions!$C$6+(1-Assumptions!$C$6)*((1+$B$4*C$6)/(1+C$6)))))))/Debt_Schedule!$E$24 -> 1.6524676 | D8: =((((Projections!$E$7*(1+$A8))*(Assumptions!$C$6+(1-Assumptions!$C$6)*((1+$B$4*D$6)/(1+D$6))))-(Projections!$E$7*(1+$A8))*(Assumptions!$E$34+Assumptions!$E$35)-Projections!$E$8*((1-Assumptions!$C$7)+Assumptions!$C$7*((1+$B$4*D$6)/(1+D$6))))-MAX(0,((((Projections!$E$7*(1+$A8))*(Assumptions!$C$6+(1-Assumptions!$C$6)*((1+$B$4*D$6)/(1+D$6))))-(Projections!$E$7*(1+$A8))*(Assumptions!$E$34+Assumptions!$E$35)-Projections!$E$8*((1-Assumptions!$C$7)+Assumptions!$C$7*((1+$B$4*D$6)/(1+D$6))))-Projections!$E$9-Debt_Schedule!$E$22)*Assumptions!$C$5)-Assumptions!$C$9*((Projections!$E$7*(1+$A8))*(Assumptions!$C$6+(1-Assumptions!$C$6)*((1+$B$4*D$6)/(1+D$6))))-MAX(0,Assumptions!$C$8*(((Projections!$E$7*(1+$A8))*(Assumptions!$C$6+(1-Assumptions!$C$6)*((1+$B$4*D$6)/(1+D$6))))-(Projections!$D$7*(1+$A8)*(Assumptions!$C$6+(1-Assumptions!$C$6)*((1+$B$4*D$6)/(1+D$6)))))))/Debt_Schedule!$E$24 -> 1.4233384 | E8: =((((Projections!$E$7*(1+$A8))*(Assumptions!$C$6+(1-Assumptions!$C$6)*((1+$B$4*E$6)/(1+E$6))))-(Projections!$E$7*(1+$A8))*(Assumptions!$E$34+Assumptions!$E$35)-Projections!$E$8*((1-Assumptions!$C$7)+Assumptions!$C$7*((1+$B$4*E$6)/(1+E$6))))-MAX(0,((((Projections!$E$7*(1+$A8))*(Assumptions!$C$6+(1-Assumptions!$C$6)*((1+$B$4*E$6)/(1+E$6))))-(Projections!$E$7*(1+$A8))*(Assumptions!$E$34+Assumptions!$E$35)-Projections!$E$8*((1-Assumptions!$C$7)+Assumptions!$C$7*((1+$B$4*E$6)/(1+E$6))))-Projections!$E$9-Debt_Schedule!$E$22)*Assumptions!$C$5)-Assumptions!$C$9*((Projections!$E$7*(1+$A8))*(Assumptions!$C$6+(1-Assumptions!$C$6)*((1+$B$4*E$6)/(1+E$6))))-MAX(0,Assumptions!$C$8*(((Projections!$E$7*(1+$A8))*(Assumptions!$C$6+(1-Assumptions!$C$6)*((1+$B$4*E$6)/(1+E$6))))-(Projections!$D$7*(1+$A8)*(Assumptions!$C$6+(1-Assumptions!$C$6)*((1+$B$4*E$6)/(1+E$6)))))))/Debt_Schedule!$E$24 -> 1.2596747 | F8: =((((Projections!$E$7*(1+$A8))*(Assumptions!$C$6+(1-Assumptions!$C$6)*((1+$B$4*F$6)/(1+F$6))))-(Projections!$E$7*(1+$A8))*(Assumptions!$E$34+Assumptions!$E$35)-Projections!$E$8*((1-Assumptions!$C$7)+Assumptions!$C$7*((1+$B$4*F$6)/(1+F$6))))-MAX(0,((((Projections!$E$7*(1+$A8))*(Assumptions!$C$6+(1-Assumptions!$C$6)*((1+$B$4*F$6)/(1+F$6))))-(Projections!$E$7*(1+$A8))*(Assumptions!$E$34+Assumptions!$E$35)-Projections!$E$8*((1-Assumptions!$C$7)+Assumptions!$C$7*((1+$B$4*F$6)/(1+F$6))))-Projections!$E$9-Debt_Schedule!$E$22)*Assumptions!$C$5)-Assumptions!$C$9*((Projections!$E$7*(1+$A8))*(Assumptions!$C$6+(1-Assumptions!$C$6)*((1+$B$4*F$6)/(1+F$6))))-MAX(0,Assumptions!$C$8*(((Projections!$E$7*(1+$A8))*(Assumptions!$C$6+(1-Assumptions!$C$6)*((1+$B$4*F$6)/(1+F$6))))-(Projections!$D$7*(1+$A8)*(Assumptions!$C$6+(1-Assumptions!$C$6)*((1+$B$4*F$6)/(1+F$6)))))))/Debt_Schedule!$E$24 -> 1.1369269 | G8: =((((Projections!$E$7*(1+$A8))*(Assumptions!$C$6+(1-Assumptions!$C$6)*((1+$B$4*G$6)/(1+G$6))))-(Projections!$E$7*(1+$A8))*(Assumptions!$E$34+Assumptions!$E$35)-Projections!$E$8*((1-Assumptions!$C$7)+Assumptions!$C$7*((1+$B$4*G$6)/(1+G$6))))-MAX(0,((((Projections!$E$7*(1+$A8))*(Assumptions!$C$6+(1-Assumptions!$C$6)*((1+$B$4*G$6)/(1+G$6))))-(Projections!$E$7*(1+$A8))*(Assumptions!$E$34+Assumptions!$E$35)-Projections!$E$8*((1-Assumptions!$C$7)+Assumptions!$C$7*((1+$B$4*G$6)/(1+G$6))))-Projections!$E$9-Debt_Schedule!$E$22)*Assumptions!$C$5)-Assumptions!$C$9*((Projections!$E$7*(1+$A8))*(Assumptions!$C$6+(1-Assumptions!$C$6)*((1+$B$4*G$6)/(1+G$6))))-MAX(0,Assumptions!$C$8*(((Projections!$E$7*(1+$A8))*(Assumptions!$C$6+(1-Assumptions!$C$6)*((1+$B$4*G$6)/(1+G$6))))-(Projections!$D$7*(1+$A8)*(Assumptions!$C$6+(1-Assumptions!$C$6)*((1+$B$4*G$6)/(1+G$6)))))))/Debt_Schedule!$E$24 -> 1.0414564
A9: -0.1 | C9: =((((Projections!$E$7*(1+$A9))*(Assumptions!$C$6+(1-Assumptions!$C$6)*((1+$B$4*C$6)/(1+C$6))))-(Projections!$E$7*(1+$A9))*(Assumptions!$E$34+Assumptions!$E$35)-Projections!$E$8*((1-Assumptions!$C$7)+Assumptions!$C$7*((1+$B$4*C$6)/(1+C$6))))-MAX(0,((((Projections!$E$7*(1+$A9))*(Assumptions!$C$6+(1-Assumptions!$C$6)*((1+$B$4*C$6)/(1+C$6))))-(Projections!$E$7*(1+$A9))*(Assumptions!$E$34+Assumptions!$E$35)-Projections!$E$8*((1-Assumptions!$C$7)+Assumptions!$C$7*((1+$B$4*C$6)/(1+C$6))))-Projections!$E$9-Debt_Schedule!$E$22)*Assumptions!$C$5)-Assumptions!$C$9*((Projections!$E$7*(1+$A9))*(Assumptions!$C$6+(1-Assumptions!$C$6)*((1+$B$4*C$6)/(1+C$6))))-MAX(0,Assumptions!$C$8*(((Projections!$E$7*(1+$A9))*(Assumptions!$C$6+(1-Assumptions!$C$6)*((1+$B$4*C$6)/(1+C$6))))-(Projections!$D$7*(1+$A9)*(Assumptions!$C$6+(1-Assumptions!$C$6)*((1+$B$4*C$6)/(1+C$6)))))))/Debt_Schedule!$E$24 -> 1.5313539 | D9: =((((Projections!$E$7*(1+$A9))*(Assumptions!$C$6+(1-Assumptions!$C$6)*((1+$B$4*D$6)/(1+D$6))))-(Projections!$E$7*(1+$A9))*(Assumptions!$E$34+Assumptions!$E$35)-Projections!$E$8*((1-Assumptions!$C$7)+Assumptions!$C$7*((1+$B$4*D$6)/(1+D$6))))-MAX(0,((((Projections!$E$7*(1+$A9))*(Assumptions!$C$6+(1-Assumptions!$C$6)*((1+$B$4*D$6)/(1+D$6))))-(Projections!$E$7*(1+$A9))*(Assumptions!$E$34+Assumptions!$E$35)-Projections!$E$8*((1-Assumptions!$C$7)+Assumptions!$C$7*((1+$B$4*D$6)/(1+D$6))))-Projections!$E$9-Debt_Schedule!$E$22)*Assumptions!$C$5)-Assumptions!$C$9*((Projections!$E$7*(1+$A9))*(Assumptions!$C$6+(1-Assumptions!$C$6)*((1+$B$4*D$6)/(1+D$6))))-MAX(0,Assumptions!$C$8*(((Projections!$E$7*(1+$A9))*(Assumptions!$C$6+(1-Assumptions!$C$6)*((1+$B$4*D$6)/(1+D$6))))-(Projections!$D$7*(1+$A9)*(Assumptions!$C$6+(1-Assumptions!$C$6)*((1+$B$4*D$6)/(1+D$6)))))))/Debt_Schedule!$E$24 -> 1.3166524 | E9: =((((Projections!$E$7*(1+$A9))*(Assumptions!$C$6+(1-Assumptions!$C$6)*((1+$B$4*E$6)/(1+E$6))))-(Projections!$E$7*(1+$A9))*(Assumptions!$E$34+Assumptions!$E$35)-Projections!$E$8*((1-Assumptions!$C$7)+Assumptions!$C$7*((1+$B$4*E$6)/(1+E$6))))-MAX(0,((((Projections!$E$7*(1+$A9))*(Assumptions!$C$6+(1-Assumptions!$C$6)*((1+$B$4*E$6)/(1+E$6))))-(Projections!$E$7*(1+$A9))*(Assumptions!$E$34+Assumptions!$E$35)-Projections!$E$8*((1-Assumptions!$C$7)+Assumptions!$C$7*((1+$B$4*E$6)/(1+E$6))))-Projections!$E$9-Debt_Schedule!$E$22)*Assumptions!$C$5)-Assumptions!$C$9*((Projections!$E$7*(1+$A9))*(Assumptions!$C$6+(1-Assumptions!$C$6)*((1+$B$4*E$6)/(1+E$6))))-MAX(0,Assumptions!$C$8*(((Projections!$E$7*(1+$A9))*(Assumptions!$C$6+(1-Assumptions!$C$6)*((1+$B$4*E$6)/(1+E$6))))-(Projections!$D$7*(1+$A9)*(Assumptions!$C$6+(1-Assumptions!$C$6)*((1+$B$4*E$6)/(1+E$6)))))))/Debt_Schedule!$E$24 -> 1.1632941 | F9: =((((Projections!$E$7*(1+$A9))*(Assumptions!$C$6+(1-Assumptions!$C$6)*((1+$B$4*F$6)/(1+F$6))))-(Projections!$E$7*(1+$A9))*(Assumptions!$E$34+Assumptions!$E$35)-Projections!$E$8*((1-Assumptions!$C$7)+Assumptions!$C$7*((1+$B$4*F$6)/(1+F$6))))-MAX(0,((((Projections!$E$7*(1+$A9))*(Assumptions!$C$6+(1-Assumptions!$C$6)*((1+$B$4*F$6)/(1+F$6))))-(Projections!$E$7*(1+$A9))*(Assumptions!$E$34+Assumptions!$E$35)-Projections!$E$8*((1-Assumptions!$C$7)+Assumptions!$C$7*((1+$B$4*F$6)/(1+F$6))))-Projections!$E$9-Debt_Schedule!$E$22)*Assumptions!$C$5)-Assumptions!$C$9*((Projections!$E$7*(1+$A9))*(Assumptions!$C$6+(1-Assumptions!$C$6)*((1+$B$4*F$6)/(1+F$6))))-MAX(0,Assumptions!$C$8*(((Projections!$E$7*(1+$A9))*(Assumptions!$C$6+(1-Assumptions!$C$6)*((1+$B$4*F$6)/(1+F$6))))-(Projections!$D$7*(1+$A9)*(Assumptions!$C$6+(1-Assumptions!$C$6)*((1+$B$4*F$6)/(1+F$6)))))))/Debt_Schedule!$E$24 -> 1.0482754 | G9: =((((Projections!$E$7*(1+$A9))*(Assumptions!$C$6+(1-Assumptions!$C$6)*((1+$B$4*G$6)/(1+G$6))))-(Projections!$E$7*(1+$A9))*(Assumptions!$E$34+Assumptions!$E$35)-Projections!$E$8*((1-Assumptions!$C$7)+Assumptions!$C$7*((1+$B$4*G$6)/(1+G$6))))-MAX(0,((((Projections!$E$7*(1+$A9))*(Assumptions!$C$6+(1-Assumptions!$C$6)*((1+$B$4*G$6)/(1+G$6))))-(Projections!$E$7*(1+$A9))*(Assumptions!$E$34+Assumptions!$E$35)-Projections!$E$8*((1-Assumptions!$C$7)+Assumptions!$C$7*((1+$B$4*G$6)/(1+G$6))))-Projections!$E$9-Debt_Schedule!$E$22)*Assumptions!$C$5)-Assumptions!$C$9*((Projections!$E$7*(1+$A9))*(Assumptions!$C$6+(1-Assumptions!$C$6)*((1+$B$4*G$6)/(1+G$6))))-MAX(0,Assumptions!$C$8*(((Projections!$E$7*(1+$A9))*(Assumptions!$C$6+(1-Assumptions!$C$6)*((1+$B$4*G$6)/(1+G$6))))-(Projections!$D$7*(1+$A9)*(Assumptions!$C$6+(1-Assumptions!$C$6)*((1+$B$4*G$6)/(1+G$6)))))))/Debt_Schedule!$E$24 -> 0.95881646
A10: -0.15 | C10: =((((Projections!$E$7*(1+$A10))*(Assumptions!$C$6+(1-Assumptions!$C$6)*((1+$B$4*C$6)/(1+C$6))))-(Projections!$E$7*(1+$A10))*(Assumptions!$E$34+Assumptions!$E$35)-Projections!$E$8*((1-Assumptions!$C$7)+Assumptions!$C$7*((1+$B$4*C$6)/(1+C$6))))-MAX(0,((((Projections!$E$7*(1+$A10))*(Assumptions!$C$6+(1-Assumptions!$C$6)*((1+$B$4*C$6)/(1+C$6))))-(Projections!$E$7*(1+$A10))*(Assumptions!$E$34+Assumptions!$E$35)-Projections!$E$8*((1-Assumptions!$C$7)+Assumptions!$C$7*((1+$B$4*C$6)/(1+C$6))))-Projections!$E$9-Debt_Schedule!$E$22)*Assumptions!$C$5)-Assumptions!$C$9*((Projections!$E$7*(1+$A10))*(Assumptions!$C$6+(1-Assumptions!$C$6)*((1+$B$4*C$6)/(1+C$6))))-MAX(0,Assumptions!$C$8*(((Projections!$E$7*(1+$A10))*(Assumptions!$C$6+(1-Assumptions!$C$6)*((1+$B$4*C$6)/(1+C$6))))-(Projections!$D$7*(1+$A10)*(Assumptions!$C$6+(1-Assumptions!$C$6)*((1+$B$4*C$6)/(1+C$6)))))))/Debt_Schedule!$E$24 -> 1.4102402 | D10: =((((Projections!$E$7*(1+$A10))*(Assumptions!$C$6+(1-Assumptions!$C$6)*((1+$B$4*D$6)/(1+D$6))))-(Projections!$E$7*(1+$A10))*(Assumptions!$E$34+Assumptions!$E$35)-Projections!$E$8*((1-Assumptions!$C$7)+Assumptions!$C$7*((1+$B$4*D$6)/(1+D$6))))-MAX(0,((((Projections!$E$7*(1+$A10))*(Assumptions!$C$6+(1-Assumptions!$C$6)*((1+$B$4*D$6)/(1+D$6))))-(Projections!$E$7*(1+$A10))*(Assumptions!$E$34+Assumptions!$E$35)-Projections!$E$8*((1-Assumptions!$C$7)+Assumptions!$C$7*((1+$B$4*D$6)/(1+D$6))))-Projections!$E$9-Debt_Schedule!$E$22)*Assumptions!$C$5)-Assumptions!$C$9*((Projections!$E$7*(1+$A10))*(Assumptions!$C$6+(1-Assumptions!$C$6)*((1+$B$4*D$6)/(1+D$6))))-MAX(0,Assumptions!$C$8*(((Projections!$E$7*(1+$A10))*(Assumptions!$C$6+(1-Assumptions!$C$6)*((1+$B$4*D$6)/(1+D$6))))-(Projections!$D$7*(1+$A10)*(Assumptions!$C$6+(1-Assumptions!$C$6)*((1+$B$4*D$6)/(1+D$6)))))))/Debt_Schedule!$E$24 -> 1.2099663 | E10: =((((Projections!$E$7*(1+$A10))*(Assumptions!$C$6+(1-Assumptions!$C$6)*((1+$B$4*E$6)/(1+E$6))))-(Projections!$E$7*(1+$A10))*(Assumptions!$E$34+Assumptions!$E$35)-Projections!$E$8*((1-Assumptions!$C$7)+Assumptions!$C$7*((1+$B$4*E$6)/(1+E$6))))-MAX(0,((((Projections!$E$7*(1+$A10))*(Assumptions!$C$6+(1-Assumptions!$C$6)*((1+$B$4*E$6)/(1+E$6))))-(Projections!$E$7*(1+$A10))*(Assumptions!$E$34+Assumptions!$E$35)-Projections!$E$8*((1-Assumptions!$C$7)+Assumptions!$C$7*((1+$B$4*E$6)/(1+E$6))))-Projections!$E$9-Debt_Schedule!$E$22)*Assumptions!$C$5)-Assumptions!$C$9*((Projections!$E$7*(1+$A10))*(Assumptions!$C$6+(1-Assumptions!$C$6)*((1+$B$4*E$6)/(1+E$6))))-MAX(0,Assumptions!$C$8*(((Projections!$E$7*(1+$A10))*(Assumptions!$C$6+(1-Assumptions!$C$6)*((1+$B$4*E$6)/(1+E$6))))-(Projections!$D$7*(1+$A10)*(Assumptions!$C$6+(1-Assumptions!$C$6)*((1+$B$4*E$6)/(1+E$6)))))))/Debt_Schedule!$E$24 -> 1.0669136 | F10: =((((Projections!$E$7*(1+$A10))*(Assumptions!$C$6+(1-Assumptions!$C$6)*((1+$B$4*F$6)/(1+F$6))))-(Projections!$E$7*(1+$A10))*(Assumptions!$E$34+Assumptions!$E$35)-Projections!$E$8*((1-Assumptions!$C$7)+Assumptions!$C$7*((1+$B$4*F$6)/(1+F$6))))-MAX(0,((((Projections!$E$7*(1+$A10))*(Assumptions!$C$6+(1-Assumptions!$C$6)*((1+$B$4*F$6)/(1+F$6))))-(Projections!$E$7*(1+$A10))*(Assumptions!$E$34+Assumptions!$E$35)-Projections!$E$8*((1-Assumptions!$C$7)+Assumptions!$C$7*((1+$B$4*F$6)/(1+F$6))))-Projections!$E$9-Debt_Schedule!$E$22)*Assumptions!$C$5)-Assumptions!$C$9*((Projections!$E$7*(1+$A10))*(Assumptions!$C$6+(1-Assumptions!$C$6)*((1+$B$4*F$6)/(1+F$6))))-MAX(0,Assumptions!$C$8*(((Projections!$E$7*(1+$A10))*(Assumptions!$C$6+(1-Assumptions!$C$6)*((1+$B$4*F$6)/(1+F$6))))-(Projections!$D$7*(1+$A10)*(Assumptions!$C$6+(1-Assumptions!$C$6)*((1+$B$4*F$6)/(1+F$6)))))))/Debt_Schedule!$E$24 -> 0.959624 | G10: =((((Projections!$E$7*(1+$A10))*(Assumptions!$C$6+(1-Assumptions!$C$6)*((1+$B$4*G$6)/(1+G$6))))-(Projections!$E$7*(1+$A10))*(Assumptions!$E$34+Assumptions!$E$35)-Projections!$E$8*((1-Assumptions!$C$7)+Assumptions!$C$7*((1+$B$4*G$6)/(1+G$6))))-MAX(0,((((Projections!$E$7*(1+$A10))*(Assumptions!$C$6+(1-Assumptions!$C$6)*((1+$B$4*G$6)/(1+G$6))))-(Projections!$E$7*(1+$A10))*(Assumptions!$E$34+Assumptions!$E$35)-Projections!$E$8*((1-Assumptions!$C$7)+Assumptions!$C$7*((1+$B$4*G$6)/(1+G$6))))-Projections!$E$9-Debt_Schedule!$E$22)*Assumptions!$C$5)-Assumptions!$C$9*((Projections!$E$7*(1+$A10))*(Assumptions!$C$6+(1-Assumptions!$C$6)*((1+$B$4*G$6)/(1+G$6))))-MAX(0,Assumptions!$C$8*(((Projections!$E$7*(1+$A10))*(Assumptions!$C$6+(1-Assumptions!$C$6)*((1+$B$4*G$6)/(1+G$6))))-(Projections!$D$7*(1+$A10)*(Assumptions!$C$6+(1-Assumptions!$C$6)*((1+$B$4*G$6)/(1+G$6)))))))/Debt_Schedule!$E$24 -> 0.87617656
A11: -0.2 | C11: =((((Projections!$E$7*(1+$A11))*(Assumptions!$C$6+(1-Assumptions!$C$6)*((1+$B$4*C$6)/(1+C$6))))-(Projections!$E$7*(1+$A11))*(Assumptions!$E$34+Assumptions!$E$35)-Projections!$E$8*((1-Assumptions!$C$7)+Assumptions!$C$7*((1+$B$4*C$6)/(1+C$6))))-MAX(0,((((Projections!$E$7*(1+$A11))*(Assumptions!$C$6+(1-Assumptions!$C$6)*((1+$B$4*C$6)/(1+C$6))))-(Projections!$E$7*(1+$A11))*(Assumptions!$E$34+Assumptions!$E$35)-Projections!$E$8*((1-Assumptions!$C$7)+Assumptions!$C$7*((1+$B$4*C$6)/(1+C$6))))-Projections!$E$9-Debt_Schedule!$E$22)*Assumptions!$C$5)-Assumptions!$C$9*((Projections!$E$7*(1+$A11))*(Assumptions!$C$6+(1-Assumptions!$C$6)*((1+$B$4*C$6)/(1+C$6))))-MAX(0,Assumptions!$C$8*(((Projections!$E$7*(1+$A11))*(Assumptions!$C$6+(1-Assumptions!$C$6)*((1+$B$4*C$6)/(1+C$6))))-(Projections!$D$7*(1+$A11)*(Assumptions!$C$6+(1-Assumptions!$C$6)*((1+$B$4*C$6)/(1+C$6)))))))/Debt_Schedule!$E$24 -> 1.2891265 | D11: =((((Projections!$E$7*(1+$A11))*(Assumptions!$C$6+(1-Assumptions!$C$6)*((1+$B$4*D$6)/(1+D$6))))-(Projections!$E$7*(1+$A11))*(Assumptions!$E$34+Assumptions!$E$35)-Projections!$E$8*((1-Assumptions!$C$7)+Assumptions!$C$7*((1+$B$4*D$6)/(1+D$6))))-MAX(0,((((Projections!$E$7*(1+$A11))*(Assumptions!$C$6+(1-Assumptions!$C$6)*((1+$B$4*D$6)/(1+D$6))))-(Projections!$E$7*(1+$A11))*(Assumptions!$E$34+Assumptions!$E$35)-Projections!$E$8*((1-Assumptions!$C$7)+Assumptions!$C$7*((1+$B$4*D$6)/(1+D$6))))-Projections!$E$9-Debt_Schedule!$E$22)*Assumptions!$C$5)-Assumptions!$C$9*((Projections!$E$7*(1+$A11))*(Assumptions!$C$6+(1-Assumptions!$C$6)*((1+$B$4*D$6)/(1+D$6))))-MAX(0,Assumptions!$C$8*(((Projections!$E$7*(1+$A11))*(Assumptions!$C$6+(1-Assumptions!$C$6)*((1+$B$4*D$6)/(1+D$6))))-(Projections!$D$7*(1+$A11)*(Assumptions!$C$6+(1-Assumptions!$C$6)*((1+$B$4*D$6)/(1+D$6)))))))/Debt_Schedule!$E$24 -> 1.1032803 | E11: =((((Projections!$E$7*(1+$A11))*(Assumptions!$C$6+(1-Assumptions!$C$6)*((1+$B$4*E$6)/(1+E$6))))-(Projections!$E$7*(1+$A11))*(Assumptions!$E$34+Assumptions!$E$35)-Projections!$E$8*((1-Assumptions!$C$7)+Assumptions!$C$7*((1+$B$4*E$6)/(1+E$6))))-MAX(0,((((Projections!$E$7*(1+$A11))*(Assumptions!$C$6+(1-Assumptions!$C$6)*((1+$B$4*E$6)/(1+E$6))))-(Projections!$E$7*(1+$A11))*(Assumptions!$E$34+Assumptions!$E$35)-Projections!$E$8*((1-Assumptions!$C$7)+Assumptions!$C$7*((1+$B$4*E$6)/(1+E$6))))-Projections!$E$9-Debt_Schedule!$E$22)*Assumptions!$C$5)-Assumptions!$C$9*((Projections!$E$7*(1+$A11))*(Assumptions!$C$6+(1-Assumptions!$C$6)*((1+$B$4*E$6)/(1+E$6))))-MAX(0,Assumptions!$C$8*(((Projections!$E$7*(1+$A11))*(Assumptions!$C$6+(1-Assumptions!$C$6)*((1+$B$4*E$6)/(1+E$6))))-(Projections!$D$7*(1+$A11)*(Assumptions!$C$6+(1-Assumptions!$C$6)*((1+$B$4*E$6)/(1+E$6)))))))/Debt_Schedule!$E$24 -> 0.97053303 | F11: =((((Projections!$E$7*(1+$A11))*(Assumptions!$C$6+(1-Assumptions!$C$6)*((1+$B$4*F$6)/(1+F$6))))-(Projections!$E$7*(1+$A11))*(Assumptions!$E$34+Assumptions!$E$35)-Projections!$E$8*((1-Assumptions!$C$7)+Assumptions!$C$7*((1+$B$4*F$6)/(1+F$6))))-MAX(0,((((Projections!$E$7*(1+$A11))*(Assumptions!$C$6+(1-Assumptions!$C$6)*((1+$B$4*F$6)/(1+F$6))))-(Projections!$E$7*(1+$A11))*(Assumptions!$E$34+Assumptions!$E$35)-Projections!$E$8*((1-Assumptions!$C$7)+Assumptions!$C$7*((1+$B$4*F$6)/(1+F$6))))-Projections!$E$9-Debt_Schedule!$E$22)*Assumptions!$C$5)-Assumptions!$C$9*((Projections!$E$7*(1+$A11))*(Assumptions!$C$6+(1-Assumptions!$C$6)*((1+$B$4*F$6)/(1+F$6))))-MAX(0,Assumptions!$C$8*(((Projections!$E$7*(1+$A11))*(Assumptions!$C$6+(1-Assumptions!$C$6)*((1+$B$4*F$6)/(1+F$6))))-(Projections!$D$7*(1+$A11)*(Assumptions!$C$6+(1-Assumptions!$C$6)*((1+$B$4*F$6)/(1+F$6)))))))/Debt_Schedule!$E$24 -> 0.87097258 | G11: =((((Projections!$E$7*(1+$A11))*(Assumptions!$C$6+(1-Assumptions!$C$6)*((1+$B$4*G$6)/(1+G$6))))-(Projections!$E$7*(1+$A11))*(Assumptions!$E$34+Assumptions!$E$35)-Projections!$E$8*((1-Assumptions!$C$7)+Assumptions!$C$7*((1+$B$4*G$6)/(1+G$6))))-MAX(0,((((Projections!$E$7*(1+$A11))*(Assumptions!$C$6+(1-Assumptions!$C$6)*((1+$B$4*G$6)/(1+G$6))))-(Projections!$E$7*(1+$A11))*(Assumptions!$E$34+Assumptions!$E$35)-Projections!$E$8*((1-Assumptions!$C$7)+Assumptions!$C$7*((1+$B$4*G$6)/(1+G$6))))-Projections!$E$9-Debt_Schedule!$E$22)*Assumptions!$C$5)-Assumptions!$C$9*((Projections!$E$7*(1+$A11))*(Assumptions!$C$6+(1-Assumptions!$C$6)*((1+$B$4*G$6)/(1+G$6))))-MAX(0,Assumptions!$C$8*(((Projections!$E$7*(1+$A11))*(Assumptions!$C$6+(1-Assumptions!$C$6)*((1+$B$4*G$6)/(1+G$6))))-(Projections!$D$7*(1+$A11)*(Assumptions!$C$6+(1-Assumptions!$C$6)*((1+$B$4*G$6)/(1+G$6)))))))/Debt_Schedule!$E$24 -> 0.79353667
A12: -0.25 | C12: =((((Projections!$E$7*(1+$A12))*(Assumptions!$C$6+(1-Assumptions!$C$6)*((1+$B$4*C$6)/(1+C$6))))-(Projections!$E$7*(1+$A12))*(Assumptions!$E$34+Assumptions!$E$35)-Projections!$E$8*((1-Assumptions!$C$7)+Assumptions!$C$7*((1+$B$4*C$6)/(1+C$6))))-MAX(0,((((Projections!$E$7*(1+$A12))*(Assumptions!$C$6+(1-Assumptions!$C$6)*((1+$B$4*C$6)/(1+C$6))))-(Projections!$E$7*(1+$A12))*(Assumptions!$E$34+Assumptions!$E$35)-Projections!$E$8*((1-Assumptions!$C$7)+Assumptions!$C$7*((1+$B$4*C$6)/(1+C$6))))-Projections!$E$9-Debt_Schedule!$E$22)*Assumptions!$C$5)-Assumptions!$C$9*((Projections!$E$7*(1+$A12))*(Assumptions!$C$6+(1-Assumptions!$C$6)*((1+$B$4*C$6)/(1+C$6))))-MAX(0,Assumptions!$C$8*(((Projections!$E$7*(1+$A12))*(Assumptions!$C$6+(1-Assumptions!$C$6)*((1+$B$4*C$6)/(1+C$6))))-(Projections!$D$7*(1+$A12)*(Assumptions!$C$6+(1-Assumptions!$C$6)*((1+$B$4*C$6)/(1+C$6)))))))/Debt_Schedule!$E$24 -> 1.1680128 | D12: =((((Projections!$E$7*(1+$A12))*(Assumptions!$C$6+(1-Assumptions!$C$6)*((1+$B$4*D$6)/(1+D$6))))-(Projections!$E$7*(1+$A12))*(Assumptions!$E$34+Assumptions!$E$35)-Projections!$E$8*((1-Assumptions!$C$7)+Assumptions!$C$7*((1+$B$4*D$6)/(1+D$6))))-MAX(0,((((Projections!$E$7*(1+$A12))*(Assumptions!$C$6+(1-Assumptions!$C$6)*((1+$B$4*D$6)/(1+D$6))))-(Projections!$E$7*(1+$A12))*(Assumptions!$E$34+Assumptions!$E$35)-Projections!$E$8*((1-Assumptions!$C$7)+Assumptions!$C$7*((1+$B$4*D$6)/(1+D$6))))-Projections!$E$9-Debt_Schedule!$E$22)*Assumptions!$C$5)-Assumptions!$C$9*((Projections!$E$7*(1+$A12))*(Assumptions!$C$6+(1-Assumptions!$C$6)*((1+$B$4*D$6)/(1+D$6))))-MAX(0,Assumptions!$C$8*(((Projections!$E$7*(1+$A12))*(Assumptions!$C$6+(1-Assumptions!$C$6)*((1+$B$4*D$6)/(1+D$6))))-(Projections!$D$7*(1+$A12)*(Assumptions!$C$6+(1-Assumptions!$C$6)*((1+$B$4*D$6)/(1+D$6)))))))/Debt_Schedule!$E$24 -> 0.99659428 | E12: =((((Projections!$E$7*(1+$A12))*(Assumptions!$C$6+(1-Assumptions!$C$6)*((1+$B$4*E$6)/(1+E$6))))-(Projections!$E$7*(1+$A12))*(Assumptions!$E$34+Assumptions!$E$35)-Projections!$E$8*((1-Assumptions!$C$7)+Assumptions!$C$7*((1+$B$4*E$6)/(1+E$6))))-MAX(0,((((Projections!$E$7*(1+$A12))*(Assumptions!$C$6+(1-Assumptions!$C$6)*((1+$B$4*E$6)/(1+E$6))))-(Projections!$E$7*(1+$A12))*(Assumptions!$E$34+Assumptions!$E$35)-Projections!$E$8*((1-Assumptions!$C$7)+Assumptions!$C$7*((1+$B$4*E$6)/(1+E$6))))-Projections!$E$9-Debt_Schedule!$E$22)*Assumptions!$C$5)-Assumptions!$C$9*((Projections!$E$7*(1+$A12))*(Assumptions!$C$6+(1-Assumptions!$C$6)*((1+$B$4*E$6)/(1+E$6))))-MAX(0,Assumptions!$C$8*(((Projections!$E$7*(1+$A12))*(Assumptions!$C$6+(1-Assumptions!$C$6)*((1+$B$4*E$6)/(1+E$6))))-(Projections!$D$7*(1+$A12)*(Assumptions!$C$6+(1-Assumptions!$C$6)*((1+$B$4*E$6)/(1+E$6)))))))/Debt_Schedule!$E$24 -> 0.87415249 | F12: =((((Projections!$E$7*(1+$A12))*(Assumptions!$C$6+(1-Assumptions!$C$6)*((1+$B$4*F$6)/(1+F$6))))-(Projections!$E$7*(1+$A12))*(Assumptions!$E$34+Assumptions!$E$35)-Projections!$E$8*((1-Assumptions!$C$7)+Assumptions!$C$7*((1+$B$4*F$6)/(1+F$6))))-MAX(0,((((Projections!$E$7*(1+$A12))*(Assumptions!$C$6+(1-Assumptions!$C$6)*((1+$B$4*F$6)/(1+F$6))))-(Projections!$E$7*(1+$A12))*(Assumptions!$E$34+Assumptions!$E$35)-Projections!$E$8*((1-Assumptions!$C$7)+Assumptions!$C$7*((1+$B$4*F$6)/(1+F$6))))-Projections!$E$9-Debt_Schedule!$E$22)*Assumptions!$C$5)-Assumptions!$C$9*((Projections!$E$7*(1+$A12))*(Assumptions!$C$6+(1-Assumptions!$C$6)*((1+$B$4*F$6)/(1+F$6))))-MAX(0,Assumptions!$C$8*(((Projections!$E$7*(1+$A12))*(Assumptions!$C$6+(1-Assumptions!$C$6)*((1+$B$4*F$6)/(1+F$6))))-(Projections!$D$7*(1+$A12)*(Assumptions!$C$6+(1-Assumptions!$C$6)*((1+$B$4*F$6)/(1+F$6)))))))/Debt_Schedule!$E$24 -> 0.78232115 | G12: =((((Projections!$E$7*(1+$A12))*(Assumptions!$C$6+(1-Assumptions!$C$6)*((1+$B$4*G$6)/(1+G$6))))-(Projections!$E$7*(1+$A12))*(Assumptions!$E$34+Assumptions!$E$35)-Projections!$E$8*((1-Assumptions!$C$7)+Assumptions!$C$7*((1+$B$4*G$6)/(1+G$6))))-MAX(0,((((Projections!$E$7*(1+$A12))*(Assumptions!$C$6+(1-Assumptions!$C$6)*((1+$B$4*G$6)/(1+G$6))))-(Projections!$E$7*(1+$A12))*(Assumptions!$E$34+Assumptions!$E$35)-Projections!$E$8*((1-Assumptions!$C$7)+Assumptions!$C$7*((1+$B$4*G$6)/(1+G$6))))-Projections!$E$9-Debt_Schedule!$E$22)*Assumptions!$C$5)-Assumptions!$C$9*((Projections!$E$7*(1+$A12))*(Assumptions!$C$6+(1-Assumptions!$C$6)*((1+$B$4*G$6)/(1+G$6))))-MAX(0,Assumptions!$C$8*(((Projections!$E$7*(1+$A12))*(Assumptions!$C$6+(1-Assumptions!$C$6)*((1+$B$4*G$6)/(1+G$6))))-(Projections!$D$7*(1+$A12)*(Assumptions!$C$6+(1-Assumptions!$C$6)*((1+$B$4*G$6)/(1+G$6)))))))/Debt_Schedule!$E$24 -> 0.71089678
A13: -0.3 | C13: =((((Projections!$E$7*(1+$A13))*(Assumptions!$C$6+(1-Assumptions!$C$6)*((1+$B$4*C$6)/(1+C$6))))-(Projections!$E$7*(1+$A13))*(Assumptions!$E$34+Assumptions!$E$35)-Projections!$E$8*((1-Assumptions!$C$7)+Assumptions!$C$7*((1+$B$4*C$6)/(1+C$6))))-MAX(0,((((Projections!$E$7*(1+$A13))*(Assumptions!$C$6+(1-Assumptions!$C$6)*((1+$B$4*C$6)/(1+C$6))))-(Projections!$E$7*(1+$A13))*(Assumptions!$E$34+Assumptions!$E$35)-Projections!$E$8*((1-Assumptions!$C$7)+Assumptions!$C$7*((1+$B$4*C$6)/(1+C$6))))-Projections!$E$9-Debt_Schedule!$E$22)*Assumptions!$C$5)-Assumptions!$C$9*((Projections!$E$7*(1+$A13))*(Assumptions!$C$6+(1-Assumptions!$C$6)*((1+$B$4*C$6)/(1+C$6))))-MAX(0,Assumptions!$C$8*(((Projections!$E$7*(1+$A13))*(Assumptions!$C$6+(1-Assumptions!$C$6)*((1+$B$4*C$6)/(1+C$6))))-(Projections!$D$7*(1+$A13)*(Assumptions!$C$6+(1-Assumptions!$C$6)*((1+$B$4*C$6)/(1+C$6)))))))/Debt_Schedule!$E$24 -> 1.0468991 | D13: =((((Projections!$E$7*(1+$A13))*(Assumptions!$C$6+(1-Assumptions!$C$6)*((1+$B$4*D$6)/(1+D$6))))-(Projections!$E$7*(1+$A13))*(Assumptions!$E$34+Assumptions!$E$35)-Projections!$E$8*((1-Assumptions!$C$7)+Assumptions!$C$7*((1+$B$4*D$6)/(1+D$6))))-MAX(0,((((Projections!$E$7*(1+$A13))*(Assumptions!$C$6+(1-Assumptions!$C$6)*((1+$B$4*D$6)/(1+D$6))))-(Projections!$E$7*(1+$A13))*(Assumptions!$E$34+Assumptions!$E$35)-Projections!$E$8*((1-Assumptions!$C$7)+Assumptions!$C$7*((1+$B$4*D$6)/(1+D$6))))-Projections!$E$9-Debt_Schedule!$E$22)*Assumptions!$C$5)-Assumptions!$C$9*((Projections!$E$7*(1+$A13))*(Assumptions!$C$6+(1-Assumptions!$C$6)*((1+$B$4*D$6)/(1+D$6))))-MAX(0,Assumptions!$C$8*(((Projections!$E$7*(1+$A13))*(Assumptions!$C$6+(1-Assumptions!$C$6)*((1+$B$4*D$6)/(1+D$6))))-(Projections!$D$7*(1+$A13)*(Assumptions!$C$6+(1-Assumptions!$C$6)*((1+$B$4*D$6)/(1+D$6)))))))/Debt_Schedule!$E$24 -> 0.88990825 | E13: =((((Projections!$E$7*(1+$A13))*(Assumptions!$C$6+(1-Assumptions!$C$6)*((1+$B$4*E$6)/(1+E$6))))-(Projections!$E$7*(1+$A13))*(Assumptions!$E$34+Assumptions!$E$35)-Projections!$E$8*((1-Assumptions!$C$7)+Assumptions!$C$7*((1+$B$4*E$6)/(1+E$6))))-MAX(0,((((Projections!$E$7*(1+$A13))*(Assumptions!$C$6+(1-Assumptions!$C$6)*((1+$B$4*E$6)/(1+E$6))))-(Projections!$E$7*(1+$A13))*(Assumptions!$E$34+Assumptions!$E$35)-Projections!$E$8*((1-Assumptions!$C$7)+Assumptions!$C$7*((1+$B$4*E$6)/(1+E$6))))-Projections!$E$9-Debt_Schedule!$E$22)*Assumptions!$C$5)-Assumptions!$C$9*((Projections!$E$7*(1+$A13))*(Assumptions!$C$6+(1-Assumptions!$C$6)*((1+$B$4*E$6)/(1+E$6))))-MAX(0,Assumptions!$C$8*(((Projections!$E$7*(1+$A13))*(Assumptions!$C$6+(1-Assumptions!$C$6)*((1+$B$4*E$6)/(1+E$6))))-(Projections!$D$7*(1+$A13)*(Assumptions!$C$6+(1-Assumptions!$C$6)*((1+$B$4*E$6)/(1+E$6)))))))/Debt_Schedule!$E$24 -> 0.77777195 | F13: =((((Projections!$E$7*(1+$A13))*(Assumptions!$C$6+(1-Assumptions!$C$6)*((1+$B$4*F$6)/(1+F$6))))-(Projections!$E$7*(1+$A13))*(Assumptions!$E$34+Assumptions!$E$35)-Projections!$E$8*((1-Assumptions!$C$7)+Assumptions!$C$7*((1+$B$4*F$6)/(1+F$6))))-MAX(0,((((Projections!$E$7*(1+$A13))*(Assumptions!$C$6+(1-Assumptions!$C$6)*((1+$B$4*F$6)/(1+F$6))))-(Projections!$E$7*(1+$A13))*(Assumptions!$E$34+Assumptions!$E$35)-Projections!$E$8*((1-Assumptions!$C$7)+Assumptions!$C$7*((1+$B$4*F$6)/(1+F$6))))-Projections!$E$9-Debt_Schedule!$E$22)*Assumptions!$C$5)-Assumptions!$C$9*((Projections!$E$7*(1+$A13))*(Assumptions!$C$6+(1-Assumptions!$C$6)*((1+$B$4*F$6)/(1+F$6))))-MAX(0,Assumptions!$C$8*(((Projections!$E$7*(1+$A13))*(Assumptions!$C$6+(1-Assumptions!$C$6)*((1+$B$4*F$6)/(1+F$6))))-(Projections!$D$7*(1+$A13)*(Assumptions!$C$6+(1-Assumptions!$C$6)*((1+$B$4*F$6)/(1+F$6)))))))/Debt_Schedule!$E$24 -> 0.69366973 | G13: =((((Projections!$E$7*(1+$A13))*(Assumptions!$C$6+(1-Assumptions!$C$6)*((1+$B$4*G$6)/(1+G$6))))-(Projections!$E$7*(1+$A13))*(Assumptions!$E$34+Assumptions!$E$35)-Projections!$E$8*((1-Assumptions!$C$7)+Assumptions!$C$7*((1+$B$4*G$6)/(1+G$6))))-MAX(0,((((Projections!$E$7*(1+$A13))*(Assumptions!$C$6+(1-Assumptions!$C$6)*((1+$B$4*G$6)/(1+G$6))))-(Projections!$E$7*(1+$A13))*(Assumptions!$E$34+Assumptions!$E$35)-Projections!$E$8*((1-Assumptions!$C$7)+Assumptions!$C$7*((1+$B$4*G$6)/(1+G$6))))-Projections!$E$9-Debt_Schedule!$E$22)*Assumptions!$C$5)-Assumptions!$C$9*((Projections!$E$7*(1+$A13))*(Assumptions!$C$6+(1-Assumptions!$C$6)*((1+$B$4*G$6)/(1+G$6))))-MAX(0,Assumptions!$C$8*(((Projections!$E$7*(1+$A13))*(Assumptions!$C$6+(1-Assumptions!$C$6)*((1+$B$4*G$6)/(1+G$6))))-(Projections!$D$7*(1+$A13)*(Assumptions!$C$6+(1-Assumptions!$C$6)*((1+$B$4*G$6)/(1+G$6)))))))/Debt_Schedule!$E$24 -> 0.62825688
A15: Base case FY2028 DSCR (Projections) | C15: =Projections!E30 -> 1.7735813
A16: Grid cell (0%, 0%) – must equal base | C16: =C7 -> 1.7735813
A17: Covenant minimum DSCR | C17: =Assumptions!$C$51 -> 1.25
A18: Cells below covenant (count) | C18: =COUNTIF(C7:G13,"<"&Assumptions!$C$51) -> 25
A19: Cells below 1.00x (count) | C19: =COUNTIF(C7:G13,"<1") -> 14

Sheet Collateral
A1: Collateral Analysis
A2: Independent valuation (fictional) dated Sep-2026. Haircuts reflect enforcement time, illiquidity and title risk in Aleppo.
A4: Security item | B4: Basis of value | C4: Market value | D4: Haircut | E4: Lending value | F4: Rationale for haircut
A5: First-degree mortgage: factory land & buildings, Sheikh Najjar Industrial City | B5: Independent valuer, Sep-2026 | C5: 2600 | D5: 0.4 | E5: =C5*(1-D5) -> 1560 | F5: Thin real-estate market, 12–24m enforcement, title/registry checks
A6: Pledge over new press, bottling line & solar PV | B6: Invoice cost (CIF Aleppo) | C6: 3200 | D6: 0.55 | E6: =C6*(1-D6) -> 1440 | F6: Specialised assets; resale and removal costs
A7: Assignment of eligible export receivables | B7: Avg. eligible balance | C7: 1000 | D7: 0.3 | E7: =C7*(1-D7) -> 700 | F7: Gulf buyers on LC / credit insurance
A8: Pledge over finished-goods inventory (olive oil) | B8: Avg. stock at cost | C8: 1200 | D8: 0.5 | E8: =C8*(1-D8) -> 600 | F8: Seasonality, price swings, storage control
A9: Cash collateral – Debt Service Reserve Account | B9: Cash at BAC | C9: =Debt_Schedule!C27 -> 278.0125 | D9: 0 | E9: =C9*(1-D9) -> 278.0125 | F9: Cash held at BAC; no haircut
A10: Personal guarantee of majority shareholder (not valued) | B10: Support only | C10: 0 | E10: 0
A11: TOTAL SECURITY | C11: =SUM(C5:C10) -> 8278.0125 | D11: =1-E11/C11 -> 0.44696719 | E11: =SUM(E5:E10) -> 4578.0125
A13: Exposure & coverage
A14: Total BAC exposure (TL + RCF limit) | C14: =Assumptions!$C$12+Assumptions!$C$17 -> 3300
A15: LTV on market value | B15: Exposure / market value | C15: =C14/C11 -> 0.39864641
A16: LTV on lending value (post-haircut) | B16: Exposure / lending value | C16: =C14/E11 -> 0.72083683
A17: Collateral coverage (lending value / exposure) | C17: =E11/C14 -> 1.3872765
A18: Term loan LTV on real estate + equipment (market) | C18: =Assumptions!$C$12/(C5+C6) -> 0.4137931
A19: Term loan LTV on real estate + equipment (lending value) | C19: =Assumptions!$C$12/(E5+E6) -> 0.8
A20: RCF borrowing base (receivables + inventory lending value) | C20: =E7+E8 -> 1300
A21: RCF limit covered by borrowing base | C21: =C20/Assumptions!$C$17 -> 1.4444444
A23: Stress: real-estate value falls 30% and equipment 20%
A24: Stressed lending value | C24: =E11-E5*0.3-E6*0.2 -> 3822.0125
A25: Stressed coverage | C25: =C24/C14 -> 1.1581856
A26: Stressed LTV on lending value | C26: =C14/C24 -> 0.86341947
A27: BAC policy: max LTV on lending value | C27: 0.85
A28: Within policy? | C28: =IF(C16<=C27,"YES","NO") -> YES

Sheet Scorecard
A1: Internal Risk Rating Scorecard
A2: Scores 1 (weak) to 10 (strong). Quantitative scores are formula-driven; qualitative scores are analyst inputs.
A4: Factor | B4: Weight | C4: Metric | D4: Score | E4: Weighted | F4: Basis
A5: Financial risk (50%)
A6: Minimum base-case DSCR | B6: 0.15 | C6: =Projections!I30 -> 1.7735813 | D6: =IF(C6>=2,9,IF(C6>=1.75,8,IF(C6>=1.5,7,IF(C6>=1.25,5,IF(C6>=1.1,3,1))))) -> 8 | E6: =B6*D6 -> 1.2 | F6: ≥2.0x=9; ≥1.75x=8; ≥1.5x=7; ≥1.25x=5; ≥1.1x=3
A7: Minimum downside-case DSCR | B7: 0.1 | C7: =Projections!I55 -> 1.271525 | D7: =IF(C7>=1.5,9,IF(C7>=1.3,7,IF(C7>=1.15,5,IF(C7>=1,3,1)))) -> 5 | E7: =B7*D7 -> 0.5 | F7: ≥1.5x=9; ≥1.3x=7; ≥1.15x=5; ≥1.0x=3
A8: Pro-forma Debt / EBITDA at drawdown | B8: 0.1 | C8: =Debt_Schedule!C26/Projections!C10 -> 1.7254389 | D8: =IF(C8<=1.5,9,IF(C8<=2,8,IF(C8<=2.5,7,IF(C8<=3,5,IF(C8<=4,3,1))))) -> 8 | E8: =B8*D8 -> 0.8 | F8: ≤1.5x=9; ≤2.0x=8; ≤2.5x=7; ≤3.0x=5; ≤4.0x=3
A9: EBITDA margin FY2025 | B9: 0.1 | C9: =Ratios!F7 -> 0.20767494 | D9: =IF(C9>=0.25,9,IF(C9>=0.2,8,IF(C9>=0.15,7,IF(C9>=0.1,5,3)))) -> 8 | E9: =B9*D9 -> 0.8 | F9: ≥25%=9; ≥20%=8; ≥15%=7; ≥10%=5
A10: Current ratio FY2025 | B10: 0.05 | C10: =Ratios!F12 -> 2.2770449 | D10: =IF(C10>=2,9,IF(C10>=1.5,7,IF(C10>=1.2,5,3))) -> 9 | E10: =B10*D10 -> 0.45 | F10: ≥2.0x=9; ≥1.5x=7; ≥1.2x=5
A11: Business risk (25%)
A12: Industry outlook (olive oil & soap exports) | B12: 0.05 | D12: 7 | E12: =B12*D12 -> 0.35 | F12: Growing Gulf demand; reconstruction tailwinds; climate-driven harvest swings
A13: Market position, diversification & growth | B13: 0.1 | D13: 7 | E13: =B13*D13 -> 0.7 | F13: 28-year track record; 55% exports to 5 countries; revenue CAGR ~20%
A14: Management, governance & transparency | B14: 0.1 | D14: 6 | E14: =B14*D14 -> 0.6 | F14: Experienced family owners; audited by local firm; key-person risk; board lacks independents
A15: Country & external risk (15%)
A16: Country, FX convertibility & sanctions legacy | B16: 0.1 | D16: 3 | E16: =B16*D16 -> 0.3 | F16: Sanctions lifted 2025 but correspondent banking still thin; SYP volatility
A17: Energy & supply chain | B17: 0.05 | D17: 5 | E17: =B17*D17 -> 0.25 | F17: Grid unreliable; solar PV cuts diesel need; imported packaging and spares
A18: Security (10%)
A19: Collateral coverage (lending value / exposure) | B19: 0.05 | C19: =Collateral!C17 -> 1.3872765 | D19: =IF(C19>=1.5,9,IF(C19>=1.25,7,IF(C19>=1,5,2))) -> 7 | E19: =B19*D19 -> 0.35 | F19: ≥1.5x=9; ≥1.25x=7; ≥1.0x=5
A20: Enforceability of security in Aleppo | B20: 0.05 | D20: 4 | E20: =B20*D20 -> 0.2 | F20: Courts reopening; registry gaps; long enforcement timelines
A22: TOTAL | B22: =B6+B7+B8+B9+B10+B12+B13+B14+B16+B17+B19+B20 -> 1 | E22: =E6+E7+E8+E9+E10+E12+E13+E14+E16+E17+E19+E20 -> 6.5
A24: Rating outcome
A25: Scorecard grade (before country cap) | C25: =IF(E22>=8,2,IF(E22>=7,3,IF(E22>=6,4,IF(E22>=5,5,IF(E22>=4,6,7))))) -> 4
A26: Country ceiling for Syrian corporates (best grade) | C26: 4
A27: FINAL INTERNAL RATING | C27: =MAX(C25,C26) -> 4
A28: Description | C28: =CHOOSE(C27,"Exceptional","Strong","Good","Satisfactory","Acceptable","Watch","Substandard") -> Satisfactory
A29: Indicative 1-year PD (illustrative master scale) | C29: =CHOOSE(C27,0.0005,0.002,0.006,0.015,0.035,0.08,0.18) -> 0.015
A31: Master scale: score ≥8.0 = BAC-2 Strong; ≥7.0 = BAC-3 Good; ≥6.0 = BAC-4 Satisfactory; ≥5.0 = BAC-5 Acceptable; ≥4.0 = BAC-6 Watch; <4.0 = BAC-7 Substandard.

Sheet Checks
A1: Model Integrity Checks
A2: All checks should read TRUE.
A4: Check | B4: Value | C4: Result
A5: Balance sheet balances – all years (sum of abs differences) | B5: =ABS(BS!C26)+ABS(BS!D26)+ABS(BS!E26)+ABS(BS!F26) -> 0 | C5: =IF(B5<0.001,"PASS","FAIL") -> PASS
A6: CF closing cash ties to BS cash – all years | B6: =ABS(CF!D29)+ABS(CF!E29)+ABS(CF!F29) -> 0 | C6: =IF(B6<0.001,"PASS","FAIL") -> PASS
A7: Retained earnings roll-forward (FY2025 RE – opening – ΣNI + Σdiv) | B7: =BS!F22-BS!C22-SUM(IS!D19:F19)-SUM(IS!D20:F20) -> 0 | C7: =IF(ABS(B7)<0.001,"PASS","FAIL") -> PASS
A8: Term loan fully repaid by FY2031 | B8: =Debt_Schedule!H10 -> 0 | C8: =IF(ABS(B8)<0.001,"PASS","FAIL") -> PASS
A9: Sum of term-loan repayments = facility amount | B9: =SUM(Debt_Schedule!D9:H9)-Assumptions!$C$12 -> 0 | C9: =IF(ABS(B9)<0.001,"PASS","FAIL") -> PASS
A10: Sensitivity grid (0%,0%) reconciles to base FY2028 DSCR | B10: =Sensitivity!C16-Sensitivity!C15 -> 0 | C10: =IF(ABS(B10)<0.000001,"PASS","FAIL") -> PASS
A11: Scorecard weights sum to 100% | B11: =Scorecard!B22 -> 1 | C11: =IF(ABS(B11-1)<0.000001,"PASS","FAIL") -> PASS
A12: Collateral lending value ≤ market value | B12: =Collateral!C11-Collateral!E11 -> 3700 | C12: =IF(B12>=0,"PASS","FAIL") -> PASS
A13: Base FY2028 is the tightest DSCR year | B13: =Projections!E30-Projections!I30 -> 0 | C13: =IF(ABS(B13)<0.000001,"PASS","FAIL") -> PASS
A14: Historical closing cash positive all years | B14: =MIN(BS!C6:F6) -> 287 | C14: =IF(B14>0,"PASS","FAIL") -> PASS
A16: ALL CHECKS PASS | C16: =IF(COUNTIF(C5:C14,"PASS")=10,"ALL PASS","CHECK") -> ALL PASS
