Workbook

Sheet Cover
A1: Investment Portfolio Proposal: Model Workbook
A2: Fictional private-banking client, USD 500,000, moderate risk profile, 10-year horizon. Prepared by Yamen Agha.
A3: Prices to 2026-10-12 (latest daily close available); statistics on 120 monthly returns, Oct 2016 to Sep 2026.
A5: Sheet guide
A6: Allocation | B6: Weights (yellow cells are inputs), USD amounts, costs, income, class totals, checks
A7: Prices | B7: Month-end adjusted closes (total return) and 3-month Treasury yield
A8: Returns | B8: Monthly returns computed by formula from Prices
A9: AssetStats | B9: Annualised mean, CAGR, volatility, Sharpe by formula
A10: Correlation / Covariance | B10: CORREL and COVARIANCE.S matrices by formula
A11: PortfolioRisk | B11: Capital market assumptions, portfolio expected return, volatility, risk contributions, parametric VaR
A12: Backtest | B12: Monthly backtest returns from the Python engine; wealth, drawdown, statistics and calendar years by formula
A13: VaR | B13: Historical and parametric VaR / CVaR by formula (daily and monthly)
A14: Scenarios | B14: Hypothetical shock matrix (inputs) and portfolio impact by formula
A15: Projection | B15: Deterministic 10-year projection with withdrawals, by formula
A16: Checks | B16: Excel results versus the Python results; PASS when they agree
A17: Sources | B17: Data sources and as-of dates

Sheet Allocation
A1: Strategic asset allocation
A2: Investment (USD) | B2: 500000
A3: Assumed US withholding tax on dividends (non-treaty) | B3: 0.3
A5: Ticker | B5: Fund role | C5: Asset class | D5: Target weight | E5: USD amount | F5: Expense ratio | G5: Annual fund cost (USD) | H5: Distribution yield (trailing) | I5: Expected income (USD, gross) | J5: Last price | K5: Shares (rounded down) | L5: Cash residual (USD) | M5: 30% withholding assumed? (1=yes)
A6: VTI | B6: US total stock market | C6: Equity | D6: 0.25 | E6: =D6*$B$2 -> 125000 | F6: 0.0003 | G6: =E6*F6 -> 37.5 | H6: 0.0104 | I6: =E6*H6 -> 1300 | J6: 381.57001 | K6: =ROUNDDOWN(E6/J6,0) -> 327 | L6: =E6-K6*J6 -> 226.60771 | M6: 1
A7: VEA | B7: Developed ex-US equity | C7: Equity | D7: 0.1 | E7: =D7*$B$2 -> 50000 | F7: 0.0003 | G7: =E7*F7 -> 15 | H7: 0.0243 | I7: =E7*H7 -> 1215 | J7: 69.949997 | K7: =ROUNDDOWN(E7/J7,0) -> 714 | L7: =E7-K7*J7 -> 55.702142 | M7: 1
A8: VWO | B8: Emerging markets equity | C8: Equity | D8: 0.05 | E8: =D8*$B$2 -> 25000 | F8: 0.0006 | G8: =E8*F8 -> 15 | H8: 0.0204 | I8: =E8*H8 -> 510 | J8: 59.73 | K8: =ROUNDDOWN(E8/J8,0) -> 418 | L8: =E8-K8*J8 -> 32.86 | M8: 1
A9: KSA | B9: Saudi Arabia equity | C9: Equity | D9: 0.03 | E9: =D9*$B$2 -> 15000 | F9: 0.0075 | G9: =E9*F9 -> 112.5 | H9: 0.0289 | I9: =E9*H9 -> 433.5 | J9: 35.66 | K9: =ROUNDDOWN(E9/J9,0) -> 420 | L9: =E9-K9*J9 -> 22.8 | M9: 1
A10: UAE | B10: UAE equity | C10: Equity | D10: 0.02 | E10: =D10*$B$2 -> 10000 | F10: 0.0059 | G10: =E10*F10 -> 59 | H10: 0.0439 | I10: =E10*H10 -> 439 | J10: 19.309999 | K10: =ROUNDDOWN(E10/J10,0) -> 517 | L10: =E10-K10*J10 -> 16.730517 | M10: 1
A11: VNQ | B11: US REITs | C11: Real assets | D11: 0.03 | E11: =D11*$B$2 -> 15000 | F11: 0.0013 | G11: =E11*F11 -> 19.5 | H11: 0.0374 | I11: =E11*H11 -> 561 | J11: 91.360001 | K11: =ROUNDDOWN(E11/J11,0) -> 164 | L11: =E11-K11*J11 -> 16.959836 | M11: 1
A12: BND | B12: US aggregate bonds | C12: Fixed income | D12: 0.25 | E12: =D12*$B$2 -> 125000 | F12: 0.0003 | G12: =E12*F12 -> 37.5 | H12: 0.0418 | I12: =E12*H12 -> 5225 | J12: 70.25 | K12: =ROUNDDOWN(E12/J12,0) -> 1779 | L12: =E12-K12*J12 -> 25.25 | M12: 0
A13: SCHP | B13: US TIPS | C13: Fixed income | D13: 0.12 | E13: =D13*$B$2 -> 60000 | F13: 0.0003 | G13: =E13*F13 -> 18 | H13: 0.0499 | I13: =E13*H13 -> 2994 | J13: 25.209999 | K13: =ROUNDDOWN(E13/J13,0) -> 2380 | L13: =E13-K13*J13 -> 0.20238 | M13: 0
A14: IAU | B14: Gold | C14: Real assets | D14: 0.07 | E14: =D14*$B$2 -> 35000 | F14: 0.0025 | G14: =E14*F14 -> 87.5 | H14: 0 | I14: =E14*H14 -> 0 | J14: 78.339996 | K14: =ROUNDDOWN(E14/J14,0) -> 446 | L14: =E14-K14*J14 -> 60.361784 | M14: 0
A15: BIL | B15: 1-3 month T-bills | C15: Cash | D15: 0.08 | E15: =D15*$B$2 -> 40000 | F15: 0.0014 | G15: =E15*F15 -> 56 | H15: 0.0366 | I15: =E15*H15 -> 1464 | J15: 91.5 | K15: =ROUNDDOWN(E15/J15,0) -> 437 | L15: =E15-K15*J15 -> 14.5 | M15: 0
A16: Total | D16: =SUM(D6:D15) -> 1 | E16: =SUM(E6:E15) -> 500000 | F16: =SUMPRODUCT(D6:D15,F6:F15) -> 0.000915 | G16: =SUM(G6:G15) -> 457.5 | H16: =SUMPRODUCT(D6:D15,H6:H15) -> 0.028283 | I16: =SUM(I6:I15) -> 14141.5 | L16: =SUM(L6:L15) -> 471.97437
A18: Asset class totals
A19: Equity | D19: =SUMIF(C6:C15,A19,D6:D15) -> 0.45 | E19: =SUMIF(C6:C15,A19,E6:E15) -> 225000
A20: Fixed income | D20: =SUMIF(C6:C15,A20,D6:D15) -> 0.37 | E20: =SUMIF(C6:C15,A20,E6:E15) -> 185000
A21: Real assets | D21: =SUMIF(C6:C15,A21,D6:D15) -> 0.1 | E21: =SUMIF(C6:C15,A21,E6:E15) -> 50000
A22: Cash | D22: =SUMIF(C6:C15,A22,D6:D15) -> 0.08 | E22: =SUMIF(C6:C15,A22,E6:E15) -> 40000
A24: Gulf equity (KSA + UAE) | D24: =D9+D10 -> 0.05
A25: Withholding-tax drag, base case: equity and REIT funds only (% of portfolio) | D25: =SUMPRODUCT(D6:D15,H6:H15,M6:M15)*B3 -> 0.0026751 | E25: Upper bound (all distributions withheld): | I25: =H16*B3 -> 0.0084849
A26: Check: weights sum to 100% | D26: =IF(ABS(D16-1)<0.000001,"PASS","FAIL") -> PASS
A27: Check: equity within 40%-60% policy range | D27: =IF(AND(D19>=0.4,D19<=0.6),"PASS","FAIL") -> PASS
A28: Check: Gulf equity at or below 6% | D28: =IF(D24<=0.06+0.000001,"PASS","FAIL") -> PASS

Sheet Prices
A1: Month end | B1: VTI | C1: VEA | D1: VWO | E1: KSA | F1: UAE | G1: VNQ | H1: BND | I1: SCHP | J1: IAU | K1: BIL | L1: SPY | M1: AGG | N1: AOR | O1: 3M T-bill yield (%)
A2: 42643 | B2: 94.948044 | C2: 27.882143 | D2: 28.550541 | E2: 16.274284 | F2: 11.323173 | G2: 58.245884 | H2: 62.16325 | I2: 20.421568 | J2: 25.379999 | K2: 72.826668 | L2: 184.71916 | M2: 84.235611 | N2: 31.736912 | O2: 0.29
A3: 42674 | B3: 92.867058 | C3: 27.211363 | D3: 28.641579 | E3: 17.196814 | F3: 10.722526 | G3: 54.901806 | H3: 61.579201 | I3: 20.298981 | J3: 24.639999 | K3: 72.842567 | L3: 181.51672 | M3: 83.547234 | N3: 31.234083 | O3: 0.34
A4: 42704 | B4: 97.037529 | C4: 26.801445 | D4: 27.480753 | E4: 19.737307 | F4: 10.575522 | G4: 53.981857 | H4: 59.994267 | I4: 19.892805 | J4: 22.58 | K4: 72.810707 | L4: 188.20352 | M4: 81.40387 | N4: 31.125738 | O4: 0.48
A5: 42735 | B5: 98.965317 | C5: 27.457682 | D5: 27.27787 | E5: 20.125727 | F5: 11.110047 | G5: 56.582214 | H5: 60.192169 | I5: 19.890501 | J5: 22.16 | K5: 72.826683 | L5: 192.01875 | M5: 81.610741 | N5: 31.616926 | O5: 0.51
A6: 42766 | B6: 100.80181 | C6: 28.464619 | D6: 28.848366 | E6: 20.159996 | F6: 11.425748 | G6: 56.472527 | H6: 60.303925 | I6: 20.064604 | J6: 23.34 | K6: 72.858543 | L6: 195.45487 | M6: 81.784393 | N6: 32.029869 | O6: 0.52
A7: 42794 | B7: 104.52634 | C7: 28.765192 | D7: 29.496391 | E7: 19.629263 | F7: 11.324995 | G7: 58.453911 | H7: 60.675716 | I7: 20.137144 | J7: 24.08 | K7: 72.895218 | L7: 203.13457 | M7: 82.312653 | N7: 32.723293 | O7: 0.53
A8: 42825 | B8: 104.58411 | C8: 29.644957 | D8: 30.335539 | E8: 19.792625 | F8: 11.274615 | G8: 57.037163 | H8: 60.651802 | I8: 20.140759 | J8: 24.02 | K8: 72.882423 | L8: 203.38843 | M8: 82.267159 | N8: 33.027138 | O8: 0.76
A9: 42855 | B9: 105.69611 | C9: 30.301222 | D9: 30.80905 | E9: 19.890646 | F9: 11.39888 | G9: 57.175289 | H9: 61.134579 | I9: 20.223913 | J9: 24.42 | K9: 72.936661 | L9: 205.40738 | M9: 83.013367 | N9: 33.483028 | O9: 0.8
A10: 42886 | B10: 106.76507 | C10: 31.33465 | D10: 31.114552 | E10: 19.768721 | F10: 11.345143 | G10: 56.760952 | H10: 61.568787 | I10: 20.242823 | J10: 24.4 | K10: 72.947823 | L10: 208.30626 | M10: 83.58371 | N10: 33.991283 | O10: 0.98
A11: 42916 | B11: 107.77646 | C11: 31.534332 | D11: 31.379169 | E11: 21.835014 | F11: 11.545914 | G11: 58.028191 | H11: 61.600357 | I11: 20.053074 | J11: 23.879999 | K11: 73.022896 | L11: 209.63417 | M11: 83.568443 | N11: 34.100758 | O11: 1.03
A12: 42947 | B12: 109.80295 | C12: 32.442516 | D12: 33.054558 | E12: 20.835854 | F12: 12.229145 | G12: 58.746292 | H12: 61.97757 | I12: 20.158152 | J12: 24.440001 | K12: 73.046829 | L12: 213.9431 | M12: 83.847534 | N12: 34.754276 | O12: 1.07
A13: 42978 | B13: 109.96748 | C13: 32.450134 | D13: 34.045975 | E13: 21.021839 | F13: 12.263651 | G13: 58.592934 | H13: 62.639488 | I13: 20.367895 | J13: 25.440001 | K13: 73.129936 | L13: 214.56726 | M13: 84.636818 | N13: 34.919704 | O13: 1.01
... A122: 46295 | B122: 374.23999 | C122: 70.610001 | D122: 59.310001 | E122: 36.32 | F122: 20.07 | G122: 89.629997 | H122: 69.901001 | I122: 25.073999 | J122: 78.099998 | K122: 91.376999 | L122: 762.63 | M122: 94.206001 | N122: 68.20504 | O122: 4.2

Sheet Returns
A1: Month end | B1: VTI | C1: VEA | D1: VWO | E1: KSA | F1: UAE | G1: VNQ | H1: BND | I1: SCHP | J1: IAU | K1: BIL | L1: SPY | M1: AGG | N1: AOR | O1: Risk-free (monthly)
A2: =Prices!A3 -> 42674 | B2: =Prices!B3/Prices!B2-1 -> -0.021917102 | C2: =Prices!C3/Prices!C2-1 -> -0.024057692 | D2: =Prices!D3/Prices!D2-1 -> 0.0031886611 | E2: =Prices!E3/Prices!E2-1 -> 0.056686365 | F2: =Prices!F3/Prices!F2-1 -> -0.05304582 | G2: =Prices!G3/Prices!G2-1 -> -0.057413121 | H2: =Prices!H3/Prices!H2-1 -> -0.0093954064 | I2: =Prices!I3/Prices!I2-1 -> -0.0060028202 | ... N2: =Prices!N3/Prices!N2-1 -> -0.015843665 | O2: =Prices!O2/100/12 -> 0.00024166667
A3: =Prices!A4 -> 42704 | B3: =Prices!B4/Prices!B3-1 -> 0.044907969 | C3: =Prices!C4/Prices!C3-1 -> -0.015064222 | D3: =Prices!D4/Prices!D3-1 -> -0.0405294 | E3: =Prices!E4/Prices!E3-1 -> 0.14773045 | F3: =Prices!F4/Prices!F3-1 -> -0.013709829 | G3: =Prices!G4/Prices!G3-1 -> -0.016756261 | H3: =Prices!H4/Prices!H3-1 -> -0.025738138 | I3: =Prices!I4/Prices!I3-1 -> -0.020009674 | ... N3: =Prices!N4/Prices!N3-1 -> -0.0034688068 | O3: =Prices!O3/100/12 -> 0.00028333333
A4: =Prices!A5 -> 42735 | B4: =Prices!B5/Prices!B4-1 -> 0.019866417 | C4: =Prices!C5/Prices!C4-1 -> 0.024485135 | D4: =Prices!D5/Prices!D4-1 -> -0.0073827307 | E4: =Prices!E5/Prices!E4-1 -> 0.019679483 | F4: =Prices!F5/Prices!F4-1 -> 0.050543604 | G4: =Prices!G5/Prices!G4-1 -> 0.048170944 | H4: =Prices!H5/Prices!H4-1 -> 0.0032986819 | I4: =Prices!I5/Prices!I4-1 -> -0.00011582077 | ... N4: =Prices!N5/Prices!N4-1 -> 0.015780766 | O4: =Prices!O4/100/12 -> 0.0004
A5: =Prices!A6 -> 42766 | B5: =Prices!B6/Prices!B5-1 -> 0.018556946 | C5: =Prices!C6/Prices!C5-1 -> 0.036672324 | D5: =Prices!D6/Prices!D5-1 -> 0.057573997 | E5: =Prices!E6/Prices!E5-1 -> 0.0017027459 | F5: =Prices!F6/Prices!F5-1 -> 0.028415811 | G5: =Prices!G6/Prices!G5-1 -> -0.001938542 | H5: =Prices!H6/Prices!H5-1 -> 0.0018566535 | I5: =Prices!I6/Prices!I5-1 -> 0.0087530726 | ... N5: =Prices!N6/Prices!N5-1 -> 0.013060821 | O5: =Prices!O5/100/12 -> 0.000425
A6: =Prices!A7 -> 42794 | B6: =Prices!B7/Prices!B6-1 -> 0.036948999 | C6: =Prices!C7/Prices!C6-1 -> 0.01055953 | D6: =Prices!D7/Prices!D6-1 -> 0.022463144 | E6: =Prices!E7/Prices!E6-1 -> -0.026326047 | F6: =Prices!F7/Prices!F6-1 -> -0.008818066 | G6: =Prices!G7/Prices!G6-1 -> 0.035085804 | H6: =Prices!H7/Prices!H6-1 -> 0.0061652869 | I6: =Prices!I7/Prices!I6-1 -> 0.0036153218 | ... N6: =Prices!N7/Prices!N6-1 -> 0.021649292 | O6: =Prices!O6/100/12 -> 0.00043333333
A7: =Prices!A8 -> 42825 | B7: =Prices!B8/Prices!B7-1 -> 0.00055267411 | C7: =Prices!C8/Prices!C7-1 -> 0.03058436 | D7: =Prices!D8/Prices!D7-1 -> 0.028449175 | E7: =Prices!E8/Prices!E7-1 -> 0.0083223705 | F7: =Prices!F8/Prices!F7-1 -> -0.0044485671 | G7: =Prices!G8/Prices!G7-1 -> -0.02423701 | H7: =Prices!H8/Prices!H7-1 -> -0.00039412802 | I7: =Prices!I8/Prices!I7-1 -> 0.000179519 | ... N7: =Prices!N8/Prices!N7-1 -> 0.0092852819 | O7: =Prices!O7/100/12 -> 0.00044166667
A8: =Prices!A9 -> 42855 | B8: =Prices!B9/Prices!B8-1 -> 0.010632667 | C8: =Prices!C9/Prices!C8-1 -> 0.022137492 | D8: =Prices!D9/Prices!D8-1 -> 0.015609118 | E8: =Prices!E9/Prices!E8-1 -> 0.0049524002 | F8: =Prices!F9/Prices!F8-1 -> 0.011021662 | G8: =Prices!G9/Prices!G8-1 -> 0.0024216843 | H8: =Prices!H9/Prices!H8-1 -> 0.007959813 | I8: =Prices!I9/Prices!I8-1 -> 0.0041286428 | ... N8: =Prices!N9/Prices!N8-1 -> 0.013803497 | O8: =Prices!O8/100/12 -> 0.00063333333
A9: =Prices!A10 -> 42886 | B9: =Prices!B10/Prices!B9-1 -> 0.010113465 | C9: =Prices!C10/Prices!C9-1 -> 0.034105159 | D9: =Prices!D10/Prices!D9-1 -> 0.0099159825 | E9: =Prices!E10/Prices!E9-1 -> -0.0061297657 | F9: =Prices!F10/Prices!F9-1 -> -0.0047142351 | G9: =Prices!G10/Prices!G9-1 -> -0.0072467845 | H9: =Prices!H10/Prices!H9-1 -> 0.0071024943 | I9: =Prices!I10/Prices!I9-1 -> 0.00093503171 | ... N9: =Prices!N10/Prices!N9-1 -> 0.015179481 | O9: =Prices!O9/100/12 -> 0.00066666667
A10: =Prices!A11 -> 42916 | B10: =Prices!B11/Prices!B10-1 -> 0.0094730516 | C10: =Prices!C11/Prices!C10-1 -> 0.006372562 | D10: =Prices!D11/Prices!D10-1 -> 0.0085046058 | E10: =Prices!E11/Prices!E10-1 -> 0.10452335 | F10: =Prices!F11/Prices!F10-1 -> 0.017696648 | G10: =Prices!G11/Prices!G10-1 -> 0.022325894 | H10: =Prices!H11/Prices!H10-1 -> 0.00051275982 | I10: =Prices!I11/Prices!I10-1 -> -0.0093736432 | ... N10: =Prices!N11/Prices!N10-1 -> 0.0032206787 | O10: =Prices!O10/100/12 -> 0.00081666667
A11: =Prices!A12 -> 42947 | B11: =Prices!B12/Prices!B11-1 -> 0.018802705 | C11: =Prices!C12/Prices!C11-1 -> 0.028799849 | D11: =Prices!D12/Prices!D11-1 -> 0.053391758 | E11: =Prices!E12/Prices!E11-1 -> -0.045759531 | F11: =Prices!F12/Prices!F11-1 -> 0.059175133 | G11: =Prices!G12/Prices!G11-1 -> 0.012375037 | H11: =Prices!H12/Prices!H11-1 -> 0.0061235522 | I11: =Prices!I12/Prices!I11-1 -> 0.0052399946 | ... N11: =Prices!N12/Prices!N11-1 -> 0.019164325 | O11: =Prices!O11/100/12 -> 0.00085833333
A12: =Prices!A13 -> 42978 | B12: =Prices!B13/Prices!B12-1 -> 0.0014983933 | C12: =Prices!C13/Prices!C12-1 -> 0.00023481533 | D12: =Prices!D13/Prices!D12-1 -> 0.029993352 | E12: =Prices!E13/Prices!E12-1 -> 0.0089262 | F12: =Prices!F13/Prices!F12-1 -> 0.00282162 | G12: =Prices!G13/Prices!G12-1 -> -0.0026105137 | H12: =Prices!H13/Prices!H12-1 -> 0.010679961 | I12: =Prices!I13/Prices!I12-1 -> 0.010404872 | ... N12: =Prices!N13/Prices!N12-1 -> 0.0047599323 | O12: =Prices!O12/100/12 -> 0.00089166667
A13: =Prices!A14 -> 43008 | B13: =Prices!B14/Prices!B13-1 -> 0.024400951 | C13: =Prices!C14/Prices!C13-1 -> 0.025142947 | D13: =Prices!D14/Prices!D13-1 -> -0.0049515104 | E13: =Prices!E14/Prices!E13-1 -> 0.001148948 | F13: =Prices!F14/Prices!F13-1 -> -0.022791174 | G13: =Prices!G14/Prices!G13-1 -> -0.001140769 | H13: =Prices!H14/Prices!H13-1 -> -0.0046878416 | I13: =Prices!I14/Prices!I13-1 -> -0.0073828444 | ... N13: =Prices!N14/Prices!N13-1 -> 0.011279363 | O13: =Prices!O13/100/12 -> 0.00084166667
... A121: =Prices!A122 -> 46295 | B121: =Prices!B122/Prices!B121-1 -> -0.0078422169 | C121: =Prices!C122/Prices!C121-1 -> -0.029283656 | D121: =Prices!D122/Prices!D121-1 -> -0.018125005 | E121: =Prices!E122/Prices!E121-1 -> -0.063917502 | F121: =Prices!F122/Prices!F121-1 -> 0.031876554 | G121: =Prices!G122/Prices!G121-1 -> -0.062553203 | H121: =Prices!H122/Prices!H121-1 -> -0.02551853 | I121: =Prices!I122/Prices!I121-1 -> -0.027213277 | ... N121: =Prices!N122/Prices!N121-1 -> -0.017493574 | O121: =Prices!O121/100/12 -> 0.0032583333

Sheet AssetStats
A1: Asset statistics, monthly returns Oct 2016 to Sep 2026 (annualised)
A3: Ticker | B3: Name | C3: Mean return (arith.) | D3: CAGR | E3: Volatility | F3: Sharpe ratio | G3: Months
A4: VTI | B4: US total stock market | C4: =AVERAGE(Returns!$B$2:$B$121)*12 -> 0.15033 | D4: =EXP(SUMPRODUCT(LN(1+Returns!$B$2:$B$121))*12/COUNT(Returns!$B$2:$B$121))-1 -> 0.14700792 | E4: =_xlfn.STDEV.S(Returns!$B$2:$B$121)*SQRT(12) -> 0.15773362 | F4: =(C4-AVERAGE(Returns!$O$2:$O$121)*12)/E4 -> 0.79543919 | G4: =COUNT(Returns!$B$2:$B$121) -> 120
A5: VEA | B5: Developed ex-US equity | C5: =AVERAGE(Returns!$C$2:$C$121)*12 -> 0.10533543 | D5: =EXP(SUMPRODUCT(LN(1+Returns!$C$2:$C$121))*12/COUNT(Returns!$C$2:$C$121))-1 -> 0.097372333 | E5: =_xlfn.STDEV.S(Returns!$C$2:$C$121)*SQRT(12) -> 0.15541578 | F5: =(C5-AVERAGE(Returns!$O$2:$O$121)*12)/E5 -> 0.51779127 | G5: =COUNT(Returns!$C$2:$C$121) -> 120
A6: VWO | B6: Emerging markets equity | C6: =AVERAGE(Returns!$D$2:$D$121)*12 -> 0.085339327 | D6: =EXP(SUMPRODUCT(LN(1+Returns!$D$2:$D$121))*12/COUNT(Returns!$D$2:$D$121))-1 -> 0.075849095 | E6: =_xlfn.STDEV.S(Returns!$D$2:$D$121)*SQRT(12) -> 0.15518417 | F6: =(C6-AVERAGE(Returns!$O$2:$O$121)*12)/E6 -> 0.38971002 | G6: =COUNT(Returns!$D$2:$D$121) -> 120
A7: KSA | B7: Saudi Arabia equity | C7: =AVERAGE(Returns!$E$2:$E$121)*12 -> 0.096567128 | D7: =EXP(SUMPRODUCT(LN(1+Returns!$E$2:$E$121))*12/COUNT(Returns!$E$2:$E$121))-1 -> 0.083588519 | E7: =_xlfn.STDEV.S(Returns!$E$2:$E$121)*SQRT(12) -> 0.18025163 | F7: =(C7-AVERAGE(Returns!$O$2:$O$121)*12)/E7 -> 0.39780294 | G7: =COUNT(Returns!$E$2:$E$121) -> 120
A8: UAE | B8: UAE equity | C8: =AVERAGE(Returns!$F$2:$F$121)*12 -> 0.073227742 | D8: =EXP(SUMPRODUCT(LN(1+Returns!$F$2:$F$121))*12/COUNT(Returns!$F$2:$F$121))-1 -> 0.058907253 | E8: =_xlfn.STDEV.S(Returns!$F$2:$F$121)*SQRT(12) -> 0.17631771 | F8: =(C8-AVERAGE(Returns!$O$2:$O$121)*12)/E8 -> 0.27430734 | G8: =COUNT(Returns!$F$2:$F$121) -> 120
A9: VNQ | B9: US REITs | C9: =AVERAGE(Returns!$G$2:$G$121)*12 -> 0.058950491 | D9: =EXP(SUMPRODUCT(LN(1+Returns!$G$2:$G$121))*12/COUNT(Returns!$G$2:$G$121))-1 -> 0.044044029 | E9: =_xlfn.STDEV.S(Returns!$G$2:$G$121)*SQRT(12) -> 0.17700042 | F9: =(C9-AVERAGE(Returns!$O$2:$O$121)*12)/E9 -> 0.19258706 | G9: =COUNT(Returns!$G$2:$G$121) -> 120
A10: BND | B10: US aggregate bonds | C10: =AVERAGE(Returns!$H$2:$H$121)*12 -> 0.013103424 | D10: =EXP(SUMPRODUCT(LN(1+Returns!$H$2:$H$121))*12/COUNT(Returns!$H$2:$H$121))-1 -> 0.011800683 | E10: =_xlfn.STDEV.S(Returns!$H$2:$H$121)*SQRT(12) -> 0.052493311 | F10: =(C10-AVERAGE(Returns!$O$2:$O$121)*12)/E10 -> -0.22401095 | G10: =COUNT(Returns!$H$2:$H$121) -> 120
A11: SCHP | B11: US TIPS | C11: =AVERAGE(Returns!$I$2:$I$121)*12 -> 0.021808213 | D11: =EXP(SUMPRODUCT(LN(1+Returns!$I$2:$I$121))*12/COUNT(Returns!$I$2:$I$121))-1 -> 0.020736047 | E11: =_xlfn.STDEV.S(Returns!$I$2:$I$121)*SQRT(12) -> 0.05037572 | F11: =(C11-AVERAGE(Returns!$O$2:$O$121)*12)/E11 -> -0.060630131 | G11: =COUNT(Returns!$I$2:$I$121) -> 120
A12: IAU | B12: Gold | C12: =AVERAGE(Returns!$J$2:$J$121)*12 -> 0.12464416 | D12: =EXP(SUMPRODUCT(LN(1+Returns!$J$2:$J$121))*12/COUNT(Returns!$J$2:$J$121))-1 -> 0.11896356 | E12: =_xlfn.STDEV.S(Returns!$J$2:$J$121)*SQRT(12) -> 0.15453119 | F12: =(C12-AVERAGE(Returns!$O$2:$O$121)*12)/E12 -> 0.64570559 | G12: =COUNT(Returns!$J$2:$J$121) -> 120
A13: BIL | B13: 1-3 month T-bills | C13: =AVERAGE(Returns!$K$2:$K$121)*12 -> 0.022727974 | D13: =EXP(SUMPRODUCT(LN(1+Returns!$K$2:$K$121))*12/COUNT(Returns!$K$2:$K$121))-1 -> 0.022950561 | E13: =_xlfn.STDEV.S(Returns!$K$2:$K$121)*SQRT(12) -> 0.0055694563 | F13: =(C13-AVERAGE(Returns!$O$2:$O$121)*12)/E13 -> -0.38325577 | G13: =COUNT(Returns!$K$2:$K$121) -> 120
A14: SPY | B14: S&P 500 | C14: =AVERAGE(Returns!$L$2:$L$121)*12 -> 0.15431801 | D14: =EXP(SUMPRODUCT(LN(1+Returns!$L$2:$L$121))*12/COUNT(Returns!$L$2:$L$121))-1 -> 0.15233882 | E14: =_xlfn.STDEV.S(Returns!$L$2:$L$121)*SQRT(12) -> 0.15329799 | F14: =(C14-AVERAGE(Returns!$O$2:$O$121)*12)/E14 -> 0.84446975 | G14: =COUNT(Returns!$L$2:$L$121) -> 120
A15: AGG | B15: US aggregate bonds (iShares) | C15: =AVERAGE(Returns!$M$2:$M$121)*12 -> 0.012546982 | D15: =EXP(SUMPRODUCT(LN(1+Returns!$M$2:$M$121))*12/COUNT(Returns!$M$2:$M$121))-1 -> 0.011249416 | E15: =_xlfn.STDEV.S(Returns!$M$2:$M$121)*SQRT(12) -> 0.052288095 | F15: =(C15-AVERAGE(Returns!$O$2:$O$121)*12)/E15 -> -0.23553197 | G15: =COUNT(Returns!$M$2:$M$121) -> 120
A16: AOR | B16: Global 60/40 allocation fund | C16: =AVERAGE(Returns!$N$2:$N$121)*12 -> 0.081737265 | D16: =EXP(SUMPRODUCT(LN(1+Returns!$N$2:$N$121))*12/COUNT(Returns!$N$2:$N$121))-1 -> 0.079506297 | E16: =_xlfn.STDEV.S(Returns!$N$2:$N$121)*SQRT(12) -> 0.10008897 | F16: =(C16-AVERAGE(Returns!$O$2:$O$121)*12)/E16 -> 0.56824208 | G16: =COUNT(Returns!$N$2:$N$121) -> 120
A18: Average risk-free (annualised) | C18: =AVERAGE(Returns!$O$2:$O$121)*12 -> 0.0248625

Sheet Correlation
A1: Correlation matrix of monthly returns
B3: VTI | C3: VEA | D3: VWO | E3: KSA | F3: UAE | G3: VNQ | H3: BND | I3: SCHP | J3: IAU | K3: BIL
A4: VTI | B4: =CORREL(Returns!$B$2:$B$121,Returns!$B$2:$B$121) -> 1 | C4: =CORREL(Returns!$B$2:$B$121,Returns!$C$2:$C$121) -> 0.84953549 | D4: =CORREL(Returns!$B$2:$B$121,Returns!$D$2:$D$121) -> 0.68858992 | E4: =CORREL(Returns!$B$2:$B$121,Returns!$E$2:$E$121) -> 0.40921682 | F4: =CORREL(Returns!$B$2:$B$121,Returns!$F$2:$F$121) -> 0.53364916 | G4: =CORREL(Returns!$B$2:$B$121,Returns!$G$2:$G$121) -> 0.78395143 | H4: =CORREL(Returns!$B$2:$B$121,Returns!$H$2:$H$121) -> 0.43813537 | I4: =CORREL(Returns!$B$2:$B$121,Returns!$I$2:$I$121) -> 0.52972499 | J4: =CORREL(Returns!$B$2:$B$121,Returns!$J$2:$J$121) -> 0.12260212 | K4: =CORREL(Returns!$B$2:$B$121,Returns!$K$2:$K$121) -> -0.015186066
A5: VEA | B5: =CORREL(Returns!$C$2:$C$121,Returns!$B$2:$B$121) -> 0.84953549 | C5: =CORREL(Returns!$C$2:$C$121,Returns!$C$2:$C$121) -> 1 | D5: =CORREL(Returns!$C$2:$C$121,Returns!$D$2:$D$121) -> 0.81745846 | E5: =CORREL(Returns!$C$2:$C$121,Returns!$E$2:$E$121) -> 0.37201717 | F5: =CORREL(Returns!$C$2:$C$121,Returns!$F$2:$F$121) -> 0.548451 | G5: =CORREL(Returns!$C$2:$C$121,Returns!$G$2:$G$121) -> 0.75738528 | H5: =CORREL(Returns!$C$2:$C$121,Returns!$H$2:$H$121) -> 0.53760344 | I5: =CORREL(Returns!$C$2:$C$121,Returns!$I$2:$I$121) -> 0.57048342 | J5: =CORREL(Returns!$C$2:$C$121,Returns!$J$2:$J$121) -> 0.32599593 | K5: =CORREL(Returns!$C$2:$C$121,Returns!$K$2:$K$121) -> 0.016981884
A6: VWO | B6: =CORREL(Returns!$D$2:$D$121,Returns!$B$2:$B$121) -> 0.68858992 | C6: =CORREL(Returns!$D$2:$D$121,Returns!$C$2:$C$121) -> 0.81745846 | D6: =CORREL(Returns!$D$2:$D$121,Returns!$D$2:$D$121) -> 1 | E6: =CORREL(Returns!$D$2:$D$121,Returns!$E$2:$E$121) -> 0.31802587 | F6: =CORREL(Returns!$D$2:$D$121,Returns!$F$2:$F$121) -> 0.49087418 | G6: =CORREL(Returns!$D$2:$D$121,Returns!$G$2:$G$121) -> 0.58129787 | H6: =CORREL(Returns!$D$2:$D$121,Returns!$H$2:$H$121) -> 0.47069192 | I6: =CORREL(Returns!$D$2:$D$121,Returns!$I$2:$I$121) -> 0.44478874 | J6: =CORREL(Returns!$D$2:$D$121,Returns!$J$2:$J$121) -> 0.37428028 | K6: =CORREL(Returns!$D$2:$D$121,Returns!$K$2:$K$121) -> 0.023452985
A7: KSA | B7: =CORREL(Returns!$E$2:$E$121,Returns!$B$2:$B$121) -> 0.40921682 | C7: =CORREL(Returns!$E$2:$E$121,Returns!$C$2:$C$121) -> 0.37201717 | D7: =CORREL(Returns!$E$2:$E$121,Returns!$D$2:$D$121) -> 0.31802587 | E7: =CORREL(Returns!$E$2:$E$121,Returns!$E$2:$E$121) -> 1 | F7: =CORREL(Returns!$E$2:$E$121,Returns!$F$2:$F$121) -> 0.33556572 | G7: =CORREL(Returns!$E$2:$E$121,Returns!$G$2:$G$121) -> 0.35455928 | H7: =CORREL(Returns!$E$2:$E$121,Returns!$H$2:$H$121) -> 0.042345169 | I7: =CORREL(Returns!$E$2:$E$121,Returns!$I$2:$I$121) -> 0.18759627 | J7: =CORREL(Returns!$E$2:$E$121,Returns!$J$2:$J$121) -> 0.012469996 | K7: =CORREL(Returns!$E$2:$E$121,Returns!$K$2:$K$121) -> -0.19480246
A8: UAE | B8: =CORREL(Returns!$F$2:$F$121,Returns!$B$2:$B$121) -> 0.53364916 | C8: =CORREL(Returns!$F$2:$F$121,Returns!$C$2:$C$121) -> 0.548451 | D8: =CORREL(Returns!$F$2:$F$121,Returns!$D$2:$D$121) -> 0.49087418 | E8: =CORREL(Returns!$F$2:$F$121,Returns!$E$2:$E$121) -> 0.33556572 | F8: =CORREL(Returns!$F$2:$F$121,Returns!$F$2:$F$121) -> 1 | G8: =CORREL(Returns!$F$2:$F$121,Returns!$G$2:$G$121) -> 0.46969785 | H8: =CORREL(Returns!$F$2:$F$121,Returns!$H$2:$H$121) -> 0.17012569 | I8: =CORREL(Returns!$F$2:$F$121,Returns!$I$2:$I$121) -> 0.28664397 | J8: =CORREL(Returns!$F$2:$F$121,Returns!$J$2:$J$121) -> 0.11910601 | K8: =CORREL(Returns!$F$2:$F$121,Returns!$K$2:$K$121) -> -0.072070904
A9: VNQ | B9: =CORREL(Returns!$G$2:$G$121,Returns!$B$2:$B$121) -> 0.78395143 | C9: =CORREL(Returns!$G$2:$G$121,Returns!$C$2:$C$121) -> 0.75738528 | D9: =CORREL(Returns!$G$2:$G$121,Returns!$D$2:$D$121) -> 0.58129787 | E9: =CORREL(Returns!$G$2:$G$121,Returns!$E$2:$E$121) -> 0.35455928 | F9: =CORREL(Returns!$G$2:$G$121,Returns!$F$2:$F$121) -> 0.46969785 | G9: =CORREL(Returns!$G$2:$G$121,Returns!$G$2:$G$121) -> 1 | H9: =CORREL(Returns!$G$2:$G$121,Returns!$H$2:$H$121) -> 0.60666218 | I9: =CORREL(Returns!$G$2:$G$121,Returns!$I$2:$I$121) -> 0.66282935 | J9: =CORREL(Returns!$G$2:$G$121,Returns!$J$2:$J$121) -> 0.21050897 | K9: =CORREL(Returns!$G$2:$G$121,Returns!$K$2:$K$121) -> -0.03368204
A10: BND | B10: =CORREL(Returns!$H$2:$H$121,Returns!$B$2:$B$121) -> 0.43813537 | C10: =CORREL(Returns!$H$2:$H$121,Returns!$C$2:$C$121) -> 0.53760344 | D10: =CORREL(Returns!$H$2:$H$121,Returns!$D$2:$D$121) -> 0.47069192 | E10: =CORREL(Returns!$H$2:$H$121,Returns!$E$2:$E$121) -> 0.042345169 | F10: =CORREL(Returns!$H$2:$H$121,Returns!$F$2:$F$121) -> 0.17012569 | G10: =CORREL(Returns!$H$2:$H$121,Returns!$G$2:$G$121) -> 0.60666218 | H10: =CORREL(Returns!$H$2:$H$121,Returns!$H$2:$H$121) -> 1 | I10: =CORREL(Returns!$H$2:$H$121,Returns!$I$2:$I$121) -> 0.86332958 | J10: =CORREL(Returns!$H$2:$H$121,Returns!$J$2:$J$121) -> 0.4269618 | K10: =CORREL(Returns!$H$2:$H$121,Returns!$K$2:$K$121) -> 0.12161968
A11: SCHP | B11: =CORREL(Returns!$I$2:$I$121,Returns!$B$2:$B$121) -> 0.52972499 | C11: =CORREL(Returns!$I$2:$I$121,Returns!$C$2:$C$121) -> 0.57048342 | D11: =CORREL(Returns!$I$2:$I$121,Returns!$D$2:$D$121) -> 0.44478874 | E11: =CORREL(Returns!$I$2:$I$121,Returns!$E$2:$E$121) -> 0.18759627 | F11: =CORREL(Returns!$I$2:$I$121,Returns!$F$2:$F$121) -> 0.28664397 | G11: =CORREL(Returns!$I$2:$I$121,Returns!$G$2:$G$121) -> 0.66282935 | H11: =CORREL(Returns!$I$2:$I$121,Returns!$H$2:$H$121) -> 0.86332958 | I11: =CORREL(Returns!$I$2:$I$121,Returns!$I$2:$I$121) -> 1 | J11: =CORREL(Returns!$I$2:$I$121,Returns!$J$2:$J$121) -> 0.44105841 | K11: =CORREL(Returns!$I$2:$I$121,Returns!$K$2:$K$121) -> -0.0035821602
A12: IAU | B12: =CORREL(Returns!$J$2:$J$121,Returns!$B$2:$B$121) -> 0.12260212 | C12: =CORREL(Returns!$J$2:$J$121,Returns!$C$2:$C$121) -> 0.32599593 | D12: =CORREL(Returns!$J$2:$J$121,Returns!$D$2:$D$121) -> 0.37428028 | E12: =CORREL(Returns!$J$2:$J$121,Returns!$E$2:$E$121) -> 0.012469996 | F12: =CORREL(Returns!$J$2:$J$121,Returns!$F$2:$F$121) -> 0.11910601 | G12: =CORREL(Returns!$J$2:$J$121,Returns!$G$2:$G$121) -> 0.21050897 | H12: =CORREL(Returns!$J$2:$J$121,Returns!$H$2:$H$121) -> 0.4269618 | I12: =CORREL(Returns!$J$2:$J$121,Returns!$I$2:$I$121) -> 0.44105841 | J12: =CORREL(Returns!$J$2:$J$121,Returns!$J$2:$J$121) -> 1 | K12: =CORREL(Returns!$J$2:$J$121,Returns!$K$2:$K$121) -> 0.18587
A13: BIL | B13: =CORREL(Returns!$K$2:$K$121,Returns!$B$2:$B$121) -> -0.015186066 | C13: =CORREL(Returns!$K$2:$K$121,Returns!$C$2:$C$121) -> 0.016981884 | D13: =CORREL(Returns!$K$2:$K$121,Returns!$D$2:$D$121) -> 0.023452985 | E13: =CORREL(Returns!$K$2:$K$121,Returns!$E$2:$E$121) -> -0.19480246 | F13: =CORREL(Returns!$K$2:$K$121,Returns!$F$2:$F$121) -> -0.072070904 | G13: =CORREL(Returns!$K$2:$K$121,Returns!$G$2:$G$121) -> -0.03368204 | H13: =CORREL(Returns!$K$2:$K$121,Returns!$H$2:$H$121) -> 0.12161968 | I13: =CORREL(Returns!$K$2:$K$121,Returns!$I$2:$I$121) -> -0.0035821602 | J13: =CORREL(Returns!$K$2:$K$121,Returns!$J$2:$J$121) -> 0.18587 | K13: =CORREL(Returns!$K$2:$K$121,Returns!$K$2:$K$121) -> 1

Sheet Covariance
A1: Covariance matrix of monthly returns (annualised)
B3: VTI | C3: VEA | D3: VWO | E3: KSA | F3: UAE | G3: VNQ | H3: BND | I3: SCHP | J3: IAU | K3: BIL
A4: VTI | B4: =_xlfn.COVARIANCE.S(Returns!$B$2:$B$121,Returns!$B$2:$B$121)*12 -> 0.024879894 | C4: =_xlfn.COVARIANCE.S(Returns!$B$2:$B$121,Returns!$C$2:$C$121)*12 -> 0.020825762 | D4: =_xlfn.COVARIANCE.S(Returns!$B$2:$B$121,Returns!$D$2:$D$121)*12 -> 0.01685514 | E4: =_xlfn.COVARIANCE.S(Returns!$B$2:$B$121,Returns!$E$2:$E$121)*12 -> 0.011634747 | F4: =_xlfn.COVARIANCE.S(Returns!$B$2:$B$121,Returns!$F$2:$F$121)*12 -> 0.01484144 | G4: =_xlfn.COVARIANCE.S(Returns!$B$2:$B$121,Returns!$G$2:$G$121)*12 -> 0.021887075 | H4: =_xlfn.COVARIANCE.S(Returns!$B$2:$B$121,Returns!$H$2:$H$121)*12 -> 0.0036277432 | I4: =_xlfn.COVARIANCE.S(Returns!$B$2:$B$121,Returns!$I$2:$I$121)*12 -> 0.0042091654 | J4: =_xlfn.COVARIANCE.S(Returns!$B$2:$B$121,Returns!$J$2:$J$121)*12 -> 0.0029883978 | K4: =_xlfn.COVARIANCE.S(Returns!$B$2:$B$121,Returns!$K$2:$K$121)*12 -> -1.3340815e-05
A5: VEA | B5: =_xlfn.COVARIANCE.S(Returns!$C$2:$C$121,Returns!$B$2:$B$121)*12 -> 0.020825762 | C5: =_xlfn.COVARIANCE.S(Returns!$C$2:$C$121,Returns!$C$2:$C$121)*12 -> 0.024154064 | D5: =_xlfn.COVARIANCE.S(Returns!$C$2:$C$121,Returns!$D$2:$D$121)*12 -> 0.01971552 | E5: =_xlfn.COVARIANCE.S(Returns!$C$2:$C$121,Returns!$E$2:$E$121)*12 -> 0.01042167 | F5: =_xlfn.COVARIANCE.S(Returns!$C$2:$C$121,Returns!$F$2:$F$121)*12 -> 0.015028959 | G5: =_xlfn.COVARIANCE.S(Returns!$C$2:$C$121,Returns!$G$2:$G$121)*12 -> 0.020834653 | H5: =_xlfn.COVARIANCE.S(Returns!$C$2:$C$121,Returns!$H$2:$H$121)*12 -> 0.0043859241 | I5: =_xlfn.COVARIANCE.S(Returns!$C$2:$C$121,Returns!$I$2:$I$121)*12 -> 0.0044664184 | J5: =_xlfn.COVARIANCE.S(Returns!$C$2:$C$121,Returns!$J$2:$J$121)*12 -> 0.0078293092 | K5: =_xlfn.COVARIANCE.S(Returns!$C$2:$C$121,Returns!$K$2:$K$121)*12 -> 1.4699203e-05
A6: VWO | B6: =_xlfn.COVARIANCE.S(Returns!$D$2:$D$121,Returns!$B$2:$B$121)*12 -> 0.01685514 | C6: =_xlfn.COVARIANCE.S(Returns!$D$2:$D$121,Returns!$C$2:$C$121)*12 -> 0.01971552 | D6: =_xlfn.COVARIANCE.S(Returns!$D$2:$D$121,Returns!$D$2:$D$121)*12 -> 0.024082128 | E6: =_xlfn.COVARIANCE.S(Returns!$D$2:$D$121,Returns!$E$2:$E$121)*12 -> 0.0088958833 | F6: =_xlfn.COVARIANCE.S(Returns!$D$2:$D$121,Returns!$F$2:$F$121)*12 -> 0.013431161 | G6: =_xlfn.COVARIANCE.S(Returns!$D$2:$D$121,Returns!$G$2:$G$121)*12 -> 0.015966895 | H6: =_xlfn.COVARIANCE.S(Returns!$D$2:$D$121,Returns!$H$2:$H$121)*12 -> 0.0038343181 | I6: =_xlfn.COVARIANCE.S(Returns!$D$2:$D$121,Returns!$I$2:$I$121)*12 -> 0.0034771424 | J6: =_xlfn.COVARIANCE.S(Returns!$D$2:$D$121,Returns!$J$2:$J$121)*12 -> 0.0089755388 | K6: =_xlfn.COVARIANCE.S(Returns!$D$2:$D$121,Returns!$K$2:$K$121)*12 -> 2.0270215e-05
A7: KSA | B7: =_xlfn.COVARIANCE.S(Returns!$E$2:$E$121,Returns!$B$2:$B$121)*12 -> 0.011634747 | C7: =_xlfn.COVARIANCE.S(Returns!$E$2:$E$121,Returns!$C$2:$C$121)*12 -> 0.01042167 | D7: =_xlfn.COVARIANCE.S(Returns!$E$2:$E$121,Returns!$D$2:$D$121)*12 -> 0.0088958833 | E7: =_xlfn.COVARIANCE.S(Returns!$E$2:$E$121,Returns!$E$2:$E$121)*12 -> 0.03249065 | F7: =_xlfn.COVARIANCE.S(Returns!$E$2:$E$121,Returns!$F$2:$F$121)*12 -> 0.010664801 | G7: =_xlfn.COVARIANCE.S(Returns!$E$2:$E$121,Returns!$G$2:$G$121)*12 -> 0.011312077 | H7: =_xlfn.COVARIANCE.S(Returns!$E$2:$E$121,Returns!$H$2:$H$121)*12 -> 0.00040067019 | I7: =_xlfn.COVARIANCE.S(Returns!$E$2:$E$121,Returns!$I$2:$I$121)*12 -> 0.0017034315 | J7: =_xlfn.COVARIANCE.S(Returns!$E$2:$E$121,Returns!$J$2:$J$121)*12 -> 0.00034734549 | K7: =_xlfn.COVARIANCE.S(Returns!$E$2:$E$121,Returns!$K$2:$K$121)*12 -> -0.00019556289
A8: UAE | B8: =_xlfn.COVARIANCE.S(Returns!$F$2:$F$121,Returns!$B$2:$B$121)*12 -> 0.01484144 | C8: =_xlfn.COVARIANCE.S(Returns!$F$2:$F$121,Returns!$C$2:$C$121)*12 -> 0.015028959 | D8: =_xlfn.COVARIANCE.S(Returns!$F$2:$F$121,Returns!$D$2:$D$121)*12 -> 0.013431161 | E8: =_xlfn.COVARIANCE.S(Returns!$F$2:$F$121,Returns!$E$2:$E$121)*12 -> 0.010664801 | F8: =_xlfn.COVARIANCE.S(Returns!$F$2:$F$121,Returns!$F$2:$F$121)*12 -> 0.031087936 | G8: =_xlfn.COVARIANCE.S(Returns!$F$2:$F$121,Returns!$G$2:$G$121)*12 -> 0.014658476 | H8: =_xlfn.COVARIANCE.S(Returns!$F$2:$F$121,Returns!$H$2:$H$121)*12 -> 0.0015745984 | I8: =_xlfn.COVARIANCE.S(Returns!$F$2:$F$121,Returns!$I$2:$I$121)*12 -> 0.0025460095 | J8: =_xlfn.COVARIANCE.S(Returns!$F$2:$F$121,Returns!$J$2:$J$121)*12 -> 0.0032452322 | K8: =_xlfn.COVARIANCE.S(Returns!$F$2:$F$121,Returns!$K$2:$K$121)*12 -> -7.0773181e-05
A9: VNQ | B9: =_xlfn.COVARIANCE.S(Returns!$G$2:$G$121,Returns!$B$2:$B$121)*12 -> 0.021887075 | C9: =_xlfn.COVARIANCE.S(Returns!$G$2:$G$121,Returns!$C$2:$C$121)*12 -> 0.020834653 | D9: =_xlfn.COVARIANCE.S(Returns!$G$2:$G$121,Returns!$D$2:$D$121)*12 -> 0.015966895 | E9: =_xlfn.COVARIANCE.S(Returns!$G$2:$G$121,Returns!$E$2:$E$121)*12 -> 0.011312077 | F9: =_xlfn.COVARIANCE.S(Returns!$G$2:$G$121,Returns!$F$2:$F$121)*12 -> 0.014658476 | G9: =_xlfn.COVARIANCE.S(Returns!$G$2:$G$121,Returns!$G$2:$G$121)*12 -> 0.03132915 | H9: =_xlfn.COVARIANCE.S(Returns!$G$2:$G$121,Returns!$H$2:$H$121)*12 -> 0.0056367035 | I9: =_xlfn.COVARIANCE.S(Returns!$G$2:$G$121,Returns!$I$2:$I$121)*12 -> 0.0059101337 | J9: =_xlfn.COVARIANCE.S(Returns!$G$2:$G$121,Returns!$J$2:$J$121)*12 -> 0.0057578596 | K9: =_xlfn.COVARIANCE.S(Returns!$G$2:$G$121,Returns!$K$2:$K$121)*12 -> -3.3203625e-05
A10: BND | B10: =_xlfn.COVARIANCE.S(Returns!$H$2:$H$121,Returns!$B$2:$B$121)*12 -> 0.0036277432 | C10: =_xlfn.COVARIANCE.S(Returns!$H$2:$H$121,Returns!$C$2:$C$121)*12 -> 0.0043859241 | D10: =_xlfn.COVARIANCE.S(Returns!$H$2:$H$121,Returns!$D$2:$D$121)*12 -> 0.0038343181 | E10: =_xlfn.COVARIANCE.S(Returns!$H$2:$H$121,Returns!$E$2:$E$121)*12 -> 0.00040067019 | F10: =_xlfn.COVARIANCE.S(Returns!$H$2:$H$121,Returns!$F$2:$F$121)*12 -> 0.0015745984 | G10: =_xlfn.COVARIANCE.S(Returns!$H$2:$H$121,Returns!$G$2:$G$121)*12 -> 0.0056367035 | H10: =_xlfn.COVARIANCE.S(Returns!$H$2:$H$121,Returns!$H$2:$H$121)*12 -> 0.0027555477 | I10: =_xlfn.COVARIANCE.S(Returns!$H$2:$H$121,Returns!$I$2:$I$121)*12 -> 0.0022829787 | J10: =_xlfn.COVARIANCE.S(Returns!$H$2:$H$121,Returns!$J$2:$J$121)*12 -> 0.0034634518 | K10: =_xlfn.COVARIANCE.S(Returns!$H$2:$H$121,Returns!$K$2:$K$121)*12 -> 3.5556632e-05
A11: SCHP | B11: =_xlfn.COVARIANCE.S(Returns!$I$2:$I$121,Returns!$B$2:$B$121)*12 -> 0.0042091654 | C11: =_xlfn.COVARIANCE.S(Returns!$I$2:$I$121,Returns!$C$2:$C$121)*12 -> 0.0044664184 | D11: =_xlfn.COVARIANCE.S(Returns!$I$2:$I$121,Returns!$D$2:$D$121)*12 -> 0.0034771424 | E11: =_xlfn.COVARIANCE.S(Returns!$I$2:$I$121,Returns!$E$2:$E$121)*12 -> 0.0017034315 | F11: =_xlfn.COVARIANCE.S(Returns!$I$2:$I$121,Returns!$F$2:$F$121)*12 -> 0.0025460095 | G11: =_xlfn.COVARIANCE.S(Returns!$I$2:$I$121,Returns!$G$2:$G$121)*12 -> 0.0059101337 | H11: =_xlfn.COVARIANCE.S(Returns!$I$2:$I$121,Returns!$H$2:$H$121)*12 -> 0.0022829787 | I11: =_xlfn.COVARIANCE.S(Returns!$I$2:$I$121,Returns!$I$2:$I$121)*12 -> 0.0025377132 | J11: =_xlfn.COVARIANCE.S(Returns!$I$2:$I$121,Returns!$J$2:$J$121)*12 -> 0.0034334722 | K11: =_xlfn.COVARIANCE.S(Returns!$I$2:$I$121,Returns!$K$2:$K$121)*12 -> -1.0050301e-06
A12: IAU | B12: =_xlfn.COVARIANCE.S(Returns!$J$2:$J$121,Returns!$B$2:$B$121)*12 -> 0.0029883978 | C12: =_xlfn.COVARIANCE.S(Returns!$J$2:$J$121,Returns!$C$2:$C$121)*12 -> 0.0078293092 | D12: =_xlfn.COVARIANCE.S(Returns!$J$2:$J$121,Returns!$D$2:$D$121)*12 -> 0.0089755388 | E12: =_xlfn.COVARIANCE.S(Returns!$J$2:$J$121,Returns!$E$2:$E$121)*12 -> 0.00034734549 | F12: =_xlfn.COVARIANCE.S(Returns!$J$2:$J$121,Returns!$F$2:$F$121)*12 -> 0.0032452322 | G12: =_xlfn.COVARIANCE.S(Returns!$J$2:$J$121,Returns!$G$2:$G$121)*12 -> 0.0057578596 | H12: =_xlfn.COVARIANCE.S(Returns!$J$2:$J$121,Returns!$H$2:$H$121)*12 -> 0.0034634518 | I12: =_xlfn.COVARIANCE.S(Returns!$J$2:$J$121,Returns!$I$2:$I$121)*12 -> 0.0034334722 | J12: =_xlfn.COVARIANCE.S(Returns!$J$2:$J$121,Returns!$J$2:$J$121)*12 -> 0.02387989 | K12: =_xlfn.COVARIANCE.S(Returns!$J$2:$J$121,Returns!$K$2:$K$121)*12 -> 0.0001599699
A13: BIL | B13: =_xlfn.COVARIANCE.S(Returns!$K$2:$K$121,Returns!$B$2:$B$121)*12 -> -1.3340815e-05 | C13: =_xlfn.COVARIANCE.S(Returns!$K$2:$K$121,Returns!$C$2:$C$121)*12 -> 1.4699203e-05 | D13: =_xlfn.COVARIANCE.S(Returns!$K$2:$K$121,Returns!$D$2:$D$121)*12 -> 2.0270215e-05 | E13: =_xlfn.COVARIANCE.S(Returns!$K$2:$K$121,Returns!$E$2:$E$121)*12 -> -0.00019556289 | F13: =_xlfn.COVARIANCE.S(Returns!$K$2:$K$121,Returns!$F$2:$F$121)*12 -> -7.0773181e-05 | G13: =_xlfn.COVARIANCE.S(Returns!$K$2:$K$121,Returns!$G$2:$G$121)*12 -> -3.3203625e-05 | H13: =_xlfn.COVARIANCE.S(Returns!$K$2:$K$121,Returns!$H$2:$H$121)*12 -> 3.5556632e-05 | I13: =_xlfn.COVARIANCE.S(Returns!$K$2:$K$121,Returns!$I$2:$I$121)*12 -> -1.0050301e-06 | J13: =_xlfn.COVARIANCE.S(Returns!$K$2:$K$121,Returns!$J$2:$J$121)*12 -> 0.0001599699 | K13: =_xlfn.COVARIANCE.S(Returns!$K$2:$K$121,Returns!$K$2:$K$121)*12 -> 3.1018844e-05

Sheet PortfolioRisk
A1: Portfolio expected return, volatility and risk contributions
A3: Market inputs (as of curve date)
A4: 3-month Treasury yield | B4: 0.0426 | C4: US Treasury par curves 2026-10-13; breakeven FRED T10YIE 2026-10-13
A5: 5-year Treasury yield | B5: 0.05
A6: 5-year TIPS real yield | B6: 0.0267
A7: 10-year breakeven inflation | B7: 0.0233
A8: Spread allowance, aggregate bonds | B8: 0.002
A9: Gold premium over inflation | B9: 0.01
A11: Ticker | B11: Weight | C11: Hist. mean | D11: Equity risk premium (input) | E11: Forward return (CMA) | F11: Marginal (Cov x w) | G11: Risk contribution | H11: Weights (row)
A12: VTI | B12: =Allocation!D6 -> 0.25 | C12: =AssetStats!C4 -> 0.15033 | D12: 0.03 | E12: =$B$4+D12 -> 0.0726 | F12: =SUMPRODUCT(Covariance!B4:K4,$B$24:$K$24) -> 0.012067946 | G12: =B12*F12/$B$27 -> 0.43495501
A13: VEA | B13: =Allocation!D7 -> 0.1 | C13: =AssetStats!C5 -> 0.10533543 | D13: 0.035 | E13: =$B$4+D13 -> 0.0776 | F13: =SUMPRODUCT(Covariance!B5:K5,$B$24:$K$24) -> 0.012027571 | G13: =B13*F13/$B$27 -> 0.17339991
A14: VWO | B14: =Allocation!D8 -> 0.05 | C14: =AssetStats!C6 -> 0.085339327 | D14: 0.04 | E14: =$B$4+D14 -> 0.0826 | F14: =SUMPRODUCT(Covariance!B6:K6,$B$24:$K$24) -> 0.010409696 | G14: =B14*F14/$B$27 -> 0.075037611
A15: KSA | B15: =Allocation!D9 -> 0.03 | C15: =AssetStats!C7 -> 0.096567128 | D15: 0.04 | E15: =$B$4+D15 -> 0.0826 | F15: =SUMPRODUCT(Covariance!B7:K7,$B$24:$K$24) -> 0.0062362742 | G15: =B15*F15/$B$27 -> 0.026972265
A16: UAE | B16: =Allocation!D10 -> 0.02 | C16: =AssetStats!C8 -> 0.073227742 | D16: 0.04 | E16: =$B$4+D16 -> 0.0826 | F16: =SUMPRODUCT(Covariance!B8:K8,$B$24:$K$24) -> 0.008186946 | G16: =B16*F16/$B$27 -> 0.023606026
A17: VNQ | B17: =Allocation!D11 -> 0.03 | C17: =AssetStats!C9 -> 0.058950491 | D17: 0.025 | E17: =$B$4+D17 -> 0.0676 | F17: =SUMPRODUCT(Covariance!B9:K9,$B$24:$K$24) -> 0.012444771 | G17: =B17*F17/$B$27 -> 0.05382439
A18: BND | B18: =Allocation!D12 -> 0.25 | C18: =AssetStats!C10 -> 0.013103424 | E18: =$B$5+$B$8 -> 0.052 | F18: =SUMPRODUCT(Covariance!B10:K10,$B$24:$K$24) -> 0.0029579878 | G18: =B18*F18/$B$27 -> 0.10661231
A19: SCHP | B19: =Allocation!D13 -> 0.12 | C19: =AssetStats!C11 -> 0.021808213 | E19: =$B$6+$B$7 -> 0.05 | F19: =SUMPRODUCT(Covariance!B11:K11,$B$24:$K$24) -> 0.0030676504 | G19: =B19*F19/$B$27 -> 0.053071097
A20: IAU | B20: =Allocation!D14 -> 0.07 | C20: =AssetStats!C12 -> 0.12464416 | E20: =$B$7+$B$9 -> 0.0333 | F20: =SUMPRODUCT(Covariance!B12:K12,$B$24:$K$24) -> 0.0051891376 | G20: =B20*F20/$B$27 -> 0.052367783
A21: BIL | B21: =Allocation!D15 -> 0.08 | C21: =AssetStats!C13 -> 0.022727974 | E21: =$B$4 -> 0.0426 | F21: =SUMPRODUCT(Covariance!B13:K13,$B$24:$K$24) -> 1.3317723e-05 | G21: =B21*F21/$B$27 -> 0.0001535999
A24: Weights (transposed) | B24: =INDEX($B$12:$B$21,1) -> 0.25 | C24: =INDEX($B$12:$B$21,2) -> 0.1 | D24: =INDEX($B$12:$B$21,3) -> 0.05 | E24: =INDEX($B$12:$B$21,4) -> 0.03 | F24: =INDEX($B$12:$B$21,5) -> 0.02 | G24: =INDEX($B$12:$B$21,6) -> 0.03 | H24: =INDEX($B$12:$B$21,7) -> 0.25 | I24: =INDEX($B$12:$B$21,8) -> 0.12 | J24: =INDEX($B$12:$B$21,9) -> 0.07 | K24: =INDEX($B$12:$B$21,10) -> 0.08
A25: Expected return, historical means | B25: =SUMPRODUCT(B12:B21,C12:C21) -> 0.074949263
A26: Expected return, forward CMA | B26: =SUMPRODUCT(B12:B21,E12:E21) -> 0.060937
A27: Portfolio variance | B27: =SUMPRODUCT(B12:B21,F12:F21) -> 0.0069363187
A28: Portfolio volatility | B28: =SQRT(B27) -> 0.083284565
A29: Sharpe (historical means, avg risk-free) | B29: =(B25-AssetStats!C18)/B28 -> 0.60139311
A30: Sharpe (forward CMA vs 3M yield) | B30: =(B26-B4)/B28 -> 0.22017285
A31: Growth assets share of risk (equity + REIT) | B31: =SUM(G12:G16)+G17 -> 0.78779521
A32: 1-year parametric VaR 95% (CMA), % of portfolio | B32: =-(B26-_xlfn.NORM.S.INV(0.95)*B28) -> 0.076053919
A33: 1-year parametric VaR 95% (CMA), USD | B33: =B32*Allocation!B2 -> 38026.959
A34: 1-year parametric CVaR 95% (CMA), % of portfolio | B34: =-(B26-B28*_xlfn.NORM.S.DIST(_xlfn.NORM.S.INV(0.95),FALSE())/0.05) -> 0.11085514

Sheet Backtest
A1: Backtest: monthly returns from the Python engine (daily simulation, rebalancing rules, 5 bp trading cost); everything else by formula
A3: Month end | B3: Risk-free | C3: Proposed return | D3: 60/40 (SPY/AGG) return | E3: Benchmark (AOR) return | F3: Proposed wealth | G3: 60/40 (SPY/AGG) wealth | H3: Benchmark (AOR) wealth | I3: Proposed peak | J3: 60/40 (SPY/AGG) peak | K3: Benchmark (AOR) peak | L3: Proposed drawdown | M3: 60/40 (SPY/AGG) drawdown | N3: Benchmark (AOR) drawdown | P3: Statistic | Q3: Proposed | R3: 60/40 (SPY/AGG) | S3: Benchmark (AOR)
A4: 42643 | F4: =Allocation!$B$2 -> 500000 | G4: =Allocation!$B$2 -> 500000 | H4: =Allocation!$B$2 -> 500000 | I4: =F4 -> 500000 | J4: =G4 -> 500000 | K4: =H4 -> 500000 | L4: 0 | M4: 0 | N4: 0 | P4: CAGR | Q4: =(F124/F4)^(12/COUNT($C$5:$C$124))-1 -> 0.07536493 | R4: =(G124/G4)^(12/COUNT($D$5:$D$124))-1 -> 0.097294542 | S4: =(H124/H4)^(12/COUNT($E$5:$E$124))-1 -> 0.0795063
A5: 42674 | B5: 0.00024167 | C5: -0.01390103 | D5: -0.01367089 | E5: -0.01584366 | F5: =F4*(1+C5) -> 493049.48 | G5: =G4*(1+D5) -> 493164.55 | H5: =H4*(1+E5) -> 492078.17 | I5: =MAX(I4,F5) -> 500000 | J5: =MAX(J4,G5) -> 500000 | K5: =MAX(K4,H5) -> 500000 | L5: =F5/I5-1 -> -0.01390103 | M5: =G5/J5-1 -> -0.01367089 | N5: =H5/K5-1 -> -0.01584366 | P5: Volatility (annualised) | Q5: =_xlfn.STDEV.S($C$5:$C$124)*SQRT(12) -> 0.082785195 | R5: =_xlfn.STDEV.S($D$5:$D$124)*SQRT(12) -> 0.10208182 | S5: =_xlfn.STDEV.S($E$5:$E$124)*SQRT(12) -> 0.10008897
A6: 42704 | B6: 0.00028333 | C6: -0.00309298 | D6: 0.01170191 | E6: -0.00346881 | F6: =F5*(1+C6) -> 491524.49 | G6: =G5*(1+D6) -> 498935.52 | H6: =H5*(1+E6) -> 490371.24 | I6: =MAX(I5,F6) -> 500000 | J6: =MAX(J5,G6) -> 500000 | K6: =MAX(K5,H6) -> 500000 | L6: =F6/I6-1 -> -0.016951014 | M6: =G6/J6-1 -> -0.0021289555 | N6: =H6/K6-1 -> -0.019257511 | P6: Sharpe ratio | Q6: =(AVERAGE($C$5:$C$124)-AVERAGE($B$5:$B$124))*12/(_xlfn.STDEV.S($C$5:$C$124)*SQRT(12)) -> 0.62119598 | R6: =(AVERAGE($D$5:$D$124)-AVERAGE($B$5:$B$124))*12/(_xlfn.STDEV.S($D$5:$D$124)*SQRT(12)) -> 0.72016773 | S6: =(AVERAGE($E$5:$E$124)-AVERAGE($B$5:$B$124))*12/(_xlfn.STDEV.S($E$5:$E$124)*SQRT(12)) -> 0.56824209
A7: 42735 | B7: 0.0004 | C7: 0.00988272 | D7: 0.01338642 | E7: 0.01578077 | F7: =F6*(1+C7) -> 496382.09 | G7: =G6*(1+D7) -> 505614.48 | H7: =H6*(1+E7) -> 498109.68 | I7: =MAX(I6,F7) -> 500000 | J7: =MAX(J6,G7) -> 505614.48 | K7: =MAX(K6,H7) -> 500000 | L7: =F7/I7-1 -> -0.0072358165 | M7: =G7/J7-1 -> 0 | N7: =H7/K7-1 -> -0.0037806397 | P7: Sortino ratio | Q7: =(AVERAGE($C$5:$C$124)-AVERAGE($B$5:$B$124))*12/(SQRT(SUMPRODUCT((($C$5:$C$124-$B$5:$B$124)<0)*($C$5:$C$124-$B$5:$B$124)^2)/COUNT($C$5:$C$124))*SQRT(12)) -> 0.92257373 | R7: =(AVERAGE($D$5:$D$124)-AVERAGE($B$5:$B$124))*12/(SQRT(SUMPRODUCT((($D$5:$D$124-$B$5:$B$124)<0)*($D$5:$D$124-$B$5:$B$124)^2)/COUNT($D$5:$D$124))*SQRT(12)) -> 1.1049736 | S7: =(AVERAGE($E$5:$E$124)-AVERAGE($B$5:$B$124))*12/(SQRT(SUMPRODUCT((($E$5:$E$124-$B$5:$B$124)<0)*($E$5:$E$124-$B$5:$B$124)^2)/COUNT($E$5:$E$124))*SQRT(12)) -> 0.83646926
A8: 42766 | B8: 0.000425 | C8: 0.01664406 | D8: 0.01158792 | E8: 0.01306082 | F8: =F7*(1+C8) -> 504643.91 | G8: =G7*(1+D8) -> 511473.5 | H8: =H7*(1+E8) -> 504615.4 | I8: =MAX(I7,F8) -> 504643.91 | J8: =MAX(J7,G8) -> 511473.5 | K8: =MAX(K7,H8) -> 504615.4 | L8: =F8/I8-1 -> 0 | M8: =G8/J8-1 -> 0 | N8: =H8/K8-1 -> 0 | P8: Max drawdown (month-end) | Q8: =MIN($L$5:$L$124) -> -0.17010315 | R8: =MIN($M$5:$M$124) -> -0.20084983 | S8: =MIN($N$5:$N$124) -> -0.20750911
A9: 42794 | B9: 0.00043333 | C9: 0.0157404 | D9: 0.02628135 | E9: 0.02164929 | F9: =F8*(1+C9) -> 512587.2 | G9: =G8*(1+D9) -> 524915.72 | H9: =H8*(1+E9) -> 515539.97 | I9: =MAX(I8,F9) -> 512587.2 | J9: =MAX(J8,G9) -> 524915.72 | K9: =MAX(K8,H9) -> 515539.97 | L9: =F9/I9-1 -> 0 | M9: =G9/J9-1 -> 0 | N9: =H9/K9-1 -> 0 | P9: Worst month | Q9: =MIN($C$5:$C$124) -> -0.07295185 | R9: =MIN($D$5:$D$124) -> -0.07364217 | S9: =MIN($E$5:$E$124) -> -0.09452928
A10: 42825 | B10: 0.00044167 | C10: 0.00390662 | D10: 0.00053746 | E10: 0.00928528 | F10: =F9*(1+C10) -> 514589.69 | G10: =G9*(1+D10) -> 525197.84 | H10: =H9*(1+E10) -> 520326.9 | I10: =MAX(I9,F10) -> 514589.69 | J10: =MAX(J9,G10) -> 525197.84 | K10: =MAX(K9,H10) -> 520326.9 | L10: =F10/I10-1 -> 0 | M10: =G10/J10-1 -> 0 | N10: =H10/K10-1 -> 0 | P10: Best month | Q10: =MAX($C$5:$C$124) -> 0.06582016 | R10: =MAX($D$5:$D$124) -> 0.08306647 | S10: =MAX($E$5:$E$124) -> 0.07536831
A11: 42855 | B11: 0.00063333 | C11: 0.00988674 | D11: 0.00958416 | E11: 0.0138035 | F11: =F10*(1+C11) -> 519677.3 | G11: =G10*(1+D11) -> 530231.42 | H11: =H10*(1+E11) -> 527509.23 | I11: =MAX(I10,F11) -> 519677.3 | J11: =MAX(J10,G11) -> 530231.42 | K11: =MAX(K10,H11) -> 527509.23 | L11: =F11/I11-1 -> 0 | M11: =G11/J11-1 -> 0 | N11: =H11/K11-1 -> 0 | P11: Share of positive months | Q11: =COUNTIF($C$5:$C$124,">0")/COUNT($C$5:$C$124) -> 0.68333333 | R11: =COUNTIF($D$5:$D$124,">0")/COUNT($D$5:$D$124) -> 0.7 | S11: =COUNTIF($E$5:$E$124,">0")/COUNT($E$5:$E$124) -> 0.65
A12: 42886 | B12: 0.00066667 | C12: 0.0080217 | D12: 0.01121737 | E12: 0.01517948 | F12: =F11*(1+C12) -> 523846 | G12: =G11*(1+D12) -> 536179.22 | H12: =H11*(1+E12) -> 535516.55 | I12: =MAX(I11,F12) -> 523846 | J12: =MAX(J11,G12) -> 536179.22 | K12: =MAX(K11,H12) -> 535516.55 | L12: =F12/I12-1 -> 0 | M12: =G12/J12-1 -> 0 | N12: =H12/K12-1 -> 0 | P12: Ending value, Sep 2026 (USD) | Q12: =F124 -> 1034019.4 | R12: =G124 -> 1265325.3 | S12: =H124 -> 1074538.1
A13: 42916 | B13: 0.00081667 | C13: 0.00599441 | D13: 0.00376092 | E13: 0.00322068 | F13: =F12*(1+C13) -> 526986.14 | G13: =G12*(1+D13) -> 538195.75 | H13: =H12*(1+E13) -> 537241.27 | I13: =MAX(I12,F13) -> 526986.14 | J13: =MAX(J12,G13) -> 538195.75 | K13: =MAX(K12,H13) -> 537241.27 | L13: =F13/I13-1 -> 0 | M13: =G13/J13-1 -> 0 | N13: =H13/K13-1 -> 0
A14: 42947 | B14: 0.00085833 | C14: 0.01425967 | D14: 0.01366858 | E14: 0.01916432 | F14: =F13*(1+C14) -> 534500.79 | G14: =G13*(1+D14) -> 545552.12 | H14: =H13*(1+E14) -> 547537.14 | I14: =MAX(I13,F14) -> 534500.79 | J14: =MAX(J13,G14) -> 545552.12 | K14: =MAX(K13,H14) -> 547537.14 | L14: =F14/I14-1 -> 0 | M14: =G14/J14-1 -> 0 | N14: =H14/K14-1 -> 0
A15: 42978 | B15: 0.00089167 | C15: 0.00905626 | D15: 0.0054893 | E15: 0.00475993 | F15: =F14*(1+C15) -> 539341.37 | G15: =G14*(1+D15) -> 548546.82 | H15: =H14*(1+E15) -> 550143.38 | I15: =MAX(I14,F15) -> 539341.37 | J15: =MAX(J14,G15) -> 548546.82 | K15: =MAX(K14,H15) -> 550143.38 | L15: =F15/I15-1 -> 0 | M15: =G15/J15-1 -> 0 | N15: =H15/K15-1 -> 0 | P15: Calendar-year returns
A16: 43008 | B16: 0.00084167 | C16: 0.00353706 | D16: 0.0098599 | E16: 0.01127936 | F16: =F15*(1+C16) -> 541249.05 | G16: =G15*(1+D16) -> 553955.44 | H16: =H15*(1+E16) -> 556348.64 | I16: =MAX(I15,F16) -> 541249.05 | J16: =MAX(J15,G16) -> 553955.44 | K16: =MAX(K15,H16) -> 556348.64 | L16: =F16/I16-1 -> 0 | M16: =G16/J16-1 -> 0 | N16: =H16/K16-1 -> 0 | P16: 2017 | Q16: =EXP(SUMPRODUCT((YEAR($A$5:$A$124)=P16)*LN(1+$C$5:$C$124)))-1 -> 0.12119403 | R16: =EXP(SUMPRODUCT((YEAR($A$5:$A$124)=P16)*LN(1+$D$5:$D$124)))-1 -> 0.14191789 | S16: =EXP(SUMPRODUCT((YEAR($A$5:$A$124)=P16)*LN(1+$E$5:$E$124)))-1 -> 0.15802578
A17: 43039 | B17: 0.00088333 | C17: 0.00745092 | D17: 0.01453005 | E17: 0.01412094 | F17: =F16*(1+C17) -> 545281.86 | G17: =G16*(1+D17) -> 562004.44 | H17: =H16*(1+E17) -> 564204.81 | I17: =MAX(I16,F17) -> 545281.86 | J17: =MAX(J16,G17) -> 562004.44 | K17: =MAX(K16,H17) -> 564204.81 | L17: =F17/I17-1 -> 0 | M17: =G17/J17-1 -> 0 | N17: =H17/K17-1 -> 0 | P17: 2018 | Q17: =EXP(SUMPRODUCT((YEAR($A$5:$A$124)=P17)*LN(1+$C$5:$C$124)))-1 -> -0.033401604 | R17: =EXP(SUMPRODUCT((YEAR($A$5:$A$124)=P17)*LN(1+$D$5:$D$124)))-1 -> -0.022336673 | S17: =EXP(SUMPRODUCT((YEAR($A$5:$A$124)=P17)*LN(1+$E$5:$E$124)))-1 -> -0.058260646
A18: 43069 | B18: 0.00095833 | C18: 0.00829678 | D18: 0.01791752 | E18: 0.01192048 | F18: =F17*(1+C18) -> 549805.94 | G18: =G17*(1+D18) -> 572074.16 | H18: =H17*(1+E18) -> 570930.4 | I18: =MAX(I17,F18) -> 549805.94 | J18: =MAX(J17,G18) -> 572074.16 | K18: =MAX(K17,H18) -> 570930.4 | L18: =F18/I18-1 -> 0 | M18: =G18/J18-1 -> 0 | N18: =H18/K18-1 -> 0 | P18: 2019 | Q18: =EXP(SUMPRODUCT((YEAR($A$5:$A$124)=P18)*LN(1+$C$5:$C$124)))-1 -> 0.16166764 | R18: =EXP(SUMPRODUCT((YEAR($A$5:$A$124)=P18)*LN(1+$D$5:$D$124)))-1 -> 0.21833867 | S18: =EXP(SUMPRODUCT((YEAR($A$5:$A$124)=P18)*LN(1+$E$5:$E$124)))-1 -> 0.18907623
A19: 43100 | B19: 0.00105833 | C19: 0.01224923 | D19: 0.00925765 | E19: 0.01032254 | F19: =F18*(1+C19) -> 556540.64 | G19: =G18*(1+D19) -> 577370.22 | H19: =H18*(1+E19) -> 576823.85 | I19: =MAX(I18,F19) -> 556540.64 | J19: =MAX(J18,G19) -> 577370.22 | K19: =MAX(K18,H19) -> 576823.85 | L19: =F19/I19-1 -> 0 | M19: =G19/J19-1 -> 0 | N19: =H19/K19-1 -> 0 | P19: 2020 | Q19: =EXP(SUMPRODUCT((YEAR($A$5:$A$124)=P19)*LN(1+$C$5:$C$124)))-1 -> 0.13578879 | R19: =EXP(SUMPRODUCT((YEAR($A$5:$A$124)=P19)*LN(1+$D$5:$D$124)))-1 -> 0.1526601 | S19: =EXP(SUMPRODUCT((YEAR($A$5:$A$124)=P19)*LN(1+$E$5:$E$124)))-1 -> 0.11423861
A20: 43131 | B20: 0.00115833 | C20: 0.02298712 | D20: 0.02931528 | E20: 0.02916316 | F20: =F19*(1+C20) -> 569333.91 | G20: =G19*(1+D20) -> 594295.99 | H20: =H19*(1+E20) -> 593645.86 | I20: =MAX(I19,F20) -> 569333.91 | J20: =MAX(J19,G20) -> 594295.99 | K20: =MAX(K19,H20) -> 593645.86 | L20: =F20/I20-1 -> 0 | M20: =G20/J20-1 -> 0 | N20: =H20/K20-1 -> 0 | P20: 2021 | Q20: =EXP(SUMPRODUCT((YEAR($A$5:$A$124)=P20)*LN(1+$C$5:$C$124)))-1 -> 0.1067543 | R20: =EXP(SUMPRODUCT((YEAR($A$5:$A$124)=P20)*LN(1+$D$5:$D$124)))-1 -> 0.15862846 | S20: =EXP(SUMPRODUCT((YEAR($A$5:$A$124)=P20)*LN(1+$E$5:$E$124)))-1 -> 0.11186459
A21: 43159 | B21: 0.00121667 | C21: -0.02762927 | D21: -0.02626535 | E21: -0.0326628 | F21: =F20*(1+C21) -> 553603.62 | G21: =G20*(1+D21) -> 578686.6 | H21: =H20*(1+E21) -> 574255.72 | I21: =MAX(I20,F21) -> 569333.91 | J21: =MAX(J20,G21) -> 594295.99 | K21: =MAX(K20,H21) -> 593645.86 | L21: =F21/I21-1 -> -0.02762927 | M21: =G21/J21-1 -> -0.02626535 | N21: =H21/K21-1 -> -0.0326628 | P21: 2022 | Q21: =EXP(SUMPRODUCT((YEAR($A$5:$A$124)=P21)*LN(1+$C$5:$C$124)))-1 -> -0.12966807 | R21: =EXP(SUMPRODUCT((YEAR($A$5:$A$124)=P21)*LN(1+$D$5:$D$124)))-1 -> -0.15952721 | S21: =EXP(SUMPRODUCT((YEAR($A$5:$A$124)=P21)*LN(1+$E$5:$E$124)))-1 -> -0.15645902
A22: 43190 | B22: 0.001375 | C22: 0.00110718 | D22: -0.0140831 | E22: -0.003354 | F22: =F21*(1+C22) -> 554216.56 | G22: =G21*(1+D22) -> 570536.9 | H22: =H21*(1+E22) -> 572329.67 | I22: =MAX(I21,F22) -> 569333.91 | J22: =MAX(J21,G22) -> 594295.99 | K22: =MAX(K21,H22) -> 593645.86 | L22: =F22/I22-1 -> -0.026552681 | M22: =G22/J22-1 -> -0.039978552 | N22: =H22/K22-1 -> -0.035907249 | P22: 2023 | Q22: =EXP(SUMPRODUCT((YEAR($A$5:$A$124)=P22)*LN(1+$C$5:$C$124)))-1 -> 0.12514992 | R22: =EXP(SUMPRODUCT((YEAR($A$5:$A$124)=P22)*LN(1+$D$5:$D$124)))-1 -> 0.17694516 | S22: =EXP(SUMPRODUCT((YEAR($A$5:$A$124)=P22)*LN(1+$E$5:$E$124)))-1 -> 0.15744451
A23: 43220 | B23: 0.00144167 | C23: -0.0002639 | D23: -0.00066318 | E23: -0.00130954 | F23: =F22*(1+C23) -> 554070.31 | G23: =G22*(1+D23) -> 570158.53 | H23: =H22*(1+E23) -> 571580.18 | I23: =MAX(I22,F23) -> 569333.91 | J23: =MAX(J22,G23) -> 594295.99 | K23: =MAX(K22,H23) -> 593645.86 | L23: =F23/I23-1 -> -0.026809573 | M23: =G23/J23-1 -> -0.040615219 | N23: =H23/K23-1 -> -0.037169767 | P23: 2024 | Q23: =EXP(SUMPRODUCT((YEAR($A$5:$A$124)=P23)*LN(1+$C$5:$C$124)))-1 -> 0.10162908 | R23: =EXP(SUMPRODUCT((YEAR($A$5:$A$124)=P23)*LN(1+$D$5:$D$124)))-1 -> 0.1507733 | S23: =EXP(SUMPRODUCT((YEAR($A$5:$A$124)=P23)*LN(1+$E$5:$E$124)))-1 -> 0.10682166
A24: 43251 | B24: 0.00155833 | C24: 0.0067716 | D24: 0.0172948 | E24: 0.00496106 | F24: =F23*(1+C24) -> 557822.25 | G24: =G23*(1+D24) -> 580019.31 | H24: =H23*(1+E24) -> 574415.82 | I24: =MAX(I23,F24) -> 569333.91 | J24: =MAX(J23,G24) -> 594295.99 | K24: =MAX(K23,H24) -> 593645.86 | L24: =F24/I24-1 -> -0.020219517 | M24: =G24/J24-1 -> -0.024022852 | N24: =H24/K24-1 -> -0.032393108 | P24: 2025 | Q24: =EXP(SUMPRODUCT((YEAR($A$5:$A$124)=P24)*LN(1+$C$5:$C$124)))-1 -> 0.16559026 | R24: =EXP(SUMPRODUCT((YEAR($A$5:$A$124)=P24)*LN(1+$D$5:$D$124)))-1 -> 0.13609221 | S24: =EXP(SUMPRODUCT((YEAR($A$5:$A$124)=P24)*LN(1+$E$5:$E$124)))-1 -> 0.16445326
A25: 43281 | B25: 0.00160833 | C25: -0.00212038 | D25: 0.00388842 | E25: -0.00471213 | F25: =F24*(1+C25) -> 556639.45 | G25: =G24*(1+D25) -> 582274.67 | H25: =H24*(1+E25) -> 571709.1 | I25: =MAX(I24,F25) -> 569333.91 | J25: =MAX(J24,G25) -> 594295.99 | K25: =MAX(K24,H25) -> 593645.86 | L25: =F25/I25-1 -> -0.022297024 | M25: =G25/J25-1 -> -0.020227843 | N25: =H25/K25-1 -> -0.036952598
A26: 43312 | B26: 0.00160833 | C26: 0.01188085 | D26: 0.02211146 | E26: 0.0202824 | F26: =F25*(1+C26) -> 563252.8 | G26: =G25*(1+D26) -> 595149.61 | H26: =H25*(1+E26) -> 583304.73 | I26: =MAX(I25,F26) -> 569333.91 | J26: =MAX(J25,G26) -> 595149.61 | K26: =MAX(K25,H26) -> 593645.86 | L26: =F26/I26-1 -> -0.010681082 | M26: =G26/J26-1 -> 0 | N26: =H26/K26-1 -> -0.017419685 | P26: Worst calendar year (2017-2025) | Q26: =MIN(Q16:Q24) -> -0.12966807 | R26: =MIN(R16:R24) -> -0.15952721 | S26: =MIN(S16:S24) -> -0.15645902
A27: 43343 | B27: 0.00169167 | C27: 0.00537671 | D27: 0.02165382 | E27: 0.00623886 | F27: =F26*(1+C27) -> 566281.25 | G27: =G26*(1+D27) -> 608036.87 | H27: =H26*(1+E27) -> 586943.89 | I27: =MAX(I26,F27) -> 569333.91 | J27: =MAX(J26,G27) -> 608036.87 | K27: =MAX(K26,H27) -> 593645.86 | L27: =F27/I27-1 -> -0.0053618006 | M27: =G27/J27-1 -> 0 | N27: =H27/K27-1 -> -0.011289504
A28: 43373 | B28: 0.00175833 | C28: -0.00283477 | D28: 0.00125119 | E28: -0.00066422 | F28: =F27*(1+C28) -> 564675.97 | G28: =G27*(1+D28) -> 608797.64 | H28: =H27*(1+E28) -> 586554.03 | I28: =MAX(I27,F28) -> 569333.91 | J28: =MAX(J27,G28) -> 608797.64 | K28: =MAX(K27,H28) -> 593645.86 | L28: =F28/I28-1 -> -0.0081813712 | M28: =G28/J28-1 -> 0 | N28: =H28/K28-1 -> -0.011946226
A29: 43404 | B29: 0.001825 | C29: -0.03439497 | D29: -0.04403866 | E29: -0.04904447 | F29: =F28*(1+C29) -> 545253.96 | G29: =G28*(1+D29) -> 581987.01 | H29: =H28*(1+E29) -> 557786.8 | I29: =MAX(I28,F29) -> 569333.91 | J29: =MAX(J28,G29) -> 608797.64 | K29: =MAX(K28,H29) -> 593645.86 | L29: =F29/I29-1 -> -0.042294943 | M29: =G29/J29-1 -> -0.04403866 | N29: =H29/K29-1 -> -0.060404799
A30: 43434 | B30: 0.00195 | C30: 0.00938376 | D30: 0.01404534 | E30: 0.01169831 | F30: =F29*(1+C30) -> 550370.49 | G30: =G29*(1+D30) -> 590161.22 | H30: =H29*(1+E30) -> 564311.96 | I30: =MAX(I29,F30) -> 569333.91 | J30: =MAX(J29,G30) -> 608797.64 | K30: =MAX(K29,H30) -> 593645.86 | L30: =F30/I30-1 -> -0.033308069 | M30: =G30/J30-1 -> -0.030611858 | N30: =H30/K30-1 -> -0.049413123
A31: 43465 | B31: 0.001975 | C31: -0.02256517 | D31: -0.04352628 | E31: -0.03738046 | F31: =F30*(1+C31) -> 537951.29 | G31: =G30*(1+D31) -> 564473.69 | H31: =H30*(1+E31) -> 543217.72 | I31: =MAX(I30,F31) -> 569333.91 | J31: =MAX(J30,G31) -> 608797.64 | K31: =MAX(K30,H31) -> 593645.86 | L31: =F31/I31-1 -> -0.055121637 | M31: =G31/J31-1 -> -0.072805718 | N31: =H31/K31-1 -> -0.084946498
A32: 43496 | B32: 0.00204167 | C32: 0.04550827 | D32: 0.05168285 | E32: 0.04914031 | F32: =F31*(1+C32) -> 562432.52 | G32: =G31*(1+D32) -> 593647.3 | H32: =H31*(1+E32) -> 569911.61 | I32: =MAX(I31,F32) -> 569333.91 | J32: =MAX(J31,G32) -> 608797.64 | K32: =MAX(K31,H32) -> 593645.86 | L32: =F32/I32-1 -> -0.012121857 | M32: =G32/J32-1 -> -0.024885675 | N32: =H32/K32-1 -> -0.039980485
A33: 43524 | B33: 0.00200833 | C33: 0.01043267 | D33: 0.01953813 | E33: 0.01615145 | F33: =F32*(1+C33) -> 568300.19 | G33: =G32*(1+D33) -> 605246.06 | H33: =H32*(1+E33) -> 579116.51 | I33: =MAX(I32,F33) -> 569333.91 | J33: =MAX(J32,G33) -> 608797.64 | K33: =MAX(K32,H33) -> 593645.86 | L33: =F33/I33-1 -> -0.0018156502 | M33: =G33/J33-1 -> -0.0058337642 | N33: =H33/K33-1 -> -0.024474778
A34: 43555 | B34: 0.00204167 | C34: 0.01410384 | D34: 0.01925176 | E34: 0.0149864 | F34: =F33*(1+C34) -> 576315.41 | G34: =G33*(1+D34) -> 616898.11 | H34: =H33*(1+E34) -> 587795.38 | I34: =MAX(I33,F34) -> 576315.41 | J34: =MAX(J33,G34) -> 616898.11 | K34: =MAX(K33,H34) -> 593645.86 | L34: =F34/I34-1 -> 0 | M34: =G34/J34-1 -> 0 | N34: =H34/K34-1 -> -0.0098551669
A35: 43585 | B35: 0.002 | C35: 0.01578628 | D35: 0.02371001 | E35: 0.02246308 | F35: =F34*(1+C35) -> 585413.29 | G35: =G34*(1+D35) -> 631524.77 | H35: =H34*(1+E35) -> 600999.07 | I35: =MAX(I34,F35) -> 585413.29 | J35: =MAX(J34,G35) -> 631524.77 | K35: =MAX(K34,H35) -> 600999.07 | L35: =F35/I35-1 -> 0 | M35: =G35/J35-1 -> 0 | N35: =H35/K35-1 -> 0
A36: 43616 | B36: 0.002025 | C36: -0.02053728 | D36: -0.0314522 | E36: -0.03054951 | F36: =F35*(1+C36) -> 573390.49 | G36: =G35*(1+D36) -> 611661.93 | H36: =H35*(1+E36) -> 582638.85 | I36: =MAX(I35,F36) -> 585413.29 | J36: =MAX(J35,G36) -> 631524.77 | K36: =MAX(K35,H36) -> 600999.07 | L36: =F36/I36-1 -> -0.02053728 | M36: =G36/J36-1 -> -0.0314522 | N36: =H36/K36-1 -> -0.03054951
A37: 43646 | B37: 0.00195833 | C37: 0.03648917 | D37: 0.04553864 | E37: 0.0433007 | F37: =F36*(1+C37) -> 594313.03 | G37: =G36*(1+D37) -> 639516.18 | H37: =H36*(1+E37) -> 607867.52 | I37: =MAX(I36,F37) -> 594313.03 | J37: =MAX(J36,G37) -> 639516.18 | K37: =MAX(K36,H37) -> 607867.52 | L37: =F37/I37-1 -> 0 | M37: =G37/J37-1 -> 0 | N37: =H37/K37-1 -> 0
A38: 43677 | B38: 0.00176667 | C38: 0.00296321 | D38: 0.00979916 | E38: -0.00128578 | F38: =F37*(1+C38) -> 596074.11 | G38: =G37*(1+D38) -> 645782.9 | H38: =H37*(1+E38) -> 607085.93 | I38: =MAX(I37,F38) -> 596074.11 | J38: =MAX(J37,G38) -> 645782.9 | K38: =MAX(K37,H38) -> 607867.52 | L38: =F38/I38-1 -> 0 | M38: =G38/J38-1 -> 0 | N38: =H38/K38-1 -> -0.00128578
... A124: 46295 | B124: 0.00325833 | C124: -0.02234846 | D124: -0.01223144 | E124: -0.01749357 | F124: =F123*(1+C124) -> 1034019.4 | G124: =G123*(1+D124) -> 1265325.3 | H124: =H123*(1+E124) -> 1074538.1 | I124: =MAX(I123,F124) -> 1057656.4 | J124: =MAX(J123,G124) -> 1280993.7 | K124: =MAX(K123,H124) -> 1093670.3 | L124: =F124/I124-1 -> -0.02234846 | M124: =G124/J124-1 -> -0.01223144 | N124: =H124/K124-1 -> -0.01749357

Sheet VaR
A1: Value at Risk and Conditional VaR, proposed portfolio
A3: Date | B3: Daily return (backtest) | D3: Measure | E3: 95% | F3: 99% | G3: 95% (USD) | H3: 99% (USD)
A4: 42646 | B4: -0.003142 | D4: Daily historical VaR | E4: =-_xlfn.PERCENTILE.INC($B$4:$B$2523,1-0.95) -> 0.0077970969 | F4: =-_xlfn.PERCENTILE.INC($B$4:$B$2523,1-0.99) -> 0.014422777 | G4: =E4*Allocation!$B$2 -> 3898.5485 | H4: =F4*Allocation!$B$2 -> 7211.3883
A5: 42647 | B5: -0.0058028325 | D5: Daily historical CVaR | E5: =-AVERAGEIF($B$4:$B$2523,"<="&_xlfn.PERCENTILE.INC($B$4:$B$2523,1-0.95)) -> 0.012883167 | F5: =-AVERAGEIF($B$4:$B$2523,"<="&_xlfn.PERCENTILE.INC($B$4:$B$2523,1-0.99)) -> 0.022949728 | G5: =E5*Allocation!$B$2 -> 6441.5833 | H5: =F5*Allocation!$B$2 -> 11474.864
A6: 42648 | B6: 0.0015787327 | D6: Daily parametric VaR | E6: =-(AVERAGE($B$4:$B$2523)-_xlfn.NORM.S.INV(0.95)*_xlfn.STDEV.S($B$4:$B$2523)) -> 0.0086782393 | F6: =-(AVERAGE($B$4:$B$2523)-_xlfn.NORM.S.INV(0.99)*_xlfn.STDEV.S($B$4:$B$2523)) -> 0.01240043 | G6: =E6*Allocation!$B$2 -> 4339.1197 | H6: =F6*Allocation!$B$2 -> 6200.2149
A7: 42649 | B7: -0.0011980601 | D7: Monthly historical VaR | E7: =-_xlfn.PERCENTILE.INC(Backtest!$C$5:$C$124,1-0.95) -> 0.032093111 | F7: =-_xlfn.PERCENTILE.INC(Backtest!$C$5:$C$124,1-0.99) -> 0.061301773 | G7: =E7*Allocation!$B$2 -> 16046.555 | H7: =F7*Allocation!$B$2 -> 30650.887
A8: 42650 | B8: -0.0014552037 | D8: Monthly historical CVaR | E8: =-AVERAGEIF(Backtest!$C$5:$C$124,"<="&_xlfn.PERCENTILE.INC(Backtest!$C$5:$C$124,1-0.95)) -> 0.051804297 | F8: =-AVERAGEIF(Backtest!$C$5:$C$124,"<="&_xlfn.PERCENTILE.INC(Backtest!$C$5:$C$124,1-0.99)) -> 0.06879983 | G8: =E8*Allocation!$B$2 -> 25902.148 | H8: =F8*Allocation!$B$2 -> 34399.915
A9: 42653 | B9: 0.001945079 | D9: Monthly parametric VaR | E9: =-(AVERAGE(Backtest!$C$5:$C$124)-_xlfn.NORM.S.INV(0.95)*_xlfn.STDEV.S(Backtest!$C$5:$C$124)) -> 0.032951396 | F9: =-(AVERAGE(Backtest!$C$5:$C$124)-_xlfn.NORM.S.INV(0.99)*_xlfn.STDEV.S(Backtest!$C$5:$C$124)) -> 0.049237764 | G9: =E9*Allocation!$B$2 -> 16475.698 | H9: =F9*Allocation!$B$2 -> 24618.882
A10: 42654 | B10: -0.0069880418
A11: 42655 | B11: 0.00079068019 | D11: Daily observations | E11: =COUNT($B$4:$B$2523) -> 2520
A12: 42656 | B12: -0.00069131125
A13: 42657 | B13: -0.00092597954
A14: 42660 | B14: -0.00054554774
A15: 42661 | B15: 0.0046822225
A16: 42662 | B16: 0.0021847219
A17: 42663 | B17: -0.0003607586
A18: 42664 | B18: 0.0001942719
A19: 42667 | B19: 0.0012870715
A20: 42668 | B20: -0.00035557437
A21: 42669 | B21: -0.0025714257
A22: 42670 | B22: -0.0029821127
A23: 42671 | B23: -0.0011020287
... A2523: 46307 | B2523: -0.0011664485

Sheet Scenarios
A1: Hypothetical scenario shocks (assumptions, editable) and portfolio impact
A3: Ticker | B3: Weight | C3: Global equity bear market | D3: Rates +150bp (bond sell-off) | E3: Stagflation, Brent to $150 | F3: Gulf escalation / Hormuz closure | G3: Recession, Fed cuts 200bp | H3: US dollar +10%
A4: VTI | B4: =Allocation!D6 -> 0.25 | C4: -0.3 | D4: -0.1 | E4: -0.15 | F4: -0.1 | G4: -0.2 | H4: -0.03
A5: VEA | B5: =Allocation!D7 -> 0.1 | C5: -0.3 | D5: -0.1 | E5: -0.18 | F5: -0.15 | G5: -0.22 | H5: -0.12
A6: VWO | B6: =Allocation!D8 -> 0.05 | C6: -0.35 | D6: -0.12 | E6: -0.18 | F6: -0.15 | G6: -0.25 | H6: -0.15
A7: KSA | B7: =Allocation!D9 -> 0.03 | C7: -0.3 | D7: -0.08 | E7: 0.05 | F7: -0.25 | G7: -0.2 | H7: -0.02
A8: UAE | B8: =Allocation!D10 -> 0.02 | C8: -0.3 | D8: -0.08 | E8: 0 | F8: -0.3 | G8: -0.2 | H8: -0.02
A9: VNQ | B9: =Allocation!D11 -> 0.03 | C9: -0.3 | D9: -0.15 | E9: -0.15 | F9: -0.08 | G9: -0.2 | H9: -0.03
A10: BND | B10: =Allocation!D12 -> 0.25 | C10: 0.04 | D10: -0.09 | E10: -0.05 | F10: 0.02 | G10: 0.08 | H10: 0.01
A11: SCHP | B11: =Allocation!D13 -> 0.12 | C11: 0.02 | D11: -0.07 | E11: 0.02 | F11: 0.03 | G11: 0.04 | H11: 0
A12: IAU | B12: =Allocation!D14 -> 0.07 | C12: 0.08 | D12: -0.05 | E12: 0.15 | F12: 0.12 | G12: 0.1 | H12: -0.08
A13: BIL | B13: =Allocation!D15 -> 0.08 | C13: 0.01 | D13: 0.01 | E13: 0.01 | F13: 0.01 | G13: 0.01 | H13: 0.01
A15: Portfolio impact | C15: =SUMPRODUCT($B$4:$B$13,C4:C13) -> -0.1277 | D15: =SUMPRODUCT($B$4:$B$13,D4:D13) -> -0.0831 | E15: =SUMPRODUCT($B$4:$B$13,E4:E13) -> -0.0663 | F15: =SUMPRODUCT($B$4:$B$13,F4:F13) -> -0.0456 | G15: =SUMPRODUCT($B$4:$B$13,G4:G13) -> -0.0679 | H15: =SUMPRODUCT($B$4:$B$13,H4:H13) -> -0.0312
A16: Impact (USD) | C16: =C15*Allocation!$B$2 -> -63850 | D16: =D15*Allocation!$B$2 -> -41550 | E16: =E15*Allocation!$B$2 -> -33150 | F16: =F15*Allocation!$B$2 -> -22800 | G16: =G15*Allocation!$B$2 -> -33950 | H16: =H15*Allocation!$B$2 -> -15600

Sheet Projection
A1: Deterministic 10-year projection at the forward expected return (median-type path, not a forecast)
A3: Expected return (CMA) | B3: =PortfolioRisk!B26 -> 0.060937
A4: Volatility | B4: =PortfolioRisk!B28 -> 0.083284565
A5: Geometric return approx. (mean - variance/2) | B5: =B3-B4^2/2 -> 0.057468841
A6: Advisory and custody fee | B6: 0.005
A7: Annual withdrawal, year 1 (USD) | B7: 15000
A8: Inflation indexation | B8: =PortfolioRisk!B7 -> 0.0233
A10: Year | B10: Start value | C10: Growth | D10: Fee | E10: Withdrawal | F10: End value | G10: End value (real)
A11: 1 | B11: =Allocation!B2 -> 500000 | C11: =B11*$B$5 -> 28734.42 | D11: =-B11*$B$6 -> -2500 | E11: =-$B$7*(1+$B$8)^(A11-1) -> -15000 | F11: =SUM(B11:E11) -> 511234.42 | G11: =F11/(1+$B$8)^A11 -> 499593.88
A12: 2 | B12: =F11 -> 511234.42 | C12: =B12*$B$5 -> 29380.049 | D12: =-B12*$B$6 -> -2556.1721 | E12: =-$B$7*(1+$B$8)^(A12-1) -> -15349.5 | F12: =SUM(B12:E12) -> 522708.8 | G12: =F12/(1+$B$8)^A12 -> 499176.19
A13: 3 | B13: =F12 -> 522708.8 | C13: =B13*$B$5 -> 30039.469 | D13: =-B13*$B$6 -> -2613.544 | E13: =-$B$7*(1+$B$8)^(A13-1) -> -15707.143 | F13: =SUM(B13:E13) -> 534427.58 | G13: =F13/(1+$B$8)^A13 -> 498746.59
A14: 4 | B14: =F13 -> 534427.58 | C14: =B14*$B$5 -> 30712.933 | D14: =-B14*$B$6 -> -2672.1379 | E14: =-$B$7*(1+$B$8)^(A14-1) -> -16073.12 | F14: =SUM(B14:E14) -> 546395.25 | G14: =F14/(1+$B$8)^A14 -> 498304.74
A15: 5 | B15: =F14 -> 546395.25 | C15: =B15*$B$5 -> 31400.702 | D15: =-B15*$B$6 -> -2731.9763 | E15: =-$B$7*(1+$B$8)^(A15-1) -> -16447.623 | F15: =SUM(B15:E15) -> 558616.36 | G15: =F15/(1+$B$8)^A15 -> 497850.3
A16: 6 | B16: =F15 -> 558616.36 | C16: =B16*$B$5 -> 32103.034 | D16: =-B16*$B$6 -> -2793.0818 | E16: =-$B$7*(1+$B$8)^(A16-1) -> -16830.853 | F16: =SUM(B16:E16) -> 571095.46 | G16: =F16/(1+$B$8)^A16 -> 497382.91
A17: 7 | B17: =F16 -> 571095.46 | C17: =B17*$B$5 -> 32820.194 | D17: =-B17*$B$6 -> -2855.4773 | E17: =-$B$7*(1+$B$8)^(A17-1) -> -17223.012 | F17: =SUM(B17:E17) -> 583837.16 | G17: =F17/(1+$B$8)^A17 -> 496902.19
A18: 8 | B18: =F17 -> 583837.16 | C18: =B18*$B$5 -> 33552.445 | D18: =-B18*$B$6 -> -2919.1858 | E18: =-$B$7*(1+$B$8)^(A18-1) -> -17624.308 | F18: =SUM(B18:E18) -> 596846.11 | G18: =F18/(1+$B$8)^A18 -> 496407.78
A19: 9 | B19: =F18 -> 596846.11 | C19: =B19*$B$5 -> 34300.054 | D19: =-B19*$B$6 -> -2984.2306 | E19: =-$B$7*(1+$B$8)^(A19-1) -> -18034.955 | F19: =SUM(B19:E19) -> 610126.98 | G19: =F19/(1+$B$8)^A19 -> 495899.26
A20: 10 | B20: =F19 -> 610126.98 | C20: =B20*$B$5 -> 35063.29 | D20: =-B20*$B$6 -> -3050.6349 | E20: =-$B$7*(1+$B$8)^(A20-1) -> -18455.169 | F20: =SUM(B20:E20) -> 623684.47 | G20: =F20/(1+$B$8)^A20 -> 495376.26
A23: Monte Carlo results (10,000 paths, from Python; static values)
A24: Percentile / probability | B24: Forward assumptions | C24: Historical bootstrap
A25: 5th percentile | B25: 371798.19 | C25: 463234.1
A26: 25th percentile | B26: 508220.89 | C26: 619939.93
A27: Median | B27: 628817.7 | C27: 752823.59
A28: 75th percentile | B28: 765932.63 | C28: 890091.01
A29: 95th percentile | B29: 1027712.7 | C29: 1114327.3
A30: Median, real (today's USD) | B30: 499453.45 | C30: 597948.08
A31: P(nominal value >= 500k) | B31: 0.7643 | C31: 0.92
A32: P(real value >= 500k) | B32: 0.4977 | C32: 0.7333
A33: P(value < 400k) | B33: 0.0762 | C33: 0.0179

Sheet Checks
A1: Reconciliation: Excel formulas versus Python results
A3: Item | B3: Excel (live formula) | C3: Python | D3: Difference | E3: Status
A4: Allocation: weighted expense ratio | B4: =Allocation!F16 -> 0.000915 | C4: 0.000915 | D4: =B4-C4 -> 0 | E4: =IF(ABS(D4)<0.0001,"PASS","CHECK") -> PASS
A5: Allocation: weighted distribution yield | B5: =Allocation!H16 -> 0.028283 | C5: 0.028283 | D5: =B5-C5 -> 0 | E5: =IF(ABS(D5)<0.0001,"PASS","CHECK") -> PASS
A6: Portfolio volatility (ex-ante, 10y covariance) | B6: =PortfolioRisk!B28 -> 0.083284565 | C6: 0.083284565 | D6: =B6-C6 -> 0 | E6: =IF(ABS(D6)<0.0001,"PASS","CHECK") -> PASS
A7: Expected return, historical means | B7: =PortfolioRisk!B25 -> 0.074949263 | C7: 0.074949263 | D7: =B7-C7 -> 0 | E7: =IF(ABS(D7)<0.0001,"PASS","CHECK") -> PASS
A8: Expected return, forward CMA | B8: =PortfolioRisk!B26 -> 0.060937 | C8: 0.060937 | D8: =B8-C8 -> 0 | E8: =IF(ABS(D8)<0.0001,"PASS","CHECK") -> PASS
A9: Proposed: CAGR | B9: =Backtest!Q4 -> 0.07536493 | C9: 0.075364933 | D9: =B9-C9 -> -3.2047174e-09 | E9: =IF(ABS(D9)<0.0001,"PASS","CHECK") -> PASS
A10: Proposed: volatility | B10: =Backtest!Q5 -> 0.082785195 | C10: 0.082785194 | D10: =B10-C10 -> 2.7808059e-10 | E10: =IF(ABS(D10)<0.0001,"PASS","CHECK") -> PASS
A11: Proposed: Sharpe | B11: =Backtest!Q6 -> 0.62119598 | C11: 0.62119603 | D11: =B11-C11 -> -5.0095962e-08 | E11: =IF(ABS(D11)<0.0001,"PASS","CHECK") -> PASS
A12: Proposed: Sortino | B12: =Backtest!Q7 -> 0.92257373 | C12: 0.92257381 | D12: =B12-C12 -> -7.8786699e-08 | E12: =IF(ABS(D12)<0.0001,"PASS","CHECK") -> PASS
A13: Proposed: max drawdown (month-end) | B13: =Backtest!Q8 -> -0.17010315 | C13: -0.17010314 | D13: =B13-C13 -> -8.3165433e-09 | E13: =IF(ABS(D13)<0.0001,"PASS","CHECK") -> PASS
A14: Proposed: worst calendar year | B14: =Backtest!Q26 -> -0.12966807 | C14: -0.12966806 | D14: =B14-C14 -> -1.5859017e-08 | E14: =IF(ABS(D14)<0.0001,"PASS","CHECK") -> PASS
A15: 60/40 (SPY/AGG): CAGR | B15: =Backtest!R4 -> 0.097294542 | C15: 0.097294542 | D15: =B15-C15 -> -5.1236504e-10 | E15: =IF(ABS(D15)<0.0001,"PASS","CHECK") -> PASS
A16: 60/40 (SPY/AGG): volatility | B16: =Backtest!R5 -> 0.10208182 | C16: 0.10208182 | D16: =B16-C16 -> 8.134981e-10 | E16: =IF(ABS(D16)<0.0001,"PASS","CHECK") -> PASS
A17: 60/40 (SPY/AGG): Sharpe | B17: =Backtest!R6 -> 0.72016773 | C17: 0.72016775 | D17: =B17-C17 -> -1.9327071e-08 | E17: =IF(ABS(D17)<0.0001,"PASS","CHECK") -> PASS
A18: 60/40 (SPY/AGG): Sortino | B18: =Backtest!R7 -> 1.1049736 | C18: 1.1049736 | D18: =B18-C18 -> -2.8879726e-08 | E18: =IF(ABS(D18)<0.0001,"PASS","CHECK") -> PASS
A19: 60/40 (SPY/AGG): max drawdown (month-end) | B19: =Backtest!R8 -> -0.20084983 | C19: -0.20084983 | D19: =B19-C19 -> -1.8398657e-09 | E19: =IF(ABS(D19)<0.0001,"PASS","CHECK") -> PASS
A20: 60/40 (SPY/AGG): worst calendar year | B20: =Backtest!R26 -> -0.15952721 | C20: -0.15952721 | D20: =B20-C20 -> -1.5282333e-09 | E20: =IF(ABS(D20)<0.0001,"PASS","CHECK") -> PASS
A21: Benchmark (AOR): CAGR | B21: =Backtest!S4 -> 0.0795063 | C21: 0.079506297 | D21: =B21-C21 -> 3.2608827e-09 | E21: =IF(ABS(D21)<0.0001,"PASS","CHECK") -> PASS
A22: Benchmark (AOR): volatility | B22: =Backtest!S5 -> 0.10008897 | C22: 0.10008897 | D22: =B22-C22 -> 1.5129223e-09 | E22: =IF(ABS(D22)<0.0001,"PASS","CHECK") -> PASS
A23: Benchmark (AOR): Sharpe | B23: =Backtest!S6 -> 0.56824209 | C23: 0.56824208 | D23: =B23-C23 -> 1.3254145e-08 | E23: =IF(ABS(D23)<0.0001,"PASS","CHECK") -> PASS
A24: Benchmark (AOR): Sortino | B24: =Backtest!S7 -> 0.83646926 | C24: 0.83646923 | D24: =B24-C24 -> 2.6789647e-08 | E24: =IF(ABS(D24)<0.0001,"PASS","CHECK") -> PASS
A25: Benchmark (AOR): max drawdown (month-end) | B25: =Backtest!S8 -> -0.20750911 | C25: -0.20750911 | D25: =B25-C25 -> 8.0348611e-10 | E25: =IF(ABS(D25)<0.0001,"PASS","CHECK") -> PASS
A26: Benchmark (AOR): worst calendar year | B26: =Backtest!S26 -> -0.15645902 | C26: -0.15645902 | D26: =B26-C26 -> 5.6124249e-09 | E26: =IF(ABS(D26)<0.0001,"PASS","CHECK") -> PASS
A27: Daily historical VaR 95% | B27: =VaR!E4 -> 0.0077970969 | C27: 0.0077970979 | D27: =B27-C27 -> -1.0232211e-09 | E27: =IF(ABS(D27)<0.0001,"PASS","CHECK") -> PASS
A28: Daily historical CVaR 95% | B28: =VaR!E5 -> 0.012883167 | C28: 0.012883166 | D28: =B28-C28 -> 3.2135015e-10 | E28: =IF(ABS(D28)<0.0001,"PASS","CHECK") -> PASS
A29: Monthly historical VaR 95% | B29: =VaR!E7 -> 0.032093111 | C29: 0.032093109 | D29: =B29-C29 -> 1.4127015e-09 | E29: =IF(ABS(D29)<0.0001,"PASS","CHECK") -> PASS
A30: Monthly parametric VaR 99% | B30: =VaR!F9 -> 0.049237764 | C30: 0.049237764 | D30: =B30-C30 -> 4.3461926e-10 | E30: =IF(ABS(D30)<0.0001,"PASS","CHECK") -> PASS
A31: 1-year parametric VaR 95% (CMA) | B31: =PortfolioRisk!B32 -> 0.076053919 | C31: 0.076053919 | D31: =B31-C31 -> 0 | E31: =IF(ABS(D31)<0.0001,"PASS","CHECK") -> PASS
A32: Scenario: Global equity bear market | B32: =Scenarios!C15 -> -0.1277 | C32: -0.1277 | D32: =B32-C32 -> 0 | E32: =IF(ABS(D32)<0.0001,"PASS","CHECK") -> PASS
A33: Scenario: Rates +150bp (bond sell-off) | B33: =Scenarios!D15 -> -0.0831 | C33: -0.0831 | D33: =B33-C33 -> 0 | E33: =IF(ABS(D33)<0.0001,"PASS","CHECK") -> PASS
A34: Scenario: Stagflation, Brent to $150 | B34: =Scenarios!E15 -> -0.0663 | C34: -0.0663 | D34: =B34-C34 -> 0 | E34: =IF(ABS(D34)<0.0001,"PASS","CHECK") -> PASS
A35: Scenario: Gulf escalation / Hormuz closure | B35: =Scenarios!F15 -> -0.0456 | C35: -0.0456 | D35: =B35-C35 -> 0 | E35: =IF(ABS(D35)<0.0001,"PASS","CHECK") -> PASS
A36: Scenario: Recession, Fed cuts 200bp | B36: =Scenarios!G15 -> -0.0679 | C36: -0.0679 | D36: =B36-C36 -> 0 | E36: =IF(ABS(D36)<0.0001,"PASS","CHECK") -> PASS
A37: Scenario: US dollar +10% | B37: =Scenarios!H15 -> -0.0312 | C37: -0.0312 | D37: =B37-C37 -> 0 | E37: =IF(ABS(D37)<0.0001,"PASS","CHECK") -> PASS
A38: VTI: volatility | B38: =AssetStats!E4 -> 0.15773362 | C38: 0.157734 | D38: =B38-C38 -> -3.8321704e-07 | E38: =IF(ABS(D38)<0.0001,"PASS","CHECK") -> PASS
A39: VTI: CAGR | B39: =AssetStats!D4 -> 0.14700792 | C39: 0.147008 | D39: =B39-C39 -> -7.9030079e-08 | E39: =IF(ABS(D39)<0.0001,"PASS","CHECK") -> PASS
A40: VEA: volatility | B40: =AssetStats!E5 -> 0.15541578 | C40: 0.155416 | D40: =B40-C40 -> -2.2074091e-07 | E40: =IF(ABS(D40)<0.0001,"PASS","CHECK") -> PASS
A41: VEA: CAGR | B41: =AssetStats!D5 -> 0.097372333 | C41: 0.097372 | D41: =B41-C41 -> 3.3348882e-07 | E41: =IF(ABS(D41)<0.0001,"PASS","CHECK") -> PASS
A42: VWO: volatility | B42: =AssetStats!E6 -> 0.15518417 | C42: 0.155184 | D42: =B42-C42 -> 1.7406196e-07 | E42: =IF(ABS(D42)<0.0001,"PASS","CHECK") -> PASS
A43: VWO: CAGR | B43: =AssetStats!D6 -> 0.075849095 | C43: 0.075849 | D43: =B43-C43 -> 9.5146364e-08 | E43: =IF(ABS(D43)<0.0001,"PASS","CHECK") -> PASS
A44: KSA: volatility | B44: =AssetStats!E7 -> 0.18025163 | C44: 0.180252 | D44: =B44-C44 -> -3.6977163e-07 | E44: =IF(ABS(D44)<0.0001,"PASS","CHECK") -> PASS
A45: KSA: CAGR | B45: =AssetStats!D7 -> 0.083588519 | C45: 0.083589 | D45: =B45-C45 -> -4.8087907e-07 | E45: =IF(ABS(D45)<0.0001,"PASS","CHECK") -> PASS
A46: UAE: volatility | B46: =AssetStats!E8 -> 0.17631771 | C46: 0.176318 | D46: =B46-C46 -> -2.8715914e-07 | E46: =IF(ABS(D46)<0.0001,"PASS","CHECK") -> PASS
A47: UAE: CAGR | B47: =AssetStats!D8 -> 0.058907253 | C47: 0.058907 | D47: =B47-C47 -> 2.5289833e-07 | E47: =IF(ABS(D47)<0.0001,"PASS","CHECK") -> PASS
A48: VNQ: volatility | B48: =AssetStats!E9 -> 0.17700042 | C48: 0.177 | D48: =B48-C48 -> 4.233461e-07 | E48: =IF(ABS(D48)<0.0001,"PASS","CHECK") -> PASS
A49: VNQ: CAGR | B49: =AssetStats!D9 -> 0.044044029 | C49: 0.044044 | D49: =B49-C49 -> 2.9361772e-08 | E49: =IF(ABS(D49)<0.0001,"PASS","CHECK") -> PASS
A50: BND: volatility | B50: =AssetStats!E10 -> 0.052493311 | C50: 0.052493 | D50: =B50-C50 -> 3.1098085e-07 | E50: =IF(ABS(D50)<0.0001,"PASS","CHECK") -> PASS
A51: BND: CAGR | B51: =AssetStats!D10 -> 0.011800683 | C51: 0.011801 | D51: =B51-C51 -> -3.1686093e-07 | E51: =IF(ABS(D51)<0.0001,"PASS","CHECK") -> PASS
A52: SCHP: volatility | B52: =AssetStats!E11 -> 0.05037572 | C52: 0.050376 | D52: =B52-C52 -> -2.7995897e-07 | E52: =IF(ABS(D52)<0.0001,"PASS","CHECK") -> PASS
A53: SCHP: CAGR | B53: =AssetStats!D11 -> 0.020736047 | C53: 0.020736 | D53: =B53-C53 -> 4.6788353e-08 | E53: =IF(ABS(D53)<0.0001,"PASS","CHECK") -> PASS
A54: IAU: volatility | B54: =AssetStats!E12 -> 0.15453119 | C54: 0.154531 | D54: =B54-C54 -> 1.9365738e-07 | E54: =IF(ABS(D54)<0.0001,"PASS","CHECK") -> PASS
A55: IAU: CAGR | B55: =AssetStats!D12 -> 0.11896356 | C55: 0.118964 | D55: =B55-C55 -> -4.4355195e-07 | E55: =IF(ABS(D55)<0.0001,"PASS","CHECK") -> PASS
A56: BIL: volatility | B56: =AssetStats!E13 -> 0.0055694563 | C56: 0.005569 | D56: =B56-C56 -> 4.563433e-07 | E56: =IF(ABS(D56)<0.0001,"PASS","CHECK") -> PASS
A57: BIL: CAGR | B57: =AssetStats!D13 -> 0.022950561 | C57: 0.022951 | D57: =B57-C57 -> -4.3853236e-07 | E57: =IF(ABS(D57)<0.0001,"PASS","CHECK") -> PASS
A58: Correlation VTI-BND | B58: =Correlation!H4 -> 0.43813537 | C58: 0.4381 | D58: =B58-C58 -> 3.5366133e-05 | E58: =IF(ABS(D58)<0.0001,"PASS","CHECK") -> PASS
A59: Correlation VTI-IAU | B59: =Correlation!J4 -> 0.12260212 | C59: 0.1226 | D59: =B59-C59 -> 2.1223095e-06 | E59: =IF(ABS(D59)<0.0001,"PASS","CHECK") -> PASS
A61: Number of checks passing | B61: =COUNTIF(E4:E59,"PASS") -> 56 | C61: 56

Sheet Sources
A1: id | B1: item | C1: value_used | D1: as_of | E1: source | F1: url | G1: retrieved
A2: S1 | B2: Daily adjusted ETF closes (dividends reinvested) for VTI VEA VWO KSA UAE VNQ BND SCHP IAU BIL SPY AGG AOR SPUS HLAL SPSK | C2: see prices_adjusted_daily.csv | D2: 2026-10-12 (latest close available from the feed at retrieval; 13 Oct ETF bars not yet published) | E2: Yahoo Finance via yfinance 1.7.0 | F2: https://finance.yahoo.com | G2: 2026-10-14
A3: S2 | B3: US Treasury daily par yield curve (nominal) | C3: 3M 4.26%; 2Y 4.79%; 5Y 5.00%; 10Y 5.21%; 30Y 5.56% | D3: 2026-10-13 | E3: US Department of the Treasury | F3: https://home.treasury.gov/resource-center/data-chart-center/interest-rates/daily-treasury-rates.csv/2026/all?type=daily_treasury_yield_curve | G3: 2026-10-14
A4: S3 | B4: US Treasury daily real (TIPS) par yield curve | C4: 5Y 2.67%; 10Y 2.88% | D4: 2026-10-13 | E4: US Department of the Treasury | F4: https://home.treasury.gov/resource-center/data-chart-center/interest-rates/daily-treasury-rates.csv/2026/all?type=daily_treasury_real_yield_curve | G4: 2026-10-14
A5: S4 | B5: FRED series (DGS3MO DGS2 DGS10 DGS30 DFII10 T10YIE DFF DFEDTARU DFEDTARL CPIAUCSL CPILFESL UNRATE DTWEXBGS DCOILBRENTEU BAMLC0A0CM BAMLH0A0HYM2) | C5: see fred_series.csv and data_asof.json | D5: various (daily series to 2026-10-09/13; CPI Aug-2026; unemployment Sep-2026) | E5: Federal Reserve Bank of St. Louis (FRED) | F5: https://fred.stlouisfed.org | G5: 2026-10-14
A6: S5 | B6: FOMC decision: target range raised 25bp to 3.75%-4.00% (12-0 vote); SEP median PCE inflation 3.7% (2026) and 2.3% (2027); GDP 2.3% (2026) | C6: 3.75%-4.00% | D6: 2026-09-16 | E6: Federal Reserve Board: FOMC statement and Chair's press conference transcript | F6: https://www.federalreserve.gov/monetarypolicy/files/monetary20260916a1.pdf | G6: 2026-10-14
A7: S6 | B7: US CPI August 2026: headline +3.4% y/y; core +2.4% y/y; energy +16.3% y/y; next release (September CPI) 14 Oct 2026 08:30 ET | C7: 3.4% / 2.4% | D7: 2026-09-11 | E7: US Bureau of Labor Statistics CPI news release | F7: https://www.bls.gov/news.release/archives/cpi_09112026.htm | G7: 2026-10-14
A8: S7 | B8: Brent futures settle $105.69 (13 Oct) after $106.65 on 12 Oct (highest since 15 Sep); WTI $94.14; Houthi attacks on Saudi Arabia and US-Russia diesel arrangement | C8: Brent $105.69 | D8: 2026-10-13 | E8: Reuters (via financialnewsletter.com) and Economic Times | F8: https://economictimes.indiatimes.com/markets/commodities/news/oil-price-today-october-13-crude-oil-falls-to-105-as-traders-assess-russian-supply-mideast-attacks-whats-next/articleshow/134906049.cms | G8: 2026-10-14
A9: S8 | B9: US equity close: S&P 500 7805.45 (-0.02%); Dow 51670.10; Nasdaq 27204.38; 10Y 5.21%; VIX 15.27; dollar index futures 102.05 | C9: S&P 500 7805.45 | D9: 2026-10-13 | E9: Associated Press market report; Dow Jones / Morningstar Data Talk | F9: https://apnews.com/article/stocks-markets-us-tech-oil-mideast-a2edaf9ec297fb75ff2a4e245063ec08 | G9: 2026-10-14
A10: S9 | B10: 10Y Treasury 5.216% (Tradeweb 3pm); 52-week high 5.310% on 5 Oct 2026; +1.06pp year to date | C10: 5.216% | D10: 2026-10-13 | E10: Dow Jones Newswires via Morningstar | F10: https://www.morningstar.com/news/dow-jones/202610137666/10-year-treasury-yield-falls-to-5216-data-talk | G10: 2026-10-14
A11: S10 | B11: Gold: record about $5590/oz intraday on 28 Jan 2026; about 25% below record in mid-October; COMEX front-month about $4180 on 13 Oct (Yahoo GC=F; see data_asof.json) | C11: about $4180 | D11: 2026-10-13 | E11: Yahoo Finance (GC=F) and metalcharts.org summary | F11: https://finance.yahoo.com/quote/GC=F | G11: 2026-10-14
A12: S11 | B12: IMF World Economic Outlook October 2026: world growth 3.1% (2026) and 3.4% (2027); global headline inflation 4.7% (2026) and 4.1% (2027); Middle East and Central Asia -0.3% in 2026; oil price assumption $95.74 (2026) | C12: 3.1% / 3.4% | D12: 2026-10-13 | E12: IMF WEO October 2026 (via AP and CNBC coverage) | F12: https://www.cnbc.com/2026/10/12/imf-world-bank-annual-meetings-october-bangkok-asia-.html | G12: 2026-10-14
... A17: S16 | B17: US income tax treaty list (no treaty with UAE or Saudi Arabia; statutory 30% withholding on US-source dividends applies to non-treaty residents) | C17: nan | D17: 2025-09-26 (Table 3) | E17: Internal Revenue Service | F17: https://www.irs.gov/businesses/international-businesses/united-states-income-tax-treaties-a-to-z | G17: 2026-10-14
